Workbook

Sheet Cover
B2: SPACEX
B3: Probabilistic Valuation Model — Q2 2026
B5: A bottoms-up, scenario-weighted view of SpaceX (post xAI merger), prior to IPO
B6: Horizons modelled: 5-year (through 2030) · 10-year (through 2035) · 20-year (through 2045)
B8: Author
B9: Dialectic
B11: Version
B12: vF · 5 June 2026
B14: Key context shaping this model
B15: • SpaceX–xAI merger closed 2 Feb 2026 at $1.25T combined valuation ($1T SpaceX + $250B xAI)
B16: • SpaceX IPO expected late June 2026 (S-1 filed May 2026)
B17: • Starshield Space Data Network contract awarded 26 May 2026 ($2.29B, Golden Dome backbone)
... B32: and should be treated as long-dated optionality, not base-case revenue. Not investment advice.

Sheet README
B2: Methodology & Conventions
B3: Read this once. The rest of the model assumes you have.
B5: Color conventions
B6: Blue text | C6: Hardcoded inputs you can edit to change the model
B7: Yellow background | C7: KEY inputs that have outsized effect on valuation — change with care
B8: Black text | C8: Formulas — do not overwrite unless you intend to break the model
B9: Green text | C9: Cross-sheet links pulling from another tab
B10: Gold fill | C10: Totals and headline outputs
B12: Scenario logic
B13: Three scenarios | C13: Bear / Base / Bull. Each with its own revenue path, EBITDA margin, and CapEx %.
B14: Scenario weights | C14: Per-line Bear/Base/Bull weights on Scenario_Engine; must sum to 100%.
B15: Probability of materialization | C15: Separate 0-100% input for each speculative line. Multiplies through.
B16: Expected free cash flow | C16: EV = scenario-weighted UFCF × materialization probability. This feeds DCF.
B18: Revenue construction
B19: Three-phase CAGR | C19: Each business line is modelled with three growth phases: ramp (2026-2030), mid (2031-2035), mature (2036-2045).
B20: Editable per scenario | C20: All three CAGRs are settable per scenario on each business-line tab.
B21: Starting revenue | C21: 2026 starting revenue is a hardcoded input per scenario.
B22: Waypoints visible | C22: Yellow-highlighted 2030/2035/2045 cells are the headline horizon outputs per scenario.
B24: Valuation method
B25: Discounted cash flow | C25: Unlevered FCF discounted at WACC. Terminal value via Gordon Growth.
B26: Enterprise → equity | C26: EV less net debt = equity value. Per-share at fully-diluted share count.
B27: Three horizons | C27: 5yr (terminal at end 2030), 10yr (end 2035), 20yr (end 2045) — all on Summary.
B28: Probability-weighted EV | C28: Final EV = Σ business lines × scenario × materialization.
B30: What this model is NOT
B31: Not predictive | C31: Outputs are conditional on assumptions you can challenge. Treat as a thinking tool.
B32: Not multiple-driven | C32: Public comps are weak for SpaceX. DCF is used because no good multiple exists.
B33: Not policy-aware | C33: Mars/Moon land sales face the 1967 Outer Space Treaty — kept at low probability.
B34: Not synergy-priced | C34: xAI cost/revenue synergies with SpaceX are modelled conservatively.

Sheet Thesis
B2: INVESTMENT THESIS
B3: SpaceX — Q2 2026 · what we are underwriting, what has to be true, what breaks it
B7: ONE-LINE THESIS
B8: SpaceX is actually 12 different current and near-term businesses backstopped by a pure monopoly on launch and LEO connectivity that is reinvesting its cash flows into — AI compute (Colossus), Orbital Data Centres (ODCs) and the Starship platform for interplanetary dominance. We believe that the business will return to cash-flow positive operating position in the short term and represents an incredibly compelling option on the inspiring future the constellation of space industries that are enabled by SpaceX's unique position. We also note the recently-closed merger with xAI (Feb 2026, $1.25T combined entity), which is highly strategic and synergistic and adds further short-term growth to this story.
B10: WHAT WE ARE UNDERWRITING | C10: WHAT HAS TO BE TRUE | D10: WHAT BREAKS THE THESIS
B11: Pillar 1 · STARLINK as the cash-flow engine | C11: Pillar 1 · STARLINK — conditions | D11: Pillar 1 · STARLINK — break points
B12: 10.3M subs, 9,600+ sats, 164 countries (S-1). Connectivity segment ran ~$13Bn run-rate Q1 2026 at Adj EBITDA mgn 64%. This is a $130-200Bn revenue business by 2030 with SaaS-like economics once satellite fleet is depreciated. Funds the rest of SpaceX. | C12: • ARPU floors at $40-50/month even as international mix grows. • Subs reach 50M+ by 2030 (5x current). • D2C (satellite-to-cell) adds incremental ARPU not cannibalises terrestrial. • Aviation/Maritime ($3Bn 2026 seed) converts to multi-billion stable enterprise revenue. • Margins hold above 60% as new gens of sats launch on Starship at lower unit cost. | D12: • Kuiper/AST/Chinese constellations force ARPU compression 30%+ within 5 years. • Spectrum disputes (FCC, ITU) limit constellation expansion. • D2C remains a one-carrier (T-Mobile) niche product. • Insurance/regulatory costs for LEO debris cleanup spike unit economics. • Geopolitical: countries ban Starlink in major markets (Brazil precedent).
B13: Pillar 2 · STARSHIP as the cost-down enabler | C13: Pillar 2 · STARSHIP — conditions | D13: Pillar 2 · STARSHIP — break points
B14: $3Bn R&D in 2025 alone (S-1). Starship unlocks Starlink v3 (more bandwidth/sat), HLS delivery (NASA), point-to-point earth travel, and Mars optionality. Without Starship, the 2030+ Starlink and lunar/Mars stories don't compound. | C14: • Orbital flight to commercial cadence by 2028 (currently end-2026 milestone slip risk). • Per-kg cost drops to <$200 (vs Falcon 9 ~$1,500). • Rapid reusability — hundreds of flights per booster. • NASA HLS milestones met on Artemis III/IV. | D14: • 24-month+ Starship slip. Cuts Starlink v3 economics. Forces Falcon 9 dependence. • Reusability breakthrough fails to materialise (each booster <10 flights). • HLS contract loss / cancellation under new administration. • Major Starship test failure with loss of life or environmental damage.
B15: Pillar 3 · AI / Colossus / xAI optionality | C15: Pillar 3 · AI — conditions | D15: Pillar 3 · AI — break points
B16: xAI (merged Feb 2026) and Colossus DC build-out. SpaceX captures Musk's compute infrastructure. Use of IPO proceeds explicitly includes 'AI compute infrastructure' per S-1. | C16: • Colossus captures ~25% of US frontier-model training spend by 2028. • xAI/Grok generates $10Bn+ revenue by 2028 (vs sub-$3Bn 2025). • Capex scale (1M GPU/yr per model assumption) is financeable without major dilution. • No regulatory action against vertically-integrated AI provider with major govt contracts. | D16: • AI capex cycle deflates (Nvidia/cloud overbuild thesis). • Open-source models or efficiency breakthroughs cut training compute demand 50%+. • Hyperscaler verticalisation (OpenAI/Anthropic in-house chips) squeezes 3rd-party compute providers. • Musk attention dilution event: xAI roadmap stalls.
B17: Pillar 4 · GOVT / STARSHIELD revenue moat | C17: Pillar 4 · GOVT — conditions | D17: Pillar 4 · GOVT — break points
B18: Starshield ($2.29Bn contract anchored May 2026), NASA HLS, USSF/NRO launches. Government revenue is contracted, recurring, and politically sticky once embedded in defence architecture. | C18: • Starshield contracts renew and expand at 18-32% margins. • USSF / NRO continues sole-source / preferred-vendor status. • ITAR/export controls don't tighten on dual-use Starlink/Starshield architecture. • Musk's relationship with sitting administration remains workable. | D18: • Blue Sweep in Nov-26 or Dem President could hold business back. Political event: Musk-administration breakdown leads to contract pulls (~30% of segment). • CFIUS review of foreign customer access. • Congressional antagonism wrt procurement practices. • Multi-vendor mandate forces competition (Northrop, RTX, Blue Origin take share).
B20: MODEL LEVERS — each thesis pillar maps to specific assumptions in the workbook
B21: Pillar | C21: Key model cell(s) | D21: What to watch
B22: Starlink cash flow | C22: Starlink_Consumer (Base 2026 rev $8B, ARPU $66, blended margin 50%) | D22: If consensus ARPU falls below $50 or subs growth stalls below 30% YoY, sense-check immediately.
B23: Starship economics | C23: Launch_Services + xAI funding capex schedule | D23: Orbital flight cadence test. Q4 2026 / Q1 2027 milestone risk.
B24: AI / Colossus + ODCs | C24: Colossus_DCs 2026 rev $16B + 1M GPU/yr mature assumption; xAI_Software | D24: Compare Colossus revenue to S-1 Connectivity Q1'26 ($3.3B). If 2026 actual < $10B, model assumption is too aggressive.
B25: Govt / Starshield | C25: Starshield (anchored to $2.29Bn May 2026 contract), NASA_Lunar HLS | D25: Renewal cadence; multi-vendor language in next NDAA / USSF procurement notices.
B26: Speculative tail | C26: PlanetX_Land, Asteroid_Mining, Mars_Moon, Lunar_Mfg, Orbital_DCs | D26: Treat as zero in base case. Only credit Bull scenarios. Re-run Comps with $251Bn removed for comparison.

Sheet Summary
C2: Summary — Headline Outputs
C3: Probability-weighted enterprise value, equity value, and per-share value across horizons
C5: Probability-weighted valuation by horizon
C6: Horizon | D6: Ent. Value ($M) | E6: Eq. Val ($M) | F6: Per Share ($) | G6: Implied EV ($B)
C7: 5-year | D7: =DCF!F13 -> 840458.19 | E7: =DCF!E19 -> 827199.19 | F7: =DCF!F19 -> 61.731282 | G7: =D7/1000 -> 840.45819
C8: 10-year | D8: =DCF!F14 -> 2685974 | E8: =DCF!E20 -> 2672715 | F8: =DCF!F20 -> 199.45634 | G8: =D8/1000 -> 2685.974
C9: 20-year | D9: =DCF!F15 -> 10191466 | E9: =DCF!E21 -> 10178207 | F9: =DCF!F21 -> 759.56771 | G9: =D9/1000 -> 10191.466
C10: Blended Fair Value | D10: =D7*$D$35+D8*$D$36+D9*$D$37 -> 2421489.5 | E10: =E7*$D$35+E8*$D$36+E9*$D$37 -> 2408230.5 | F10: =F7*$D$35+F8*$D$36+F9*$D$37 -> 179.7187 | G10: =G7*$D$35+G8*$D$36+G9*$D$37 -> 2421.4895
C12: Major Reference points
C13: Feb 2026 SpaceX–xAI merger valuation | D13: $1,250B | E13: Combined SpaceX ($1T) + xAI ($250B)
C14: 2026 implied IPO valuation range | D14: $1.5–2.0T | E14: Banker leaks; based on consensus $100+ IPO price × ~1.85B shares
C15: 2025 SpaceX revenue (actual) | D15: $18.7B | E15: +33% YoY; from S-1 filing
C16: 2025 SpaceX Adj EBITDA (actual) | D16: $6.6B | E16: From S-1 filing
C18: Probability-weighted revenue at horizon endpoints ($M)
C19: Business Line | D19: 2030 Revenue | E19: 2035 Revenue | F19: 2045 Revenue | G19: Notes
B20: 1 | C20: Launch Services & Lunar Vehicles | D20: ='P&L_Consolidated'!G7 -> 52361.288 | E20: ='P&L_Consolidated'!L7 -> 207734.38 | F20: ='P&L_Consolidated'!V7 -> 1753174.7 | G20: Falcon + Starship + HLS Artemis lunar lander
B21: 2 | C21: Crewed Spaceflight | D21: ='P&L_Consolidated'!G8 -> 6045.9067 | E21: ='P&L_Consolidated'!L8 -> 15716.949 | F21: ='P&L_Consolidated'!V8 -> 58265.392 | G21: NASA CCP/CRS + Polaris/Axiom + Starports/P2P (tourism/private merged)
B22: 3 | C22: Other Space Services | D22: ='P&L_Consolidated'!G9 -> 573.51036 | E22: ='P&L_Consolidated'!L9 -> 2180.3754 | F22: ='P&L_Consolidated'!V9 -> 15525.749 | G22: Satellite servicing + orbital tug + rocketry IP licensing or manufacture/sales
B23: 4 | C23: Starlink Connectivity (Consumer + Av/Mar) | D23: ='P&L_Consolidated'!G10 -> 63825.515 | E23: ='P&L_Consolidated'!L10 -> 249694.26 | F23: ='P&L_Consolidated'!V10 -> 989981.58 | G23: Residential + business + aviation + maritime broadband (merged connectivity)
B24: 5 | C24: Starlink Direct-to-Cell | D24: ='P&L_Consolidated'!G11 -> 9991.5116 | E24: ='P&L_Consolidated'!L11 -> 94139.592 | F24: ='P&L_Consolidated'!V11 -> 990791.62 | G24: Carrier deal scaling + spectrum policy
B25: 6 | C25: Starshield & Golden Dome (Defense) | D25: ='P&L_Consolidated'!G12 -> 15401.722 | E25: ='P&L_Consolidated'!L12 -> 59352.602 | F25: ='P&L_Consolidated'!V12 -> 325904.38 | G25: Defense contract pipeline (Golden Dome, NRO)
B26: 7 | C26: xAI Software (Grok + API) | D26: ='P&L_Consolidated'!G13 -> 12200.307 | E26: ='P&L_Consolidated'!L13 -> 65348.604 | F26: ='P&L_Consolidated'!V13 -> 326970.1 | G26: Grok subs, enterprise API revenue
B27: 8 | C27: Colossus Terrestrial Data Centres | D27: ='P&L_Consolidated'!G14 -> 68191.519 | E27: ='P&L_Consolidated'!L14 -> 219904.96 | F27: ='P&L_Consolidated'!V14 -> 797628.52 | G27: 1M GPU/yr × $30B per million mature pricing
B28: 9 | C28: Orbital Data Centres | D28: ='P&L_Consolidated'!G15 -> 0 | E28: ='P&L_Consolidated'!L15 -> 68340.86 | F28: ='P&L_Consolidated'!V15 -> 1960783.4 | G28: First commercial 2031 (base); long-dated
B29: 10 | C29: Deep Space Optionality | D29: ='P&L_Consolidated'!G16 -> 0 | E29: ='P&L_Consolidated'!L16 -> 45.939975 | F29: ='P&L_Consolidated'!V16 -> 110622.97 | G29: Lunar Mfg + Asteroid + Mars/Moon (long-dated optionality merged)
B30: 11 | C30: X Platform | D30: ='P&L_Consolidated'!G17 -> 15774.079 | E30: ='P&L_Consolidated'!L17 -> 45235.993 | F30: ='P&L_Consolidated'!V17 -> 227301.68 | G30: X.com social/ads/premium + Xmoney payments (merged)
B31: 12 | C31: Terafab — Semiconductor Manufacturing | D31: ='P&L_Consolidated'!G18 -> 0 | E31: ='P&L_Consolidated'!L18 -> 36020.876 | F31: ='P&L_Consolidated'!V18 -> 1085705.8 | G31: $55B chip fab; AI5/AI6 + D3; captive + 3P sales
C32: Total | D32: =SUM(D20:D31) -> 244365.36 | E32: =SUM(E20:E31) -> 1063715.4 | F32: =SUM(F20:F31) -> 8642655.9
C34: Horizon blending weights
C35: 5-year weight | D35: =Assumptions!C35 -> 0.55
C36: 10-year weight | D36: =Assumptions!C36 -> 0.35
C37: 20-year weight | D37: =Assumptions!C37 -> 0.1
C38: Sum (should = 100%) | D38: =SUM(D35:D37) -> 1

Sheet Sum of Parts
B2: Sum-of-the-Parts: SpaceX by Business Unit
B3: Per-segment PV of 10-year UFCF (2026–2035) + Gordon terminal value. WACC and g linked to Assumptions. Tiered by confidence — anchor businesses left, speculative right.
B5: WACC | C5: =Assumptions!C15 -> 0.0900375 | D5: Terminal g | E5: =Assumptions!C16 -> 0.04 | F5: Horizon | G5: 10yr (central)
B7: Tier | C7: Business Unit | D7: PV of UFCF (10yr, $M) | E7: PV of TV ($M) | F7: Segment EV (Base, $M) | G7: Bear EV ($M) | H7: Bull EV ($M) | I7: % of total Base | J7: S-1 anchored? | P7: Chart data (sorted: anchor → plausible → speculative) | U7: Cumulative build (sorted by Base EV descending) — rebuilt
P8: Segment | Q8: Bear EV | R8: Base EV | S8: Bull EV | U8: Segment | V8: Base EV ($Bn) | W8: Cumulative Base ($Bn) | X8: Bear EV ($Bn) | Y8: Cumulative Bear ($Bn) | Z8: Bull EV ($Bn) | AA8: Cumulative Bull ($Bn)
A9: 1 | B9: ANCHOR | C9: Launch Services & Lunar Vehicles | D9: =SUMPRODUCT(Launch_Services!C43:L43,$C$26:$L$26) -> 54862.628 | E9: =(Launch_Services!L43*(1+$E$5)/($C$5-$E$5))*$L$26 -> 269033.82 | F9: =D9+E9 -> 323896.45 | G9: =F9*IFERROR(Launch_Services!L30/MAX(0.001,Launch_Services!L31),0.7)*0.7 -> 76260.265 | H9: =F9*MIN(2,MAX(1,IFERROR(Launch_Services!L32/MAX(0.001,Launch_Services!L31),1.4)))*1.1 -> 712572.19 | I9: =F9/$F$21 -> 0.14351954 | J9: Yes | P9: Starlink Connectivity | Q9: =G10/1000 -> 83.699618 | R9: =F10/1000 -> 744.569 | S9: =H10/1000 -> 1638.0518 | U9: Starlink Connectivity | V9: =F10/1000 -> 744.569 | W9: =V9 -> 744.569 | X9: =G10/1000 -> 83.699618 | Y9: =X9 -> 83.699618 | Z9: =H10/1000 -> 1638.0518 | AA9: =Z9 -> 1638.0518
A10: 2 | B10: ANCHOR | C10: Starlink Connectivity | D10: =SUMPRODUCT(Starlink!C43:L43,$C$26:$L$26) -> 130980.71 | E10: =(Starlink!L43*(1+$E$5)/($C$5-$E$5))*$L$26 -> 613588.29 | F10: =D10+E10 -> 744569 | G10: =F10*IFERROR(Starlink!L30/MAX(0.001,Starlink!L31),0.7)*0.7 -> 83699.618 | H10: =F10*MIN(2,MAX(1,IFERROR(Starlink!L32/MAX(0.001,Starlink!L31),1.4)))*1.1 -> 1638051.8 | I10: =F10/$F$21 -> 0.32992087 | J10: Yes | P10: Starlink D2C | Q10: =G15/1000 -> 28.292797 | R10: =F15/1000 -> 379.86154 | S10: =H15/1000 -> 835.69539 | U10: Starlink D2C | V10: =F15/1000 -> 379.86154 | W10: =W9+V10 -> 1124.4305 | X10: =G15/1000 -> 28.292797 | Y10: =Y9+X10 -> 111.99241 | Z10: =H15/1000 -> 835.69539 | AA10: =AA9+Z10 -> 2473.7472
A11: 3 | B11: ANCHOR | C11: Starshield | D11: =SUMPRODUCT(Starshield!C43:L43,$C$26:$L$26) -> 34177.949 | E11: =(Starshield!L43*(1+$E$5)/($C$5-$E$5))*$L$26 -> 155878.84 | F11: =D11+E11 -> 190056.79 | G11: =F11*IFERROR(Starshield!L30/MAX(0.001,Starshield!L31),0.7)*0.7 -> 42070.067 | H11: =F11*MIN(2,MAX(1,IFERROR(Starshield!L32/MAX(0.001,Starshield!L31),1.4)))*1.1 -> 418124.94 | I11: =F11/$F$21 -> 0.084214763 | J11: Yes | P11: Launch Services | Q11: =G9/1000 -> 76.260265 | R11: =F9/1000 -> 323.89645 | S11: =H9/1000 -> 712.57219 | U11: Launch Services | V11: =F9/1000 -> 323.89645 | W11: =W10+V11 -> 1448.327 | X11: =G9/1000 -> 76.260265 | Y11: =Y10+X11 -> 188.25268 | Z11: =H9/1000 -> 712.57219 | AA11: =AA10+Z11 -> 3186.3194
A12: 4 | B12: ANCHOR | C12: xAI Software | D12: =SUMPRODUCT(xAI_Software!C43:L43,$C$26:$L$26) -> 13442.087 | E12: =(xAI_Software!L43*(1+$E$5)/($C$5-$E$5))*$L$26 -> 72503.162 | F12: =D12+E12 -> 85945.249 | G12: =F12*IFERROR(xAI_Software!L30/MAX(0.001,xAI_Software!L31),0.7)*0.7 -> 13413.769 | H12: =F12*MIN(2,MAX(1,IFERROR(xAI_Software!L32/MAX(0.001,xAI_Software!L31),1.4)))*1.1 -> 189079.55 | I12: =F12/$F$21 -> 0.038082611 | J12: Yes | P12: Colossus DCs | Q12: =G13/1000 -> 58.817416 | R12: =F13/1000 -> 328.72532 | S12: =H13/1000 -> 723.1957 | U12: Colossus DCs | V12: =F13/1000 -> 328.72532 | W12: =W11+V12 -> 1777.0523 | X12: =G13/1000 -> 58.817416 | Y12: =Y11+X12 -> 247.0701 | Z12: =H13/1000 -> 723.1957 | AA12: =AA11+Z12 -> 3909.5151
A13: 5 | B13: ANCHOR | C13: Colossus DCs | D13: =SUMPRODUCT(Colossus_DCs!C43:L43,$C$26:$L$26) -> 60527.583 | E13: =(Colossus_DCs!L43*(1+$E$5)/($C$5-$E$5))*$L$26 -> 268197.74 | F13: =D13+E13 -> 328725.32 | G13: =F13*IFERROR(Colossus_DCs!L30/MAX(0.001,Colossus_DCs!L31),0.7)*0.7 -> 58817.416 | H13: =F13*MIN(2,MAX(1,IFERROR(Colossus_DCs!L32/MAX(0.001,Colossus_DCs!L31),1.4)))*1.1 -> 723195.7 | I13: =F13/$F$21 -> 0.14565923 | J13: Yes | P13: Starshield | Q13: =G11/1000 -> 42.070067 | R13: =F11/1000 -> 190.05679 | S13: =H11/1000 -> 418.12494 | U13: Starshield | V13: =F11/1000 -> 190.05679 | W13: =W12+V13 -> 1967.1091 | X13: =G11/1000 -> 42.070067 | Y13: =Y12+X13 -> 289.14016 | Z13: =H11/1000 -> 418.12494 | AA13: =AA12+Z13 -> 4327.64
A14: 6 | B14: ANCHOR | C14: Crewed Spaceflight | D14: =SUMPRODUCT('Crewed Trips'!C43:L43,$C$26:$L$26) -> 14714.373 | E14: =('Crewed Trips'!L43*(1+$E$5)/($C$5-$E$5))*$L$26 -> 48774.974 | F14: =D14+E14 -> 63489.348 | G14: =F14*IFERROR('Crewed Trips'!L30/MAX(0.001,'Crewed Trips'!L31),0.7)*0.7 -> 6968.9925 | H14: =F14*MIN(2,MAX(1,IFERROR('Crewed Trips'!L32/MAX(0.001,'Crewed Trips'!L31),1.4)))*1.1 -> 139676.56 | I14: =F14/$F$21 -> 0.02813233 | J14: Yes | P14: xAI Software | Q14: =G12/1000 -> 13.413769 | R14: =F12/1000 -> 85.945249 | S14: =H12/1000 -> 189.07955 | U14: xAI Software | V14: =F12/1000 -> 85.945249 | W14: =W13+V14 -> 2053.0544 | X14: =G12/1000 -> 13.413769 | Y14: =Y13+X14 -> 302.55393 | Z14: =H12/1000 -> 189.07955 | AA14: =AA13+Z14 -> 4516.7196
A15: 7 | B15: PLAUSIBLE | C15: Starlink D2C | D15: =SUMPRODUCT(Starlink_D2C!C43:L43,$C$26:$L$26) -> 47415.05 | E15: =(Starlink_D2C!L43*(1+$E$5)/($C$5-$E$5))*$L$26 -> 332446.49 | F15: =D15+E15 -> 379861.54 | G15: =F15*IFERROR(Starlink_D2C!L30/MAX(0.001,Starlink_D2C!L31),0.7)*0.7 -> 28292.797 | H15: =F15*MIN(2,MAX(1,IFERROR(Starlink_D2C!L32/MAX(0.001,Starlink_D2C!L31),1.4)))*1.1 -> 835695.39 | I15: =F15/$F$21 -> 0.16831785 | J15: Yes (T-Mobile) | P15: Crewed Spaceflight | Q15: =G14/1000 -> 6.9689925 | R15: =F14/1000 -> 63.489348 | S15: =H14/1000 -> 139.67656 | U15: Crewed Spaceflight | V15: =F14/1000 -> 63.489348 | W15: =W14+V15 -> 2116.5437 | X15: =G14/1000 -> 6.9689925 | Y15: =Y14+X15 -> 309.52292 | Z15: =H14/1000 -> 139.67656 | AA15: =AA14+Z15 -> 4656.3961
A16: 8 | B16: PLAUSIBLE | C16: Other Space Services | D16: =SUMPRODUCT(Other_Services!C43:L43,$C$26:$L$26) -> 1118.0775 | E16: =(Other_Services!L43*(1+$E$5)/($C$5-$E$5))*$L$26 -> 4989.8954 | F16: =D16+E16 -> 6107.9729 | G16: =F16*IFERROR(Other_Services!L30/MAX(0.001,Other_Services!L31),0.7)*0.7 -> 497.29509 | H16: =F16*MIN(2,MAX(1,IFERROR(Other_Services!L32/MAX(0.001,Other_Services!L31),1.4)))*1.1 -> 13437.54 | I16: =F16/$F$21 -> 0.0027064621 | J16: Satellite service + orbital tug + Rocketry IP license | P16: Terafab | Q16: =G18/1000 -> 6.2297376 | R16: =F18/1000 -> 53.956821 | S16: =H18/1000 -> 118.70501 | U16: Terafab | V16: =F18/1000 -> 53.956821 | W16: =W15+V16 -> 2170.5005 | X16: =G18/1000 -> 6.2297376 | Y16: =Y15+X16 -> 315.75266 | Z16: =H18/1000 -> 118.70501 | AA16: =AA15+Z16 -> 4775.1012
A17: 9 | B17: PLAUSIBLE | C17: X Platform | D17: =SUMPRODUCT('X Platform'!C43:L43,$C$26:$L$26) -> 10371.258 | E17: =('X Platform'!L43*(1+$E$5)/($C$5-$E$5))*$L$26 -> 43103.677 | F17: =D17+E17 -> 53474.934 | G17: =F17*IFERROR('X Platform'!L30/MAX(0.001,'X Platform'!L31),0.7)*0.7 -> 7846.3845 | H17: =F17*MIN(2,MAX(1,IFERROR('X Platform'!L32/MAX(0.001,'X Platform'!L31),1.4)))*1.1 -> 117644.86 | I17: =F17/$F$21 -> 0.023694912 | J17: Yes (Conn. seg.) | P17: X Platform | Q17: =G17/1000 -> 7.8463845 | R17: =F17/1000 -> 53.474934 | S17: =H17/1000 -> 117.64486 | U17: X Platform | V17: =F17/1000 -> 53.474934 | W17: =W16+V17 -> 2223.9755 | X17: =G17/1000 -> 7.8463845 | Y17: =Y16+X17 -> 323.59905 | Z17: =H17/1000 -> 117.64486 | AA17: =AA16+Z17 -> 4892.746
A18: 10 | B18: PLAUSIBLE | C18: Terafab — Semiconductor Manufacturing | D18: =SUMPRODUCT(Terafab!C43:L43,$C$26:$L$26) -> 5193.8734 | E18: =(Terafab!L43*(1+$E$5)/($C$5-$E$5))*$L$26 -> 48762.948 | F18: =D18+E18 -> 53956.821 | G18: =F18*IFERROR(Terafab!L30/MAX(0.001,Terafab!L31),0.7)*0.7 -> 6229.7376 | H18: =F18*MIN(2,MAX(1,IFERROR(Terafab!L32/MAX(0.001,Terafab!L31),1.4)))*1.1 -> 118705.01 | I18: =F18/$F$21 -> 0.023908438 | J18: Adjacent (Tesla) | P18: Orbital DCs | Q18: =G19/1000 -> 2.3282476 | R18: =F19/1000 -> 26.711956 | S18: =H19/1000 -> 77.017301 | U18: Orbital DCs | V18: =F19/1000 -> 26.711956 | W18: =W17+V18 -> 2250.6874 | X18: =G19/1000 -> 2.3282476 | Y18: =Y17+X18 -> 325.92729 | Z18: =H19/1000 -> 77.017301 | AA18: =AA17+Z18 -> 4969.7633
A19: 11 | B19: SPECULATIVE | C19: Orbital DCs | D19: =SUMPRODUCT(Orbital_DCs!C43:L43,$C$26:$L$26) -> 2016.1022 | E19: =(Orbital_DCs!L43*(1+$E$5)/($C$5-$E$5))*$L$26 -> 24695.854 | F19: =D19+E19 -> 26711.956 | G19: =F19*IFERROR(Orbital_DCs!L30/MAX(0.001,Orbital_DCs!L31),0.5)*0.4 -> 2328.2476 | H19: =F19*MIN(3,MAX(1,IFERROR(Orbital_DCs!L32/MAX(0.001,Orbital_DCs!L31),2)))*1.2 -> 77017.301 | I19: =F19/$F$21 -> 0.011836152 | J19: No | P19: Other Space Services | Q19: =G16/1000 -> 0.49729509 | R19: =F16/1000 -> 6.1079729 | S19: =H16/1000 -> 13.43754 | U19: Other Space Services | V19: =F16/1000 -> 6.1079729 | W19: =W18+V19 -> 2256.7954 | X19: =G16/1000 -> 0.49729509 | Y19: =Y18+X19 -> 326.42459 | Z19: =H16/1000 -> 13.43754 | AA19: =AA18+Z19 -> 4983.2008
A20: 12 | B20: SPECULATIVE | C20: Deep Space Optionality | D20: =SUMPRODUCT('Deep Space Option'!C43:L43,$C$26:$L$26) -> 2.2759525 | E20: =('Deep Space Option'!L43*(1+$E$5)/($C$5-$E$5))*$L$26 -> 13.181843 | F20: =D20+E20 -> 15.457795 | G20: =F20*IFERROR('Deep Space Option'!L30/MAX(0.001,'Deep Space Option'!L31),0.5)*0.4 -> 1.7110895 | H20: =F20*MIN(3,MAX(1,IFERROR('Deep Space Option'!L32/MAX(0.001,'Deep Space Option'!L31),2)))*1.2 -> 55.648062 | I20: =F20/$F$21 -> 6.8493977e-06 | J20: Lunar Mfg + Asteroid + Mars/Moon (LT optionality) | P20: Deep Space Optionality | Q20: =G20/1000 -> 0.0017110895 | R20: =F20/1000 -> 0.015457795 | S20: =H20/1000 -> 0.055648062 | U20: Deep Space Optionality | V20: =F20/1000 -> 0.015457795 | W20: =W19+V20 -> 2256.8108 | X20: =G20/1000 -> 0.0017110895 | Y20: =Y19+X20 -> 326.4263 | Z20: =H20/1000 -> 0.055648062 | AA20: =AA19+Z20 -> 4983.2565
B21: TOTAL SOTP | C21: Enterprise Value (SOTP, 10yr) | D21: =SUM(D9:D20) -> 374821.97 | E21: =SUM(E9:E20) -> 1881988.9 | F21: =SUM(F9:F20) -> 2256810.8 | G21: =SUM(G9:G20) -> 326426.3 | H21: =SUM(H9:H20) -> 4983256.5 | I21: =SUM(I9:I20) -> 1
F23: Amount ($M)
B24: Discount factor (10yr) | L24: Year offsets used in PV calcs (1–10). Hidden helper.
B25: Year # | C25: 1 | D25: 2 | E25: 3 | F25: 4 | G25: 5 | H25: 6 | I25: 7 | J25: 8 | K25: 9 | L25: 10
B26: Disc factor | C26: =1/(1+$C$5)^C25 -> 0.91739963 | D26: =1/(1+$C$5)^D25 -> 0.84162208 | E26: =1/(1+$C$5)^E25 -> 0.77210379 | F26: =1/(1+$C$5)^F25 -> 0.70832773 | G26: =1/(1+$C$5)^G25 -> 0.6498196 | H26: =1/(1+$C$5)^H25 -> 0.59614426 | I26: =1/(1+$C$5)^I25 -> 0.54690252 | J26: =1/(1+$C$5)^J25 -> 0.50172817 | ... L26: =1/(1+$C$5)^L25 -> 0.42226551
B28: RECONCILIATION: SoTP → DCF (10-yr horizon, $M)
B29: Bridge component | C29: Source / formula | F29: Amount ($M)
B30: SoTP base (raw UFCF + TV) | C30: Sum of segment PV(UFCF) + PV(TV) on segment row 43 | F30: =F21 -> 2256810.8
B31: (+) D&A tax shield | C31: PV of (D&A × tax) + PV of TV on year-10 D&A — corporate-level in DCF | F31: =SUMPRODUCT(DCF!C43:L43,DCF!C8:L8)+(DCF!L43*(1+Assumptions!$C$16)/(Assumptions!$C$15-Assumptions!$C$16))*DCF!L8 -> 286216.31
B32: (+) NOL utilisation benefit | C32: PV of (NOL used × tax) — one-shot 2026–27, then exhausted | F32: =SUMPRODUCT(DCF!C49:L49,DCF!C8:L8) -> 4726.9676
B33: (−) ΔNWC drag | C33: PV of ΔNWC — working capital investment as revenue scales | F33: =SUMPRODUCT(DCF!C45:L45,DCF!C8:L8)+(DCF!L45*(1+Assumptions!$C$16)/(Assumptions!$C$15-Assumptions!$C$16))*DCF!L8 -> -91464.872
B34: (+) Segment → Consolidated UFCF (PV of flows) | C34: PV of consolidated UFCF (P&L row 52) minus sum of segment PV(UFCF). Captures overhead/eliminations not in segment tabs. | F34: =SUMPRODUCT(DCF!C9:L9)-'Sum of Parts'!D21 -> 50314.183
B35: (+) Segment → Consolidated UFCF (terminal value) | C35: TV using consolidated year-10 UFCF (DCF!L7) minus SoTP TV using sum of segment year-10 UFCF. Same overhead/elimination effect, capitalised into perpetuity. | F35: =(DCF!L7*(1+Assumptions!$C$16)/(Assumptions!$C$15-Assumptions!$C$16))*DCF!L8-'Sum of Parts'!E21 -> 179370.58
B36: DCF EV (Adjusted UFCF, 10yr) | C36: Should approximate DCF!F14 | F36: =F30+F31+F32+F33+F34+F35 -> 2685974
B37: DCF EV (reference, from DCF!F14) | F37: =DCF!F14 -> 2685974
B38: Residual (rounding / unidentified) | F38: =F37-F36 -> 0

Sheet DCF
B2: Discounted Cash Flow
B3: Three horizons. EV at 2026 = PV of projected UFCF + PV of terminal value.
B5: Year | C5: 2026 | D5: 2027 | E5: 2028 | F5: 2029 | G5: 2030 | H5: 2031 | I5: 2032 | J5: 2033 | K5: 2034 | L5: 2035 | M5: 2036 | N5: 2037 | O5: 2038 | P5: 2039 | Q5: 2040 | R5: 2041 | S5: 2042 | T5: 2043 | U5: 2044 | V5: 2045
B6: Period (t, from 2026) | C6: 1 | D6: 2 | E6: 3 | F6: 4 | G6: 5 | H6: 6 | I6: 7 | J6: 8 | K6: 9 | L6: 10 | M6: 11 | N6: 12 | O6: 13 | P6: 14 | Q6: 15 | R6: 16 | S6: 17 | T6: 18 | U6: 19 | V6: 20
B7: UFCF ($M, prob-weighted) | C7: ='P&L_Consolidated'!C52 -> 10001.628 | D7: ='P&L_Consolidated'!D52 -> 14853.238 | E7: ='P&L_Consolidated'!E52 -> 22190.225 | F7: ='P&L_Consolidated'!F52 -> 33361.11 | G7: ='P&L_Consolidated'!G52 -> 50494.52 | H7: ='P&L_Consolidated'!H52 -> 67758.755 | I7: ='P&L_Consolidated'!I52 -> 91324.912 | J7: ='P&L_Consolidated'!J52 -> 123992.55 | ... V7: ='P&L_Consolidated'!V52 -> 1887737.3
B8: Discount factor at WACC | C8: =1/(1+Assumptions!$C$15)^C6 -> 0.91739963 | D8: =1/(1+Assumptions!$C$15)^D6 -> 0.84162208 | E8: =1/(1+Assumptions!$C$15)^E6 -> 0.77210379 | F8: =1/(1+Assumptions!$C$15)^F6 -> 0.70832773 | G8: =1/(1+Assumptions!$C$15)^G6 -> 0.6498196 | H8: =1/(1+Assumptions!$C$15)^H6 -> 0.59614426 | I8: =1/(1+Assumptions!$C$15)^I6 -> 0.54690252 | J8: =1/(1+Assumptions!$C$15)^J6 -> 0.50172817 | ... V8: =1/(1+Assumptions!$C$15)^V6 -> 0.17830816
B9: PV of UFCF ($M) | C9: =C7*C8 -> 9175.4897 | D9: =D7*D8 -> 12500.813 | E9: =E7*E8 -> 17133.156 | F9: =F7*F8 -> 23630.599 | G9: =G7*G8 -> 32812.328 | H9: =H7*H8 -> 40393.993 | I9: =I7*I8 -> 49945.825 | J9: =J7*J8 -> 62210.557 | ... V9: =V7*V8 -> 336598.97
B11: Enterprise value by horizon ($M)
B12: Horizon | C12: Years modeled | D12: PV of UFCFs ($M) | E12: Terminal value (PV, $M) | F12: Enterprise Value ($M)
B13: 5-year | C13: 2026-2030 | D13: =SUM(C53:G53) -> 106628.21 | E13: =(G52*(1+Assumptions!$C$16)/(Assumptions!$C$15-Assumptions!$C$16))*G8 -> 733829.97 | F13: =D13+E13 -> 840458.19
B14: 10-year | C14: 2026-2035 | D14: =SUM(C53:L53) -> 463446.04 | E14: =(L52*(1+Assumptions!$C$16)/(Assumptions!$C$15-Assumptions!$C$16))*L8 -> 2222528 | F14: =D14+E14 -> 2685974
B15: 20-year | C15: 2026-2045 | D15: =SUM(C53:V53) -> 2597483.2 | E15: =(V52*(1+Assumptions!$C$16)/(Assumptions!$C$15-Assumptions!$C$16))*V8 -> 7593983.1 | F15: =D15+E15 -> 10191466
B17: Enterprise → equity bridge ($M, except per share)
B18: Horizon | C18: EV ($M) | D18: Less: Net debt | E18: Equity value ($M) | F18: Per share ($)
B19: 5-year | C19: =F13 -> 840458.19 | D19: =Assumptions!$C$22 -> 13259 | E19: =C19-D19 -> 827199.19 | F19: =E19/Assumptions!$C$25 -> 61.731282
B20: 10-year | C20: =F14 -> 2685974 | D20: =Assumptions!$C$22 -> 13259 | E20: =C20-D20 -> 2672715 | F20: =E20/Assumptions!$C$25 -> 199.45634
B21: 20-year | C21: =F15 -> 10191466 | D21: =Assumptions!$C$22 -> 13259 | E21: =C21-D21 -> 10178207 | F21: =E21/Assumptions!$C$25 -> 759.56771
B23: Sensitivity: 10-year horizon Equity per share — WACC vs Terminal growth (centred on base case WACC 9.0% × g 4.0%, highlighted)
B24: WACC ↓ / Terminal g → | C24: 0.03 | D24: 0.035 | E24: 0.04 | F24: 0.045 | G24: 0.05
B25: 0.075 | C25: =($C$52/(1+$B25)^1+$D$52/(1+$B25)^2+$E$52/(1+$B25)^3+$F$52/(1+$B25)^4+$G$52/(1+$B25)^5+$H$52/(1+$B25)^6+$I$52/(1+$B25)^7+$J$52/(1+$B25)^8+$K$52/(1+$B25)^9+$L$52/(1+$B25)^10+$L$52*(1+C$24)/($B25-C$24)/(1+$B25)^10-Assumptions!$C$22)/Assumptions!$C$25 -> 247.1886 | D25: =($C$52/(1+$B25)^1+$D$52/(1+$B25)^2+$E$52/(1+$B25)^3+$F$52/(1+$B25)^4+$G$52/(1+$B25)^5+$H$52/(1+$B25)^6+$I$52/(1+$B25)^7+$J$52/(1+$B25)^8+$K$52/(1+$B25)^9+$L$52/(1+$B25)^10+$L$52*(1+D$24)/($B25-D$24)/(1+$B25)^10-Assumptions!$C$22)/Assumptions!$C$25 -> 274.56904 | E25: =($C$52/(1+$B25)^1+$D$52/(1+$B25)^2+$E$52/(1+$B25)^3+$F$52/(1+$B25)^4+$G$52/(1+$B25)^5+$H$52/(1+$B25)^6+$I$52/(1+$B25)^7+$J$52/(1+$B25)^8+$K$52/(1+$B25)^9+$L$52/(1+$B25)^10+$L$52*(1+E$24)/($B25-E$24)/(1+$B25)^10-Assumptions!$C$22)/Assumptions!$C$25 -> 309.77247 | F25: =($C$52/(1+$B25)^1+$D$52/(1+$B25)^2+$E$52/(1+$B25)^3+$F$52/(1+$B25)^4+$G$52/(1+$B25)^5+$H$52/(1+$B25)^6+$I$52/(1+$B25)^7+$J$52/(1+$B25)^8+$K$52/(1+$B25)^9+$L$52/(1+$B25)^10+$L$52*(1+F$24)/($B25-F$24)/(1+$B25)^10-Assumptions!$C$22)/Assumptions!$C$25 -> 356.71036 | G25: =($C$52/(1+$B25)^1+$D$52/(1+$B25)^2+$E$52/(1+$B25)^3+$F$52/(1+$B25)^4+$G$52/(1+$B25)^5+$H$52/(1+$B25)^6+$I$52/(1+$B25)^7+$J$52/(1+$B25)^8+$K$52/(1+$B25)^9+$L$52/(1+$B25)^10+$L$52*(1+G$24)/($B25-G$24)/(1+$B25)^10-Assumptions!$C$22)/Assumptions!$C$25 -> 422.42342
B26: 0.0825 | C26: =($C$52/(1+$B26)^1+$D$52/(1+$B26)^2+$E$52/(1+$B26)^3+$F$52/(1+$B26)^4+$G$52/(1+$B26)^5+$H$52/(1+$B26)^6+$I$52/(1+$B26)^7+$J$52/(1+$B26)^8+$K$52/(1+$B26)^9+$L$52/(1+$B26)^10+$L$52*(1+C$24)/($B26-C$24)/(1+$B26)^10-Assumptions!$C$22)/Assumptions!$C$25 -> 203.21065 | D26: =($C$52/(1+$B26)^1+$D$52/(1+$B26)^2+$E$52/(1+$B26)^3+$F$52/(1+$B26)^4+$G$52/(1+$B26)^5+$H$52/(1+$B26)^6+$I$52/(1+$B26)^7+$J$52/(1+$B26)^8+$K$52/(1+$B26)^9+$L$52/(1+$B26)^10+$L$52*(1+D$24)/($B26-D$24)/(1+$B26)^10-Assumptions!$C$22)/Assumptions!$C$25 -> 221.77522 | E26: =($C$52/(1+$B26)^1+$D$52/(1+$B26)^2+$E$52/(1+$B26)^3+$F$52/(1+$B26)^4+$G$52/(1+$B26)^5+$H$52/(1+$B26)^6+$I$52/(1+$B26)^7+$J$52/(1+$B26)^8+$K$52/(1+$B26)^9+$L$52/(1+$B26)^10+$L$52*(1+E$24)/($B26-E$24)/(1+$B26)^10-Assumptions!$C$22)/Assumptions!$C$25 -> 244.70793 | F26: =($C$52/(1+$B26)^1+$D$52/(1+$B26)^2+$E$52/(1+$B26)^3+$F$52/(1+$B26)^4+$G$52/(1+$B26)^5+$H$52/(1+$B26)^6+$I$52/(1+$B26)^7+$J$52/(1+$B26)^8+$K$52/(1+$B26)^9+$L$52/(1+$B26)^10+$L$52*(1+F$24)/($B26-F$24)/(1+$B26)^10-Assumptions!$C$22)/Assumptions!$C$25 -> 273.75603 | G26: =($C$52/(1+$B26)^1+$D$52/(1+$B26)^2+$E$52/(1+$B26)^3+$F$52/(1+$B26)^4+$G$52/(1+$B26)^5+$H$52/(1+$B26)^6+$I$52/(1+$B26)^7+$J$52/(1+$B26)^8+$K$52/(1+$B26)^9+$L$52/(1+$B26)^10+$L$52*(1+G$24)/($B26-G$24)/(1+$B26)^10-Assumptions!$C$22)/Assumptions!$C$25 -> 311.74201
B27: 0.09 | C27: =($C$52/(1+$B27)^1+$D$52/(1+$B27)^2+$E$52/(1+$B27)^3+$F$52/(1+$B27)^4+$G$52/(1+$B27)^5+$H$52/(1+$B27)^6+$I$52/(1+$B27)^7+$J$52/(1+$B27)^8+$K$52/(1+$B27)^9+$L$52/(1+$B27)^10+$L$52*(1+C$24)/($B27-C$24)/(1+$B27)^10-Assumptions!$C$22)/Assumptions!$C$25 -> 170.64245 | D27: =($C$52/(1+$B27)^1+$D$52/(1+$B27)^2+$E$52/(1+$B27)^3+$F$52/(1+$B27)^4+$G$52/(1+$B27)^5+$H$52/(1+$B27)^6+$I$52/(1+$B27)^7+$J$52/(1+$B27)^8+$K$52/(1+$B27)^9+$L$52/(1+$B27)^10+$L$52*(1+D$24)/($B27-D$24)/(1+$B27)^10-Assumptions!$C$22)/Assumptions!$C$25 -> 183.82613 | E27: =($C$52/(1+$B27)^1+$D$52/(1+$B27)^2+$E$52/(1+$B27)^3+$F$52/(1+$B27)^4+$G$52/(1+$B27)^5+$H$52/(1+$B27)^6+$I$52/(1+$B27)^7+$J$52/(1+$B27)^8+$K$52/(1+$B27)^9+$L$52/(1+$B27)^10+$L$52*(1+E$24)/($B27-E$24)/(1+$B27)^10-Assumptions!$C$22)/Assumptions!$C$25 -> 199.64655 | F27: =($C$52/(1+$B27)^1+$D$52/(1+$B27)^2+$E$52/(1+$B27)^3+$F$52/(1+$B27)^4+$G$52/(1+$B27)^5+$H$52/(1+$B27)^6+$I$52/(1+$B27)^7+$J$52/(1+$B27)^8+$K$52/(1+$B27)^9+$L$52/(1+$B27)^10+$L$52*(1+F$24)/($B27-F$24)/(1+$B27)^10-Assumptions!$C$22)/Assumptions!$C$25 -> 218.98262 | G27: =($C$52/(1+$B27)^1+$D$52/(1+$B27)^2+$E$52/(1+$B27)^3+$F$52/(1+$B27)^4+$G$52/(1+$B27)^5+$H$52/(1+$B27)^6+$I$52/(1+$B27)^7+$J$52/(1+$B27)^8+$K$52/(1+$B27)^9+$L$52/(1+$B27)^10+$L$52*(1+G$24)/($B27-G$24)/(1+$B27)^10-Assumptions!$C$22)/Assumptions!$C$25 -> 243.1527
B28: 0.0975 | C28: =($C$52/(1+$B28)^1+$D$52/(1+$B28)^2+$E$52/(1+$B28)^3+$F$52/(1+$B28)^4+$G$52/(1+$B28)^5+$H$52/(1+$B28)^6+$I$52/(1+$B28)^7+$J$52/(1+$B28)^8+$K$52/(1+$B28)^9+$L$52/(1+$B28)^10+$L$52*(1+C$24)/($B28-C$24)/(1+$B28)^10-Assumptions!$C$22)/Assumptions!$C$25 -> 145.65694 | D28: =($C$52/(1+$B28)^1+$D$52/(1+$B28)^2+$E$52/(1+$B28)^3+$F$52/(1+$B28)^4+$G$52/(1+$B28)^5+$H$52/(1+$B28)^6+$I$52/(1+$B28)^7+$J$52/(1+$B28)^8+$K$52/(1+$B28)^9+$L$52/(1+$B28)^10+$L$52*(1+D$24)/($B28-D$24)/(1+$B28)^10-Assumptions!$C$22)/Assumptions!$C$25 -> 155.35231 | E28: =($C$52/(1+$B28)^1+$D$52/(1+$B28)^2+$E$52/(1+$B28)^3+$F$52/(1+$B28)^4+$G$52/(1+$B28)^5+$H$52/(1+$B28)^6+$I$52/(1+$B28)^7+$J$52/(1+$B28)^8+$K$52/(1+$B28)^9+$L$52/(1+$B28)^10+$L$52*(1+E$24)/($B28-E$24)/(1+$B28)^10-Assumptions!$C$22)/Assumptions!$C$25 -> 166.73383 | F28: =($C$52/(1+$B28)^1+$D$52/(1+$B28)^2+$E$52/(1+$B28)^3+$F$52/(1+$B28)^4+$G$52/(1+$B28)^5+$H$52/(1+$B28)^6+$I$52/(1+$B28)^7+$J$52/(1+$B28)^8+$K$52/(1+$B28)^9+$L$52/(1+$B28)^10+$L$52*(1+F$24)/($B28-F$24)/(1+$B28)^10-Assumptions!$C$22)/Assumptions!$C$25 -> 180.28327 | G28: =($C$52/(1+$B28)^1+$D$52/(1+$B28)^2+$E$52/(1+$B28)^3+$F$52/(1+$B28)^4+$G$52/(1+$B28)^5+$H$52/(1+$B28)^6+$I$52/(1+$B28)^7+$J$52/(1+$B28)^8+$K$52/(1+$B28)^9+$L$52/(1+$B28)^10+$L$52*(1+G$24)/($B28-G$24)/(1+$B28)^10-Assumptions!$C$22)/Assumptions!$C$25 -> 196.68522
B29: 0.105 | C29: =($C$52/(1+$B29)^1+$D$52/(1+$B29)^2+$E$52/(1+$B29)^3+$F$52/(1+$B29)^4+$G$52/(1+$B29)^5+$H$52/(1+$B29)^6+$I$52/(1+$B29)^7+$J$52/(1+$B29)^8+$K$52/(1+$B29)^9+$L$52/(1+$B29)^10+$L$52*(1+C$24)/($B29-C$24)/(1+$B29)^10-Assumptions!$C$22)/Assumptions!$C$25 -> 125.95939 | D29: =($C$52/(1+$B29)^1+$D$52/(1+$B29)^2+$E$52/(1+$B29)^3+$F$52/(1+$B29)^4+$G$52/(1+$B29)^5+$H$52/(1+$B29)^6+$I$52/(1+$B29)^7+$J$52/(1+$B29)^8+$K$52/(1+$B29)^9+$L$52/(1+$B29)^10+$L$52*(1+D$24)/($B29-D$24)/(1+$B29)^10-Assumptions!$C$22)/Assumptions!$C$25 -> 133.28712 | E29: =($C$52/(1+$B29)^1+$D$52/(1+$B29)^2+$E$52/(1+$B29)^3+$F$52/(1+$B29)^4+$G$52/(1+$B29)^5+$H$52/(1+$B29)^6+$I$52/(1+$B29)^7+$J$52/(1+$B29)^8+$K$52/(1+$B29)^9+$L$52/(1+$B29)^10+$L$52*(1+E$24)/($B29-E$24)/(1+$B29)^10-Assumptions!$C$22)/Assumptions!$C$25 -> 141.74219 | F29: =($C$52/(1+$B29)^1+$D$52/(1+$B29)^2+$E$52/(1+$B29)^3+$F$52/(1+$B29)^4+$G$52/(1+$B29)^5+$H$52/(1+$B29)^6+$I$52/(1+$B29)^7+$J$52/(1+$B29)^8+$K$52/(1+$B29)^9+$L$52/(1+$B29)^10+$L$52*(1+F$24)/($B29-F$24)/(1+$B29)^10-Assumptions!$C$22)/Assumptions!$C$25 -> 151.60643 | G29: =($C$52/(1+$B29)^1+$D$52/(1+$B29)^2+$E$52/(1+$B29)^3+$F$52/(1+$B29)^4+$G$52/(1+$B29)^5+$H$52/(1+$B29)^6+$I$52/(1+$B29)^7+$J$52/(1+$B29)^8+$K$52/(1+$B29)^9+$L$52/(1+$B29)^10+$L$52*(1+G$24)/($B29-G$24)/(1+$B29)^10-Assumptions!$C$22)/Assumptions!$C$25 -> 163.26418
B31: FCF Adjustments — NOL, D&A tax shield, ΔNWC
B32: Original UFCF taxes EBITDA at 21% and has no D&A add-back or working-capital line. Below converts to proper unlevered FCF.
B34: Adjustment Drivers
B35: D&A as % of revenue (blended) | C35: 0.12
B36: NWC as % of revenue (blended) | C36: 0.03
B37: Opening NOL stock ($M) | C37: 25000
B38: NOL utilisation cap (post-TCJA) | C38: 0.8
B40: Adjustment time series
B41: Revenue ($M, from P&L) | C41: ='P&L_Consolidated'!C19 -> 56159.35 | D41: ='P&L_Consolidated'!D19 -> 80075.08 | E41: ='P&L_Consolidated'!E19 -> 115167.15 | F41: ='P&L_Consolidated'!F19 -> 167052.89 | G41: ='P&L_Consolidated'!G19 -> 244365.36 | H41: ='P&L_Consolidated'!H19 -> 330705 | I41: ='P&L_Consolidated'!I19 -> 436713.03 | J41: ='P&L_Consolidated'!J19 -> 581686.28 | ... V41: ='P&L_Consolidated'!V19 -> 8642655.9
B42: D&A = Rev × D&A% | C42: =C41*$C$35 -> 6739.122 | D42: =D41*$C$35 -> 9609.0096 | E42: =E41*$C$35 -> 13820.058 | F42: =F41*$C$35 -> 20046.347 | G42: =G41*$C$35 -> 29323.843 | H42: =H41*$C$35 -> 39684.6 | I42: =I41*$C$35 -> 52405.563 | J42: =J41*$C$35 -> 69802.353 | ... V42: =V41*$C$35 -> 1037118.7
B43: (+) D&A tax shield = D&A × tax | C43: =C42*Assumptions!$C$12 -> 1415.2156 | D43: =D42*Assumptions!$C$12 -> 2017.892 | E43: =E42*Assumptions!$C$12 -> 2902.2122 | F43: =F42*Assumptions!$C$12 -> 4209.7329 | G43: =G42*Assumptions!$C$12 -> 6158.007 | H43: =H42*Assumptions!$C$12 -> 8333.7659 | I43: =I42*Assumptions!$C$12 -> 11005.168 | J43: =J42*Assumptions!$C$12 -> 14658.494 | ... V43: =V42*Assumptions!$C$12 -> 217794.93
B44: NWC = Rev × NWC% | C44: =C41*$C$36 -> 1684.7805 | D44: =D41*$C$36 -> 2402.2524 | E44: =E41*$C$36 -> 3455.0145 | F44: =F41*$C$36 -> 5011.5868 | G44: =G41*$C$36 -> 7330.9607 | H44: =H41*$C$36 -> 9921.1499 | I44: =I41*$C$36 -> 13101.391 | J44: =J41*$C$36 -> 17450.588 | ... V44: =V41*$C$36 -> 259279.68
B45: (−) ΔNWC | C45: =-C44 -> -1684.7805 | D45: =-(D44-C44) -> -717.4719 | E45: =-(E44-D44) -> -1052.7621 | F45: =-(F44-E44) -> -1556.5723 | G45: =-(G44-F44) -> -2319.3739 | H45: =-(H44-G44) -> -2590.1892 | I45: =-(I44-H44) -> -3180.241 | J45: =-(J44-I44) -> -4349.1975 | K45: =-(K44-J44) -> -6018.8051 | ... V45: =-(V44-U44) -> -56443.978
B46: NOL opening | C46: =$C$37 -> 25000 | D46: =C50 -> 5616.7176 | E46: =D50 -> 0 | F46: =E50 -> 0 | G46: =F50 -> 0 | H46: =G50 -> 0 | I46: =H50 -> 0 | J46: =I50 -> 0 | K46: =J50 -> 0 | ... V46: =U50 -> 0
B47: EBIT = EBITDA − D&A | C47: ='P&L_Consolidated'!C35-C42 -> 24229.103 | D47: ='P&L_Consolidated'!D35-D42 -> 35128.579 | E47: ='P&L_Consolidated'!E35-E42 -> 51335.037 | F47: ='P&L_Consolidated'!F35-F42 -> 75604.323 | G47: ='P&L_Consolidated'!G35-G42 -> 112213.56 | H47: ='P&L_Consolidated'!H35-H42 -> 152166.21 | I47: ='P&L_Consolidated'!I35-I42 -> 202527.39 | J47: ='P&L_Consolidated'!J35-J42 -> 271720.12 | ... V47: ='P&L_Consolidated'!V35-V42 -> 4124192.6
B48: NOL used (min of EBIT×80%, NOL) | C48: =MAX(0,MIN(C46,MAX(0,C47)*$C$38)) -> 19383.282 | D48: =MAX(0,MIN(D46,MAX(0,D47)*$C$38)) -> 5616.7176 | E48: =MAX(0,MIN(E46,MAX(0,E47)*$C$38)) -> 0 | F48: =MAX(0,MIN(F46,MAX(0,F47)*$C$38)) -> 0 | G48: =MAX(0,MIN(G46,MAX(0,G47)*$C$38)) -> 0 | H48: =MAX(0,MIN(H46,MAX(0,H47)*$C$38)) -> 0 | I48: =MAX(0,MIN(I46,MAX(0,I47)*$C$38)) -> 0 | J48: =MAX(0,MIN(J46,MAX(0,J47)*$C$38)) -> 0 | ... V48: =MAX(0,MIN(V46,MAX(0,V47)*$C$38)) -> 0
B49: (+) Cash tax saved by NOL | C49: =C48*Assumptions!$C$12 -> 4070.4893 | D49: =D48*Assumptions!$C$12 -> 1179.5107 | E49: =E48*Assumptions!$C$12 -> 0 | F49: =F48*Assumptions!$C$12 -> 0 | G49: =G48*Assumptions!$C$12 -> 0 | H49: =H48*Assumptions!$C$12 -> 0 | I49: =I48*Assumptions!$C$12 -> 0 | J49: =J48*Assumptions!$C$12 -> 0 | ... V49: =V48*Assumptions!$C$12 -> 0
B50: NOL closing | C50: =MAX(0,C46-C48) -> 5616.7176 | D50: =MAX(0,D46-D48) -> 0 | E50: =MAX(0,E46-E48) -> 0 | F50: =MAX(0,F46-F48) -> 0 | G50: =MAX(0,G46-G48) -> 0 | H50: =MAX(0,H46-H48) -> 0 | I50: =MAX(0,I46-I48) -> 0 | J50: =MAX(0,J46-J48) -> 0 | ... V50: =MAX(0,V46-V48) -> 0
B51: Total FCF adjustment | C51: =C43+C45+C49 -> 3800.9244 | D51: =D43+D45+D49 -> 2479.9308 | E51: =E43+E45+E49 -> 1849.4501 | F51: =F43+F45+F49 -> 2653.1606 | G51: =G43+G45+G49 -> 3838.6331 | H51: =H43+H45+H49 -> 5743.5767 | I51: =I43+I45+I49 -> 7824.9273 | J51: =J43+J45+J49 -> 10309.297 | ... V51: =V43+V45+V49 -> 161350.95
B52: Adjusted UFCF ($M) | C52: =C7+C51 -> 13802.552 | D52: =D7+D51 -> 17333.169 | E52: =E7+E51 -> 24039.675 | F52: =F7+F51 -> 36014.271 | G52: =G7+G51 -> 54333.153 | H52: =H7+H51 -> 73502.332 | I52: =I7+I51 -> 99149.839 | J52: =J7+J51 -> 134301.85 | ... V52: =V7+V51 -> 2049088.3
B53: PV of Adjusted UFCF ($M) | C53: =C52*C8 -> 12662.456 | D53: =D52*D8 -> 14587.978 | E53: =E52*E8 -> 18561.124 | F53: =F52*F8 -> 25509.906 | G53: =G52*G8 -> 35306.747 | H53: =H52*H8 -> 43817.993 | I53: =I52*I8 -> 54225.297 | J53: =J52*J8 -> 67383.022 | ... V53: =V52*V8 -> 365369.16

Sheet Sensitivities
A1: SENSITIVITY TABLES
A2: All tables centred on base case (WACC 9.0%, g 4.0%). Tables 1 & 2 show the BLENDED equity (55% × 5yr + 35% × 10yr + 10% × 20yr) — consistent with Summary!E10.
A4: Table 1: Blended Enterprise Value ($M) — WACC × Terminal Growth (base highlighted)
B6: g → | C6: 0.03 | D6: 0.035 | E6: 0.04 | F6: 0.045 | G6: 0.05
B7: WACC ↓
B8: 0.075 | C8: {=Assumptions!$C$35*(SUMPRODUCT(DCF!$C$52:$G$52,1/(1+$B8)^{1,2,3,4,5})+DCF!$G$52*(1+C$6)/($B8-C$6)/(1+$B8)^5)+Assumptions!$C$36*(SUMPRODUCT(DCF!$C$52:$L$52,1/(1+$B8)^{1,2,3,4,5,6,7,8,9,10})+DCF!$L$52*(1+C$6)/($B8-C$6)/(1+$B8)^10)+Assumptions!$C$37*(SUMPRODUCT(DCF!$C$52:$V$52,1/(1+$B8)^{1,2,3,4,5,6,7,8,9,10,11,12,13,14,15,16,17,18,19,20})+DCF!$V$52*(1+C$6)/($B8-C$6)/(1+$B8)^20)} -> 3126104.9 | D8: {=Assumptions!$C$35*(SUMPRODUCT(DCF!$C$52:$G$52,1/(1+$B8)^{1,2,3,4,5})+DCF!$G$52*(1+D$6)/($B8-D$6)/(1+$B8)^5)+Assumptions!$C$36*(SUMPRODUCT(DCF!$C$52:$L$52,1/(1+$B8)^{1,2,3,4,5,6,7,8,9,10})+DCF!$L$52*(1+D$6)/($B8-D$6)/(1+$B8)^10)+Assumptions!$C$37*(SUMPRODUCT(DCF!$C$52:$V$52,1/(1+$B8)^{1,2,3,4,5,6,7,8,9,10,11,12,13,14,15,16,17,18,19,20})+DCF!$V$52*(1+D$6)/($B8-D$6)/(1+$B8)^20)} -> 3460721.1 | E8: {=Assumptions!$C$35*(SUMPRODUCT(DCF!$C$52:$G$52,1/(1+$B8)^{1,2,3,4,5})+DCF!$G$52*(1+E$6)/($B8-E$6)/(1+$B8)^5)+Assumptions!$C$36*(SUMPRODUCT(DCF!$C$52:$L$52,1/(1+$B8)^{1,2,3,4,5,6,7,8,9,10})+DCF!$L$52*(1+E$6)/($B8-E$6)/(1+$B8)^10)+Assumptions!$C$37*(SUMPRODUCT(DCF!$C$52:$V$52,1/(1+$B8)^{1,2,3,4,5,6,7,8,9,10,11,12,13,14,15,16,17,18,19,20})+DCF!$V$52*(1+E$6)/($B8-E$6)/(1+$B8)^20)} -> 3890941.8 | F8: {=Assumptions!$C$35*(SUMPRODUCT(DCF!$C$52:$G$52,1/(1+$B8)^{1,2,3,4,5})+DCF!$G$52*(1+F$6)/($B8-F$6)/(1+$B8)^5)+Assumptions!$C$36*(SUMPRODUCT(DCF!$C$52:$L$52,1/(1+$B8)^{1,2,3,4,5,6,7,8,9,10})+DCF!$L$52*(1+F$6)/($B8-F$6)/(1+$B8)^10)+Assumptions!$C$37*(SUMPRODUCT(DCF!$C$52:$V$52,1/(1+$B8)^{1,2,3,4,5,6,7,8,9,10,11,12,13,14,15,16,17,18,19,20})+DCF!$V$52*(1+F$6)/($B8-F$6)/(1+$B8)^20)} -> 4464569.5 | G8: {=Assumptions!$C$35*(SUMPRODUCT(DCF!$C$52:$G$52,1/(1+$B8)^{1,2,3,4,5})+DCF!$G$52*(1+G$6)/($B8-G$6)/(1+$B8)^5)+Assumptions!$C$36*(SUMPRODUCT(DCF!$C$52:$L$52,1/(1+$B8)^{1,2,3,4,5,6,7,8,9,10})+DCF!$L$52*(1+G$6)/($B8-G$6)/(1+$B8)^10)+Assumptions!$C$37*(SUMPRODUCT(DCF!$C$52:$V$52,1/(1+$B8)^{1,2,3,4,5,6,7,8,9,10,11,12,13,14,15,16,17,18,19,20})+DCF!$V$52*(1+G$6)/($B8-G$6)/(1+$B8)^20)} -> 5267648.3
B9: 0.0825 | C9: {=Assumptions!$C$35*(SUMPRODUCT(DCF!$C$52:$G$52,1/(1+$B9)^{1,2,3,4,5})+DCF!$G$52*(1+C$6)/($B9-C$6)/(1+$B9)^5)+Assumptions!$C$36*(SUMPRODUCT(DCF!$C$52:$L$52,1/(1+$B9)^{1,2,3,4,5,6,7,8,9,10})+DCF!$L$52*(1+C$6)/($B9-C$6)/(1+$B9)^10)+Assumptions!$C$37*(SUMPRODUCT(DCF!$C$52:$V$52,1/(1+$B9)^{1,2,3,4,5,6,7,8,9,10,11,12,13,14,15,16,17,18,19,20})+DCF!$V$52*(1+C$6)/($B9-C$6)/(1+$B9)^20)} -> 2523892.3 | D9: {=Assumptions!$C$35*(SUMPRODUCT(DCF!$C$52:$G$52,1/(1+$B9)^{1,2,3,4,5})+DCF!$G$52*(1+D$6)/($B9-D$6)/(1+$B9)^5)+Assumptions!$C$36*(SUMPRODUCT(DCF!$C$52:$L$52,1/(1+$B9)^{1,2,3,4,5,6,7,8,9,10})+DCF!$L$52*(1+D$6)/($B9-D$6)/(1+$B9)^10)+Assumptions!$C$37*(SUMPRODUCT(DCF!$C$52:$V$52,1/(1+$B9)^{1,2,3,4,5,6,7,8,9,10,11,12,13,14,15,16,17,18,19,20})+DCF!$V$52*(1+D$6)/($B9-D$6)/(1+$B9)^20)} -> 2745701.1 | E9: {=Assumptions!$C$35*(SUMPRODUCT(DCF!$C$52:$G$52,1/(1+$B9)^{1,2,3,4,5})+DCF!$G$52*(1+E$6)/($B9-E$6)/(1+$B9)^5)+Assumptions!$C$36*(SUMPRODUCT(DCF!$C$52:$L$52,1/(1+$B9)^{1,2,3,4,5,6,7,8,9,10})+DCF!$L$52*(1+E$6)/($B9-E$6)/(1+$B9)^10)+Assumptions!$C$37*(SUMPRODUCT(DCF!$C$52:$V$52,1/(1+$B9)^{1,2,3,4,5,6,7,8,9,10,11,12,13,14,15,16,17,18,19,20})+DCF!$V$52*(1+E$6)/($B9-E$6)/(1+$B9)^20)} -> 3019700.2 | F9: {=Assumptions!$C$35*(SUMPRODUCT(DCF!$C$52:$G$52,1/(1+$B9)^{1,2,3,4,5})+DCF!$G$52*(1+F$6)/($B9-F$6)/(1+$B9)^5)+Assumptions!$C$36*(SUMPRODUCT(DCF!$C$52:$L$52,1/(1+$B9)^{1,2,3,4,5,6,7,8,9,10})+DCF!$L$52*(1+F$6)/($B9-F$6)/(1+$B9)^10)+Assumptions!$C$37*(SUMPRODUCT(DCF!$C$52:$V$52,1/(1+$B9)^{1,2,3,4,5,6,7,8,9,10,11,12,13,14,15,16,17,18,19,20})+DCF!$V$52*(1+F$6)/($B9-F$6)/(1+$B9)^20)} -> 3366765.7 | G9: {=Assumptions!$C$35*(SUMPRODUCT(DCF!$C$52:$G$52,1/(1+$B9)^{1,2,3,4,5})+DCF!$G$52*(1+G$6)/($B9-G$6)/(1+$B9)^5)+Assumptions!$C$36*(SUMPRODUCT(DCF!$C$52:$L$52,1/(1+$B9)^{1,2,3,4,5,6,7,8,9,10})+DCF!$L$52*(1+G$6)/($B9-G$6)/(1+$B9)^10)+Assumptions!$C$37*(SUMPRODUCT(DCF!$C$52:$V$52,1/(1+$B9)^{1,2,3,4,5,6,7,8,9,10,11,12,13,14,15,16,17,18,19,20})+DCF!$V$52*(1+G$6)/($B9-G$6)/(1+$B9)^20)} -> 3820620.6
B10: 0.09 | C10: {=Assumptions!$C$35*(SUMPRODUCT(DCF!$C$52:$G$52,1/(1+$B10)^{1,2,3,4,5})+DCF!$G$52*(1+C$6)/($B10-C$6)/(1+$B10)^5)+Assumptions!$C$36*(SUMPRODUCT(DCF!$C$52:$L$52,1/(1+$B10)^{1,2,3,4,5,6,7,8,9,10})+DCF!$L$52*(1+C$6)/($B10-C$6)/(1+$B10)^10)+Assumptions!$C$37*(SUMPRODUCT(DCF!$C$52:$V$52,1/(1+$B10)^{1,2,3,4,5,6,7,8,9,10,11,12,13,14,15,16,17,18,19,20})+DCF!$V$52*(1+C$6)/($B10-C$6)/(1+$B10)^20)} -> 2084548.4 | D10: {=Assumptions!$C$35*(SUMPRODUCT(DCF!$C$52:$G$52,1/(1+$B10)^{1,2,3,4,5})+DCF!$G$52*(1+D$6)/($B10-D$6)/(1+$B10)^5)+Assumptions!$C$36*(SUMPRODUCT(DCF!$C$52:$L$52,1/(1+$B10)^{1,2,3,4,5,6,7,8,9,10})+DCF!$L$52*(1+D$6)/($B10-D$6)/(1+$B10)^10)+Assumptions!$C$37*(SUMPRODUCT(DCF!$C$52:$V$52,1/(1+$B10)^{1,2,3,4,5,6,7,8,9,10,11,12,13,14,15,16,17,18,19,20})+DCF!$V$52*(1+D$6)/($B10-D$6)/(1+$B10)^20)} -> 2238838.4 | E10: {=Assumptions!$C$35*(SUMPRODUCT(DCF!$C$52:$G$52,1/(1+$B10)^{1,2,3,4,5})+DCF!$G$52*(1+E$6)/($B10-E$6)/(1+$B10)^5)+Assumptions!$C$36*(SUMPRODUCT(DCF!$C$52:$L$52,1/(1+$B10)^{1,2,3,4,5,6,7,8,9,10})+DCF!$L$52*(1+E$6)/($B10-E$6)/(1+$B10)^10)+Assumptions!$C$37*(SUMPRODUCT(DCF!$C$52:$V$52,1/(1+$B10)^{1,2,3,4,5,6,7,8,9,10,11,12,13,14,15,16,17,18,19,20})+DCF!$V$52*(1+E$6)/($B10-E$6)/(1+$B10)^20)} -> 2423986.5 | F10: {=Assumptions!$C$35*(SUMPRODUCT(DCF!$C$52:$G$52,1/(1+$B10)^{1,2,3,4,5})+DCF!$G$52*(1+F$6)/($B10-F$6)/(1+$B10)^5)+Assumptions!$C$36*(SUMPRODUCT(DCF!$C$52:$L$52,1/(1+$B10)^{1,2,3,4,5,6,7,8,9,10})+DCF!$L$52*(1+F$6)/($B10-F$6)/(1+$B10)^10)+Assumptions!$C$37*(SUMPRODUCT(DCF!$C$52:$V$52,1/(1+$B10)^{1,2,3,4,5,6,7,8,9,10,11,12,13,14,15,16,17,18,19,20})+DCF!$V$52*(1+F$6)/($B10-F$6)/(1+$B10)^20)} -> 2650278.6 | G10: {=Assumptions!$C$35*(SUMPRODUCT(DCF!$C$52:$G$52,1/(1+$B10)^{1,2,3,4,5})+DCF!$G$52*(1+G$6)/($B10-G$6)/(1+$B10)^5)+Assumptions!$C$36*(SUMPRODUCT(DCF!$C$52:$L$52,1/(1+$B10)^{1,2,3,4,5,6,7,8,9,10})+DCF!$L$52*(1+G$6)/($B10-G$6)/(1+$B10)^10)+Assumptions!$C$37*(SUMPRODUCT(DCF!$C$52:$V$52,1/(1+$B10)^{1,2,3,4,5,6,7,8,9,10,11,12,13,14,15,16,17,18,19,20})+DCF!$V$52*(1+G$6)/($B10-G$6)/(1+$B10)^20)} -> 2933143.8
B11: 0.0975 | C11: {=Assumptions!$C$35*(SUMPRODUCT(DCF!$C$52:$G$52,1/(1+$B11)^{1,2,3,4,5})+DCF!$G$52*(1+C$6)/($B11-C$6)/(1+$B11)^5)+Assumptions!$C$36*(SUMPRODUCT(DCF!$C$52:$L$52,1/(1+$B11)^{1,2,3,4,5,6,7,8,9,10})+DCF!$L$52*(1+C$6)/($B11-C$6)/(1+$B11)^10)+Assumptions!$C$37*(SUMPRODUCT(DCF!$C$52:$V$52,1/(1+$B11)^{1,2,3,4,5,6,7,8,9,10,11,12,13,14,15,16,17,18,19,20})+DCF!$V$52*(1+C$6)/($B11-C$6)/(1+$B11)^20)} -> 1752599.2 | D11: {=Assumptions!$C$35*(SUMPRODUCT(DCF!$C$52:$G$52,1/(1+$B11)^{1,2,3,4,5})+DCF!$G$52*(1+D$6)/($B11-D$6)/(1+$B11)^5)+Assumptions!$C$36*(SUMPRODUCT(DCF!$C$52:$L$52,1/(1+$B11)^{1,2,3,4,5,6,7,8,9,10})+DCF!$L$52*(1+D$6)/($B11-D$6)/(1+$B11)^10)+Assumptions!$C$37*(SUMPRODUCT(DCF!$C$52:$V$52,1/(1+$B11)^{1,2,3,4,5,6,7,8,9,10,11,12,13,14,15,16,17,18,19,20})+DCF!$V$52*(1+D$6)/($B11-D$6)/(1+$B11)^20)} -> 1863945.1 | E11: {=Assumptions!$C$35*(SUMPRODUCT(DCF!$C$52:$G$52,1/(1+$B11)^{1,2,3,4,5})+DCF!$G$52*(1+E$6)/($B11-E$6)/(1+$B11)^5)+Assumptions!$C$36*(SUMPRODUCT(DCF!$C$52:$L$52,1/(1+$B11)^{1,2,3,4,5,6,7,8,9,10})+DCF!$L$52*(1+E$6)/($B11-E$6)/(1+$B11)^10)+Assumptions!$C$37*(SUMPRODUCT(DCF!$C$52:$V$52,1/(1+$B11)^{1,2,3,4,5,6,7,8,9,10,11,12,13,14,15,16,17,18,19,20})+DCF!$V$52*(1+E$6)/($B11-E$6)/(1+$B11)^20)} -> 1994655.5 | F11: {=Assumptions!$C$35*(SUMPRODUCT(DCF!$C$52:$G$52,1/(1+$B11)^{1,2,3,4,5})+DCF!$G$52*(1+F$6)/($B11-F$6)/(1+$B11)^5)+Assumptions!$C$36*(SUMPRODUCT(DCF!$C$52:$L$52,1/(1+$B11)^{1,2,3,4,5,6,7,8,9,10})+DCF!$L$52*(1+F$6)/($B11-F$6)/(1+$B11)^10)+Assumptions!$C$37*(SUMPRODUCT(DCF!$C$52:$V$52,1/(1+$B11)^{1,2,3,4,5,6,7,8,9,10,11,12,13,14,15,16,17,18,19,20})+DCF!$V$52*(1+F$6)/($B11-F$6)/(1+$B11)^20)} -> 2150263.1 | G11: {=Assumptions!$C$35*(SUMPRODUCT(DCF!$C$52:$G$52,1/(1+$B11)^{1,2,3,4,5})+DCF!$G$52*(1+G$6)/($B11-G$6)/(1+$B11)^5)+Assumptions!$C$36*(SUMPRODUCT(DCF!$C$52:$L$52,1/(1+$B11)^{1,2,3,4,5,6,7,8,9,10})+DCF!$L$52*(1+G$6)/($B11-G$6)/(1+$B11)^10)+Assumptions!$C$37*(SUMPRODUCT(DCF!$C$52:$V$52,1/(1+$B11)^{1,2,3,4,5,6,7,8,9,10,11,12,13,14,15,16,17,18,19,20})+DCF!$V$52*(1+G$6)/($B11-G$6)/(1+$B11)^20)} -> 2338630.2
B12: 0.105 | C12: {=Assumptions!$C$35*(SUMPRODUCT(DCF!$C$52:$G$52,1/(1+$B12)^{1,2,3,4,5})+DCF!$G$52*(1+C$6)/($B12-C$6)/(1+$B12)^5)+Assumptions!$C$36*(SUMPRODUCT(DCF!$C$52:$L$52,1/(1+$B12)^{1,2,3,4,5,6,7,8,9,10})+DCF!$L$52*(1+C$6)/($B12-C$6)/(1+$B12)^10)+Assumptions!$C$37*(SUMPRODUCT(DCF!$C$52:$V$52,1/(1+$B12)^{1,2,3,4,5,6,7,8,9,10,11,12,13,14,15,16,17,18,19,20})+DCF!$V$52*(1+C$6)/($B12-C$6)/(1+$B12)^20)} -> 1494889.6 | D12: {=Assumptions!$C$35*(SUMPRODUCT(DCF!$C$52:$G$52,1/(1+$B12)^{1,2,3,4,5})+DCF!$G$52*(1+D$6)/($B12-D$6)/(1+$B12)^5)+Assumptions!$C$36*(SUMPRODUCT(DCF!$C$52:$L$52,1/(1+$B12)^{1,2,3,4,5,6,7,8,9,10})+DCF!$L$52*(1+D$6)/($B12-D$6)/(1+$B12)^10)+Assumptions!$C$37*(SUMPRODUCT(DCF!$C$52:$V$52,1/(1+$B12)^{1,2,3,4,5,6,7,8,9,10,11,12,13,14,15,16,17,18,19,20})+DCF!$V$52*(1+D$6)/($B12-D$6)/(1+$B12)^20)} -> 1577620.3 | E12: {=Assumptions!$C$35*(SUMPRODUCT(DCF!$C$52:$G$52,1/(1+$B12)^{1,2,3,4,5})+DCF!$G$52*(1+E$6)/($B12-E$6)/(1+$B12)^5)+Assumptions!$C$36*(SUMPRODUCT(DCF!$C$52:$L$52,1/(1+$B12)^{1,2,3,4,5,6,7,8,9,10})+DCF!$L$52*(1+E$6)/($B12-E$6)/(1+$B12)^10)+Assumptions!$C$37*(SUMPRODUCT(DCF!$C$52:$V$52,1/(1+$B12)^{1,2,3,4,5,6,7,8,9,10,11,12,13,14,15,16,17,18,19,20})+DCF!$V$52*(1+E$6)/($B12-E$6)/(1+$B12)^20)} -> 1673078.8 | F12: {=Assumptions!$C$35*(SUMPRODUCT(DCF!$C$52:$G$52,1/(1+$B12)^{1,2,3,4,5})+DCF!$G$52*(1+F$6)/($B12-F$6)/(1+$B12)^5)+Assumptions!$C$36*(SUMPRODUCT(DCF!$C$52:$L$52,1/(1+$B12)^{1,2,3,4,5,6,7,8,9,10})+DCF!$L$52*(1+F$6)/($B12-F$6)/(1+$B12)^10)+Assumptions!$C$37*(SUMPRODUCT(DCF!$C$52:$V$52,1/(1+$B12)^{1,2,3,4,5,6,7,8,9,10,11,12,13,14,15,16,17,18,19,20})+DCF!$V$52*(1+F$6)/($B12-F$6)/(1+$B12)^20)} -> 1784447 | G12: {=Assumptions!$C$35*(SUMPRODUCT(DCF!$C$52:$G$52,1/(1+$B12)^{1,2,3,4,5})+DCF!$G$52*(1+G$6)/($B12-G$6)/(1+$B12)^5)+Assumptions!$C$36*(SUMPRODUCT(DCF!$C$52:$L$52,1/(1+$B12)^{1,2,3,4,5,6,7,8,9,10})+DCF!$L$52*(1+G$6)/($B12-G$6)/(1+$B12)^10)+Assumptions!$C$37*(SUMPRODUCT(DCF!$C$52:$V$52,1/(1+$B12)^{1,2,3,4,5,6,7,8,9,10,11,12,13,14,15,16,17,18,19,20})+DCF!$V$52*(1+G$6)/($B12-G$6)/(1+$B12)^20)} -> 1916064.1
A14: Table 2: Blended Value per Share ($) — WACC × Terminal Growth (base highlighted)
B16: g → | C16: =C6 -> 0.03 | D16: =D6 -> 0.035 | E16: =E6 -> 0.04 | F16: =F6 -> 0.045 | G16: =G6 -> 0.05
B17: WACC ↓
B18: =B8 -> 0.075 | C18: =(C8-Assumptions!$C$22)/Assumptions!$C$25 -> 232.30193 | D18: =(D8-Assumptions!$C$22)/Assumptions!$C$25 -> 257.27329 | E18: =(E8-Assumptions!$C$22)/Assumptions!$C$25 -> 289.37932 | F18: =(F8-Assumptions!$C$22)/Assumptions!$C$25 -> 332.18735 | G18: =(G8-Assumptions!$C$22)/Assumptions!$C$25 -> 392.1186
B19: =B9 -> 0.0825 | C19: =(C9-Assumptions!$C$22)/Assumptions!$C$25 -> 187.3607 | D19: =(D9-Assumptions!$C$22)/Assumptions!$C$25 -> 203.91359 | E19: =(E9-Assumptions!$C$22)/Assumptions!$C$25 -> 224.36128 | F19: =(F9-Assumptions!$C$22)/Assumptions!$C$25 -> 250.2617 | G19: =(G9-Assumptions!$C$22)/Assumptions!$C$25 -> 284.13147
B20: =B10 -> 0.09 | C20: =(C10-Assumptions!$C$22)/Assumptions!$C$25 -> 154.57383 | D20: =(D10-Assumptions!$C$22)/Assumptions!$C$25 -> 166.08802 | E20: =(E10-Assumptions!$C$22)/Assumptions!$C$25 -> 179.90504 | F20: =(F10-Assumptions!$C$22)/Assumptions!$C$25 -> 196.79251 | G20: =(G10-Assumptions!$C$22)/Assumptions!$C$25 -> 217.90185 | H20: =H10 -> 0 | I20: =I10 -> 0
B21: =B11 -> 0.0975 | C21: =(C11-Assumptions!$C$22)/Assumptions!$C$25 -> 129.80151 | D21: =(D11-Assumptions!$C$22)/Assumptions!$C$25 -> 138.1109 | E21: =(E11-Assumptions!$C$22)/Assumptions!$C$25 -> 147.86541 | F21: =(F11-Assumptions!$C$22)/Assumptions!$C$25 -> 159.47792 | G21: =(G11-Assumptions!$C$22)/Assumptions!$C$25 -> 173.53516
B22: =B12 -> 0.105 | C22: =(C12-Assumptions!$C$22)/Assumptions!$C$25 -> 110.56944 | D22: =(D12-Assumptions!$C$22)/Assumptions!$C$25 -> 116.74338 | E22: =(E12-Assumptions!$C$22)/Assumptions!$C$25 -> 123.86715 | F22: =(F12-Assumptions!$C$22)/Assumptions!$C$25 -> 132.17821 | G22: =(G12-Assumptions!$C$22)/Assumptions!$C$25 -> 142.00038
D23: =D13 -> 0
A24: Table 3: Probability-of-Success Sensitivity — SOTP Total Equity ($M) | D24: =D14 -> 0
A25: How does total equity move as we re-weight the speculative bucket? (Anchor + Plausible held constant at Base.) | D25: =D15 -> 0
D26: =D16 -> 0.035
B27: Speculative scenario | C27: Spec EV contrib ($M) | D27: Anchor+Plausible ($M) | E27: Total EV ($M) | F27: Total equity ($M) | G27: $/share
B28: All speculative zeroed out (100% failure) | C28: 0 | D28: ='Sum of Parts'!F21-SUMIFS('Sum of Parts'!$F$9:$F$20,'Sum of Parts'!$B$9:$B$20,"SPECULATIVE") -> 2230083.4 | E28: =C28+D28 -> 2230083.4 | F28: =E28-Assumptions!$C$22 -> 2216824.4 | G28: =F28/Assumptions!$C$25 -> 165.43466
B29: Bear case for speculative (current materialisation × 0.25) | C29: =SUMIFS('Sum of Parts'!$F$9:$F$20,'Sum of Parts'!$B$9:$B$20,"SPECULATIVE")*0.25 -> 6681.8536 | D29: =$D$28 -> 2230083.4 | E29: =C29+D29 -> 2236765.3 | F29: =E29-Assumptions!$C$22 -> 2223506.3 | G29: =F29/Assumptions!$C$25 -> 165.9333
B30: Base case (current model weighting) | C30: =SUMIFS('Sum of Parts'!$F$9:$F$20,'Sum of Parts'!$B$9:$B$20,"SPECULATIVE") -> 26727.414 | D30: =$D$28 -> 2230083.4 | E30: =C30+D30 -> 2256810.8 | F30: =E30-Assumptions!$C$22 -> 2243551.8 | G30: =F30/Assumptions!$C$25 -> 167.42924
B31: Bull case (current × 3, broader optionality success) | C31: =SUMIFS('Sum of Parts'!$F$9:$F$20,'Sum of Parts'!$B$9:$B$20,"SPECULATIVE")*3 -> 80182.243 | D31: =$D$28 -> 2230083.4 | E31: =C31+D31 -> 2310265.7 | F31: =E31-Assumptions!$C$22 -> 2297006.7 | G31: =F31/Assumptions!$C$25 -> 171.41841
B32: Bull-Bull (current × 10, all optionality realised) | C32: =SUMIFS('Sum of Parts'!$F$9:$F$20,'Sum of Parts'!$B$9:$B$20,"SPECULATIVE")*10 -> 267274.14 | D32: =$D$28 -> 2230083.4 | E32: =C32+D32 -> 2497357.6 | F32: =E32-Assumptions!$C$22 -> 2484098.6 | G32: =F32/Assumptions!$C$25 -> 185.38049
B34: Speculative segments full write-off VaR
B35: If both SPECULATIVE-tier segments are removed entirely (legal/physics/timeline failure), what's the value at risk?
B36: Orbital DCs current Base EV ($M) | C36: ='Sum of Parts'!F19 -> 26711.956
B37: Deep Space Optionality current Base EV ($M) | C37: ='Sum of Parts'!F20 -> 15.457795
B38: Combined speculative VaR ($M) | C38: =C36+C37 -> 26727.414
B39: Impact on $/share if both written off | C39: =-C38/Assumptions!$C$25 -> -1.9945832
A45: Table 4: SENSITIVITY TORNADO — Drivers ranked by equity impact ($Bn)
A46: Each row shows the equity impact ($Bn) of moving one driver to a downside or upside case while holding others at base. Sorted by absolute swing.
B48: Driver | C48: Downside case | D48: Upside case | E48: Downside impact ($Bn) | F48: Upside impact ($Bn) | G48: Range ($Bn) | I48: Tornado data (sorted by range descending)
B49: Base equity ($Bn) | G49: =Summary!E10/1000 -> 2408.2305 | I49: Driver | J49: Downside | K49: Upside
B50: WACC ±150bps | C50: 0.105 | D50: 0.075 | E50: =(E12-E10)/1000 -> -750.90776 | F50: =(E8-E10)/1000 -> 1466.9553 | G50: =F50-E50 -> 2217.8631 | I50: =B50 -> WACC ±150bps | J50: =E50 -> -750.90776 | K50: =F50 -> 1466.9553
B51: Terminal g ±100bps | C51: 0.03 | D51: 0.05 | E51: =(D10-E10)/1000 -> -185.14809 | F51: =(G10-E10)/1000 -> 509.15726 | G51: =F51-E51 -> 694.30535 | I51: =B52 -> Speculative bucket success | J51: =E52 -> -26.727414 | K51: =F52 -> 53.454828
B52: Speculative bucket success | C52: All zeroed (legal/physics fail) | D52: Bull (3× current weighting) | E52: =(F28-F30)/1000 -> -26.727414 | F52: =(F31-F30)/1000 -> 53.454828 | G52: =F52-E52 -> 80.182243 | I52: =B51 -> Terminal g ±100bps | J52: =E51 -> -185.14809 | K52: =F51 -> 509.15726
B53: Starlink D2C materialisation | C53: −50% (one carrier only, slow ramp) | D53: +20% (multi-carrier, mass market) | E53: =-'Sum of Parts'!F17*0.5/1000 -> -26.737467 | F53: ='Sum of Parts'!F17*0.2/1000 -> 10.694987 | G53: =F53-E53 -> 37.432454 | I53: =B56 -> Governance discount (dual class) | J53: =E56 -> -481.64611 | K53: =F56 -> 0
B54: Colossus DCs (xAI demand) | C54: −40% (AI capex slowdown) | D54: +30% (compute demand acceleration) | E54: =-'Sum of Parts'!F14*0.4/1000 -> -25.395739 | F54: ='Sum of Parts'!F14*0.3/1000 -> 19.046804 | G54: =F54-E54 -> 44.442543 | I54: =B53 -> Starlink D2C materialisation | J54: =E53 -> -26.737467 | K54: =F53 -> 10.694987
B55: Starship programme (24-mo slip) | C55: Launch cost reductions delayed | D55: Ahead of plan (cost down 30%) | E55: =-'Sum of Parts'!F9*0.2/1000-'Sum of Parts'!F10*0.1/1000 -> -139.23619 | F55: ='Sum of Parts'!F9*0.15/1000+'Sum of Parts'!F10*0.05/1000 -> 85.812918 | G55: =F55-E55 -> 225.04911 | I55: =B55 -> Starship programme (24-mo slip) | J55: =E55 -> -139.23619 | K55: =F55 -> 85.812918
B56: Governance discount (dual class) | C56: 20% discount (high) | D56: 0% (no discount applied) | E56: =-Summary!E10*0.2/1000 -> -481.64611 | F56: 0 | G56: =F56-E56 -> 481.64611 | I56: =B54 -> Colossus DCs (xAI demand) | J56: =E54 -> -25.395739 | K56: =F54 -> 19.046804
B57: NOL stock (NWC + D&A assumptions) | C57: NOL = $0 (none); NWC 5% | D57: NOL = $40B; NWC 1% | E57: -25 | F57: 35 | G57: =F57-E57 -> 60 | I57: =B57 -> NOL stock (NWC + D&A assumptions) | J57: =E57 -> -25 | K57: =F57 -> 35

Sheet Monte_Carlo
A1: MONTE CARLO SIMULATION — SpaceX Valuation Distribution | I1: u_WACC | J1: u_g | K1: u_anchor | L1: u_plaus | M1: u_spec | N1: EV ($M) | O1: $/share
A2: 5,000 trials. Random draws on WACC, terminal g, and 5 segment-bucket scenario outcomes. Output: equity value distribution. | I2: =MAX($D$6,MIN($E$6,_xlfn.NORM.INV(RAND(),$B$6,$C$6))) -> 0.095931609 | J2: =MAX($D$7,MIN($E$7,_xlfn.NORM.INV(RAND(),$B$7,$C$7))) -> 0.044659803 | K2: =RAND() -> 0.021136744 | L2: =RAND() -> 0.11813364 | M2: =RAND() -> 0.74083563 | N2: =(IF(K2<$E$10,$B$10,IF(K2<$E$10+$F$10,$C$10,$D$10))+IF(L2<$E$11,$B$11,IF(L2<$E$11+$F$11,$C$11,$D$11))+IF(M2<$E$12,$B$12,IF(M2<$E$12+$F$12,$C$12,$D$12)))*MIN(2.5,MAX(0.5,(0.09-0.04)/MAX(0.025,(I2-J2)))) -> 342121.51 | O2: =(N2-Assumptions!$C$22)/Assumptions!$C$25 -> 24.541978
A3: F9 = recalc (or press F9). Distribution updates live. | I3: =MAX($D$6,MIN($E$6,_xlfn.NORM.INV(RAND(),$B$6,$C$6))) -> 0.079123846 | J3: =MAX($D$7,MIN($E$7,_xlfn.NORM.INV(RAND(),$B$7,$C$7))) -> 0.041667591 | K3: =RAND() -> 0.35594137 | L3: =RAND() -> 0.61542808 | M3: =RAND() -> 0.061270816 | N3: =(IF(K3<$E$10,$B$10,IF(K3<$E$10+$F$10,$C$10,$D$10))+IF(L3<$E$11,$B$11,IF(L3<$E$11+$F$11,$C$11,$D$11))+IF(M3<$E$12,$B$12,IF(M3<$E$12+$F$12,$C$12,$D$12)))*MIN(2.5,MAX(0.5,(0.09-0.04)/MAX(0.025,(I3-J3)))) -> 2980027.5 | O3: =(N3-Assumptions!$C$22)/Assumptions!$C$25 -> 221.40063
I4: =MAX($D$6,MIN($E$6,_xlfn.NORM.INV(RAND(),$B$6,$C$6))) -> 0.11032875 | J4: =MAX($D$7,MIN($E$7,_xlfn.NORM.INV(RAND(),$B$7,$C$7))) -> 0.027101773 | K4: =RAND() -> 0.21882029 | L4: =RAND() -> 0.553015 | M4: =RAND() -> 0.65744169 | N4: =(IF(K4<$E$10,$B$10,IF(K4<$E$10+$F$10,$C$10,$D$10))+IF(L4<$E$11,$B$11,IF(L4<$E$11+$F$11,$C$11,$D$11))+IF(M4<$E$12,$B$12,IF(M4<$E$12+$F$12,$C$12,$D$12)))*MIN(2.5,MAX(0.5,(0.09-0.04)/MAX(0.025,(I4-J4)))) -> 1355816.9 | O4: =(N4-Assumptions!$C$22)/Assumptions!$C$25 -> 100.19089
A5: INPUT DISTRIBUTIONS | B5: Mean | C5: Stdev | D5: Min | E5: Max | F5: Notes | I5: =MAX($D$6,MIN($E$6,_xlfn.NORM.INV(RAND(),$B$6,$C$6))) -> 0.089944321 | J5: =MAX($D$7,MIN($E$7,_xlfn.NORM.INV(RAND(),$B$7,$C$7))) -> 0.032623461 | K5: =RAND() -> 0.16314547 | L5: =RAND() -> 0.35159069 | M5: =RAND() -> 0.49369953 | N5: =(IF(K5<$E$10,$B$10,IF(K5<$E$10+$F$10,$C$10,$D$10))+IF(L5<$E$11,$B$11,IF(L5<$E$11+$F$11,$C$11,$D$11))+IF(M5<$E$12,$B$12,IF(M5<$E$12+$F$12,$C$12,$D$12)))*MIN(2.5,MAX(0.5,(0.09-0.04)/MAX(0.025,(I5-J5)))) -> 677730.03 | O5: =(N5-Assumptions!$C$22)/Assumptions!$C$25 -> 49.58739
A6: WACC | B6: 0.09 | C6: 0.015 | D6: 0.06 | E6: 0.14 | F6: Normal truncated. Tighter ranges = more concentrated distribution. | I6: =MAX($D$6,MIN($E$6,_xlfn.NORM.INV(RAND(),$B$6,$C$6))) -> 0.07733347 | J6: =MAX($D$7,MIN($E$7,_xlfn.NORM.INV(RAND(),$B$7,$C$7))) -> 0.036915591 | K6: =RAND() -> 0.051014521 | L6: =RAND() -> 0.62082895 | M6: =RAND() -> 0.341316 | N6: =(IF(K6<$E$10,$B$10,IF(K6<$E$10+$F$10,$C$10,$D$10))+IF(L6<$E$11,$B$11,IF(L6<$E$11+$F$11,$C$11,$D$11))+IF(M6<$E$12,$B$12,IF(M6<$E$12+$F$12,$C$12,$D$12)))*MIN(2.5,MAX(0.5,(0.09-0.04)/MAX(0.025,(I6-J6)))) -> 961160.48 | O6: =(N6-Assumptions!$C$22)/Assumptions!$C$25 -> 70.738916
A7: Terminal growth | B7: 0.04 | C7: 0.01 | D7: 0.02 | E7: 0.055 | F7: Normal truncated. | I7: =MAX($D$6,MIN($E$6,_xlfn.NORM.INV(RAND(),$B$6,$C$6))) -> 0.092912354 | J7: =MAX($D$7,MIN($E$7,_xlfn.NORM.INV(RAND(),$B$7,$C$7))) -> 0.023189666 | K7: =RAND() -> 0.53468673 | L7: =RAND() -> 0.72077079 | M7: =RAND() -> 0.46133951 | N7: =(IF(K7<$E$10,$B$10,IF(K7<$E$10+$F$10,$C$10,$D$10))+IF(L7<$E$11,$B$11,IF(L7<$E$11+$F$11,$C$11,$D$11))+IF(M7<$E$12,$B$12,IF(M7<$E$12+$F$12,$C$12,$D$12)))*MIN(2.5,MAX(0.5,(0.09-0.04)/MAX(0.025,(I7-J7)))) -> 1600923.2 | O7: =(N7-Assumptions!$C$22)/Assumptions!$C$25 -> 118.4824
I8: =MAX($D$6,MIN($E$6,_xlfn.NORM.INV(RAND(),$B$6,$C$6))) -> 0.076983207 | J8: =MAX($D$7,MIN($E$7,_xlfn.NORM.INV(RAND(),$B$7,$C$7))) -> 0.032200035 | K8: =RAND() -> 0.27634448 | L8: =RAND() -> 0.46753763 | M8: =RAND() -> 0.87088995 | N8: =(IF(K8<$E$10,$B$10,IF(K8<$E$10+$F$10,$C$10,$D$10))+IF(L8<$E$11,$B$11,IF(L8<$E$11+$F$11,$C$11,$D$11))+IF(M8<$E$12,$B$12,IF(M8<$E$12+$F$12,$C$12,$D$12)))*MIN(2.5,MAX(0.5,(0.09-0.04)/MAX(0.025,(I8-J8)))) -> 2519708.6 | O8: =(N8-Assumptions!$C$22)/Assumptions!$C$25 -> 187.04848
A9: SEGMENT BUCKET SCENARIO PROBS | B9: Bear EV ($M) | C9: Base EV ($M) | D9: Bull EV ($M) | E9: P(Bear) | F9: P(Base) | G9: P(Bull) | I9: =MAX($D$6,MIN($E$6,_xlfn.NORM.INV(RAND(),$B$6,$C$6))) -> 0.088513862 | J9: =MAX($D$7,MIN($E$7,_xlfn.NORM.INV(RAND(),$B$7,$C$7))) -> 0.030132391 | K9: =RAND() -> 0.96360053 | L9: =RAND() -> 0.15016888 | M9: =RAND() -> 0.78564126 | N9: =(IF(K9<$E$10,$B$10,IF(K9<$E$10+$F$10,$C$10,$D$10))+IF(L9<$E$11,$B$11,IF(L9<$E$11+$F$11,$C$11,$D$11))+IF(M9<$E$12,$B$12,IF(M9<$E$12+$F$12,$C$12,$D$12)))*MIN(2.5,MAX(0.5,(0.09-0.04)/MAX(0.025,(I9-J9)))) -> 3331788.6 | O9: =(N9-Assumptions!$C$22)/Assumptions!$C$25 -> 247.65146
A10: Anchor (Launch, Starlink, Starshield, xAI, Colossus, Crewed Spaceflight) | B10: =SUMIFS('Sum of Parts'!G9:G28,'Sum of Parts'!B9:B28,"ANCHOR") -> 281230.13 | C10: =SUMIFS('Sum of Parts'!F9:F28,'Sum of Parts'!B9:B28,"ANCHOR") -> 1736682.2 | D10: =SUMIFS('Sum of Parts'!H9:H28,'Sum of Parts'!B9:B28,"ANCHOR") -> 3820700.8 | E10: 0.2 | F10: 0.6 | G10: 0.2 | I10: =MAX($D$6,MIN($E$6,_xlfn.NORM.INV(RAND(),$B$6,$C$6))) -> 0.10126927 | J10: =MAX($D$7,MIN($E$7,_xlfn.NORM.INV(RAND(),$B$7,$C$7))) -> 0.027000331 | K10: =RAND() -> 0.70355912 | L10: =RAND() -> 0.28078083 | M10: =RAND() -> 0.17991245 | N10: =(IF(K10<$E$10,$B$10,IF(K10<$E$10+$F$10,$C$10,$D$10))+IF(L10<$E$11,$B$11,IF(L10<$E$11+$F$11,$C$11,$D$11))+IF(M10<$E$12,$B$12,IF(M10<$E$12+$F$12,$C$12,$D$12)))*MIN(2.5,MAX(0.5,(0.09-0.04)/MAX(0.025,(I10-J10)))) -> 1199612.1 | O10: =(N10-Assumptions!$C$22)/Assumptions!$C$25 -> 88.533815
A11: Plausible adjacents (Starlink D2C, Other Space Services, X Platform, Terafab) | B11: =SUMIFS('Sum of Parts'!G9:G28,'Sum of Parts'!B9:B28,"PLAUSIBLE") -> 42866.214 | C11: =SUMIFS('Sum of Parts'!F9:F28,'Sum of Parts'!B9:B28,"PLAUSIBLE") -> 493401.27 | D11: =SUMIFS('Sum of Parts'!H9:H28,'Sum of Parts'!B9:B28,"PLAUSIBLE") -> 1085482.8 | E11: 0.3 | F11: 0.5 | G11: 0.2 | I11: =MAX($D$6,MIN($E$6,_xlfn.NORM.INV(RAND(),$B$6,$C$6))) -> 0.10126603 | J11: =MAX($D$7,MIN($E$7,_xlfn.NORM.INV(RAND(),$B$7,$C$7))) -> 0.050429663 | K11: =RAND() -> 0.21399973 | L11: =RAND() -> 0.072825277 | M11: =RAND() -> 0.56290991 | N11: =(IF(K11<$E$10,$B$10,IF(K11<$E$10+$F$10,$C$10,$D$10))+IF(L11<$E$11,$B$11,IF(L11<$E$11+$F$11,$C$11,$D$11))+IF(M11<$E$12,$B$12,IF(M11<$E$12+$F$12,$C$12,$D$12)))*MIN(2.5,MAX(0.5,(0.09-0.04)/MAX(0.025,(I11-J11)))) -> 1752562.8 | O11: =(N11-Assumptions!$C$22)/Assumptions!$C$25 -> 129.79879
A12: Speculative (Orbital DCs, Deep Space Optionality) | B12: =SUMIFS('Sum of Parts'!G9:G28,'Sum of Parts'!B9:B28,"SPECULATIVE") -> 2329.9587 | C12: =SUMIFS('Sum of Parts'!F9:F28,'Sum of Parts'!B9:B28,"SPECULATIVE") -> 26727.414 | D12: =SUMIFS('Sum of Parts'!H9:H28,'Sum of Parts'!B9:B28,"SPECULATIVE") -> 77072.949 | E12: 0.6 | F12: 0.3 | G12: 0.1 | I12: =MAX($D$6,MIN($E$6,_xlfn.NORM.INV(RAND(),$B$6,$C$6))) -> 0.10411045 | J12: =MAX($D$7,MIN($E$7,_xlfn.NORM.INV(RAND(),$B$7,$C$7))) -> 0.022805231 | K12: =RAND() -> 0.80379084 | L12: =RAND() -> 0.64146631 | M12: =RAND() -> 0.34453956 | N12: =(IF(K12<$E$10,$B$10,IF(K12<$E$10+$F$10,$C$10,$D$10))+IF(L12<$E$11,$B$11,IF(L12<$E$11+$F$11,$C$11,$D$11))+IF(M12<$E$12,$B$12,IF(M12<$E$12+$F$12,$C$12,$D$12)))*MIN(2.5,MAX(0.5,(0.09-0.04)/MAX(0.025,(I12-J12)))) -> 2654461.8 | O12: =(N12-Assumptions!$C$22)/Assumptions!$C$25 -> 197.10468
A13: TOTAL (Base) | B13: =SUM(B10:B12) -> 326426.3 | C13: =SUM(C10:C12) -> 2256810.8 | D13: =SUM(D10:D12) -> 4983256.5 | E13: Reconcile to SOTP | F13: ='Sum of Parts'!F31 -> 286216.31 | G13: 0.1 | I13: =MAX($D$6,MIN($E$6,_xlfn.NORM.INV(RAND(),$B$6,$C$6))) -> 0.094364506 | J13: =MAX($D$7,MIN($E$7,_xlfn.NORM.INV(RAND(),$B$7,$C$7))) -> 0.055 | K13: =RAND() -> 0.60988858 | L13: =RAND() -> 0.43465947 | M13: =RAND() -> 0.26954884 | N13: =(IF(K13<$E$10,$B$10,IF(K13<$E$10+$F$10,$C$10,$D$10))+IF(L13<$E$11,$B$11,IF(L13<$E$11+$F$11,$C$11,$D$11))+IF(M13<$E$12,$B$12,IF(M13<$E$12+$F$12,$C$12,$D$12)))*MIN(2.5,MAX(0.5,(0.09-0.04)/MAX(0.025,(I13-J13)))) -> 2835566.4 | O13: =(N13-Assumptions!$C$22)/Assumptions!$C$25 -> 210.61996
I14: =MAX($D$6,MIN($E$6,_xlfn.NORM.INV(RAND(),$B$6,$C$6))) -> 0.076443475 | J14: =MAX($D$7,MIN($E$7,_xlfn.NORM.INV(RAND(),$B$7,$C$7))) -> 0.040866936 | K14: =RAND() -> 0.61488375 | L14: =RAND() -> 0.068872772 | M14: =RAND() -> 0.33571401 | N14: =(IF(K14<$E$10,$B$10,IF(K14<$E$10+$F$10,$C$10,$D$10))+IF(L14<$E$11,$B$11,IF(L14<$E$11+$F$11,$C$11,$D$11))+IF(M14<$E$12,$B$12,IF(M14<$E$12+$F$12,$C$12,$D$12)))*MIN(2.5,MAX(0.5,(0.09-0.04)/MAX(0.025,(I14-J14)))) -> 2504288.5 | O14: =(N14-Assumptions!$C$22)/Assumptions!$C$25 -> 185.89772
A15: Note: Bear scenario above also embeds a 'speculative line write-off' option (probability of failure already inside materialization weights). | I15: =MAX($D$6,MIN($E$6,_xlfn.NORM.INV(RAND(),$B$6,$C$6))) -> 0.11930354 | J15: =MAX($D$7,MIN($E$7,_xlfn.NORM.INV(RAND(),$B$7,$C$7))) -> 0.046688356 | K15: =RAND() -> 0.433397 | L15: =RAND() -> 0.95290242 | M15: =RAND() -> 0.080175621 | N15: =(IF(K15<$E$10,$B$10,IF(K15<$E$10+$F$10,$C$10,$D$10))+IF(L15<$E$11,$B$11,IF(L15<$E$11+$F$11,$C$11,$D$11))+IF(M15<$E$12,$B$12,IF(M15<$E$12+$F$12,$C$12,$D$12)))*MIN(2.5,MAX(0.5,(0.09-0.04)/MAX(0.025,(I15-J15)))) -> 1944837.6 | O15: =(N15-Assumptions!$C$22)/Assumptions!$C$25 -> 144.14766
I16: =MAX($D$6,MIN($E$6,_xlfn.NORM.INV(RAND(),$B$6,$C$6))) -> 0.099800336 | J16: =MAX($D$7,MIN($E$7,_xlfn.NORM.INV(RAND(),$B$7,$C$7))) -> 0.038926882 | K16: =RAND() -> 0.80126146 | L16: =RAND() -> 0.3059207 | M16: =RAND() -> 0.16561512 | N16: =(IF(K16<$E$10,$B$10,IF(K16<$E$10+$F$10,$C$10,$D$10))+IF(L16<$E$11,$B$11,IF(L16<$E$11+$F$11,$C$11,$D$11))+IF(M16<$E$12,$B$12,IF(M16<$E$12+$F$12,$C$12,$D$12)))*MIN(2.5,MAX(0.5,(0.09-0.04)/MAX(0.025,(I16-J16)))) -> 3545414.1 | O16: =(N16-Assumptions!$C$22)/Assumptions!$C$25 -> 263.59366
A17: DISTRIBUTION OUTPUTS — 5,000 trials | B17: EV ($M) | C17: $/share | I17: =MAX($D$6,MIN($E$6,_xlfn.NORM.INV(RAND(),$B$6,$C$6))) -> 0.10605608 | J17: =MAX($D$7,MIN($E$7,_xlfn.NORM.INV(RAND(),$B$7,$C$7))) -> 0.04895497 | K17: =RAND() -> 0.77953765 | L17: =RAND() -> 0.37927813 | M17: =RAND() -> 0.30731473 | N17: =(IF(K17<$E$10,$B$10,IF(K17<$E$10+$F$10,$C$10,$D$10))+IF(L17<$E$11,$B$11,IF(L17<$E$11+$F$11,$C$11,$D$11))+IF(M17<$E$12,$B$12,IF(M17<$E$12+$F$12,$C$12,$D$12)))*MIN(2.5,MAX(0.5,(0.09-0.04)/MAX(0.025,(I17-J17)))) -> 1954789.9 | O17: =(N17-Assumptions!$C$22)/Assumptions!$C$25 -> 144.89036
A18: P10 (downside) | B18: =_xlfn.PERCENTILE.INC(N2:N5001,0.1) -> 710054.26 | C18: =_xlfn.PERCENTILE.INC(O2:O5001,0.1) -> 51.999646 | E18: HISTOGRAM (equal-width 250K bins; $M) | F18: Bin upper ($M) | G18: Count | I18: =MAX($D$6,MIN($E$6,_xlfn.NORM.INV(RAND(),$B$6,$C$6))) -> 0.06 | J18: =MAX($D$7,MIN($E$7,_xlfn.NORM.INV(RAND(),$B$7,$C$7))) -> 0.03675107 | K18: =RAND() -> 0.97801141 | L18: =RAND() -> 0.29041954 | M18: =RAND() -> 0.058774675 | N18: =(IF(K18<$E$10,$B$10,IF(K18<$E$10+$F$10,$C$10,$D$10))+IF(L18<$E$11,$B$11,IF(L18<$E$11+$F$11,$C$11,$D$11))+IF(M18<$E$12,$B$12,IF(M18<$E$12+$F$12,$C$12,$D$12)))*MIN(2.5,MAX(0.5,(0.09-0.04)/MAX(0.025,(I18-J18)))) -> 7731793.9 | O18: =(N18-Assumptions!$C$22)/Assumptions!$C$25 -> 576.01006
A19: P25 | B19: =_xlfn.PERCENTILE.INC(N2:N5001,0.25) -> 1511586.6 | C19: =_xlfn.PERCENTILE.INC(O2:O5001,0.25) -> 111.8155 | E19: Bin label | I19: =MAX($D$6,MIN($E$6,_xlfn.NORM.INV(RAND(),$B$6,$C$6))) -> 0.080391844 | J19: =MAX($D$7,MIN($E$7,_xlfn.NORM.INV(RAND(),$B$7,$C$7))) -> 0.046631409 | K19: =RAND() -> 0.014780255 | L19: =RAND() -> 0.061895892 | M19: =RAND() -> 0.87970147 | N19: =(IF(K19<$E$10,$B$10,IF(K19<$E$10+$F$10,$C$10,$D$10))+IF(L19<$E$11,$B$11,IF(L19<$E$11+$F$11,$C$11,$D$11))+IF(M19<$E$12,$B$12,IF(M19<$E$12+$F$12,$C$12,$D$12)))*MIN(2.5,MAX(0.5,(0.09-0.04)/MAX(0.025,(I19-J19)))) -> 519578.25 | O19: =(N19-Assumptions!$C$22)/Assumptions!$C$25 -> 37.785019
A20: P50 (median) | B20: =_xlfn.PERCENTILE.INC(N2:N5001,0.5) -> 2241300.2 | C20: =_xlfn.PERCENTILE.INC(O2:O5001,0.5) -> 166.27173 | E20: $0.00-0.25T | F20: 250000 | G20: =COUNTIFS($N$2:$N$5001,"<="&F20) -> 45 | I20: =MAX($D$6,MIN($E$6,_xlfn.NORM.INV(RAND(),$B$6,$C$6))) -> 0.085882192 | J20: =MAX($D$7,MIN($E$7,_xlfn.NORM.INV(RAND(),$B$7,$C$7))) -> 0.044212078 | K20: =RAND() -> 0.071814412 | L20: =RAND() -> 0.0093985021 | M20: =RAND() -> 0.40420126 | N20: =(IF(K20<$E$10,$B$10,IF(K20<$E$10+$F$10,$C$10,$D$10))+IF(L20<$E$11,$B$11,IF(L20<$E$11+$F$11,$C$11,$D$11))+IF(M20<$E$12,$B$12,IF(M20<$E$12+$F$12,$C$12,$D$12)))*MIN(2.5,MAX(0.5,(0.09-0.04)/MAX(0.025,(I20-J20)))) -> 391679.15 | O20: =(N20-Assumptions!$C$22)/Assumptions!$C$25 -> 28.24031
A21: Mean | B21: =AVERAGE(N2:N5001) -> 2620384.4 | C21: =AVERAGE(O2:O5001) -> 194.56159 | E21: $0.25-0.50T | F21: 500000 | G21: =COUNTIFS($N$2:$N$5001,"<="&F21,$N$2:$N$5001,">"&F20) -> 243 | I21: =MAX($D$6,MIN($E$6,_xlfn.NORM.INV(RAND(),$B$6,$C$6))) -> 0.10462928 | J21: =MAX($D$7,MIN($E$7,_xlfn.NORM.INV(RAND(),$B$7,$C$7))) -> 0.046494399 | K21: =RAND() -> 0.53087413 | L21: =RAND() -> 0.84746876 | M21: =RAND() -> 0.43767438 | N21: =(IF(K21<$E$10,$B$10,IF(K21<$E$10+$F$10,$C$10,$D$10))+IF(L21<$E$11,$B$11,IF(L21<$E$11+$F$11,$C$11,$D$11))+IF(M21<$E$12,$B$12,IF(M21<$E$12+$F$12,$C$12,$D$12)))*MIN(2.5,MAX(0.5,(0.09-0.04)/MAX(0.025,(I21-J21)))) -> 2429260 | O21: =(N21-Assumptions!$C$22)/Assumptions!$C$25 -> 180.29858
A22: P75 | B22: =_xlfn.PERCENTILE.INC(N2:N5001,0.75) -> 3466701.4 | C22: =_xlfn.PERCENTILE.INC(O2:O5001,0.75) -> 257.71958 | E22: $0.50-0.75T | F22: 750000 | G22: =COUNTIFS($N$2:$N$5001,"<="&F22,$N$2:$N$5001,">"&F21) -> 236 | I22: =MAX($D$6,MIN($E$6,_xlfn.NORM.INV(RAND(),$B$6,$C$6))) -> 0.088222057 | J22: =MAX($D$7,MIN($E$7,_xlfn.NORM.INV(RAND(),$B$7,$C$7))) -> 0.036707529 | K22: =RAND() -> 0.50944406 | L22: =RAND() -> 0.099187561 | M22: =RAND() -> 0.065790875 | N22: =(IF(K22<$E$10,$B$10,IF(K22<$E$10+$F$10,$C$10,$D$10))+IF(L22<$E$11,$B$11,IF(L22<$E$11+$F$11,$C$11,$D$11))+IF(M22<$E$12,$B$12,IF(M22<$E$12+$F$12,$C$12,$D$12)))*MIN(2.5,MAX(0.5,(0.09-0.04)/MAX(0.025,(I22-J22)))) -> 1729491.1 | O22: =(N22-Assumptions!$C$22)/Assumptions!$C$25 -> 128.07702
A23: P90 (upside) | B23: =_xlfn.PERCENTILE.INC(N2:N5001,0.9) -> 4733118.2 | C23: =_xlfn.PERCENTILE.INC(O2:O5001,0.9) -> 352.2283 | E23: $0.75-1.00T | F23: 1000000 | G23: =COUNTIFS($N$2:$N$5001,"<="&F23,$N$2:$N$5001,">"&F22) -> 184 | I23: =MAX($D$6,MIN($E$6,_xlfn.NORM.INV(RAND(),$B$6,$C$6))) -> 0.084790669 | J23: =MAX($D$7,MIN($E$7,_xlfn.NORM.INV(RAND(),$B$7,$C$7))) -> 0.031048088 | K23: =RAND() -> 0.13306 | L23: =RAND() -> 0.9984549 | M23: =RAND() -> 0.28338326 | N23: =(IF(K23<$E$10,$B$10,IF(K23<$E$10+$F$10,$C$10,$D$10))+IF(L23<$E$11,$B$11,IF(L23<$E$11+$F$11,$C$11,$D$11))+IF(M23<$E$12,$B$12,IF(M23<$E$12+$F$12,$C$12,$D$12)))*MIN(2.5,MAX(0.5,(0.09-0.04)/MAX(0.025,(I23-J23)))) -> 1273704.1 | O23: =(N23-Assumptions!$C$22)/Assumptions!$C$25 -> 94.063065
A24: Stdev | B24: =_xlfn.STDEV.S(N2:N5001) -> 1698263.1 | C24: =_xlfn.STDEV.S(O2:O5001) -> 126.73605 | E24: $1.00-1.25T | F24: 1250000 | G24: =COUNTIFS($N$2:$N$5001,"<="&F24,$N$2:$N$5001,">"&F23) -> 218 | I24: =MAX($D$6,MIN($E$6,_xlfn.NORM.INV(RAND(),$B$6,$C$6))) -> 0.093106003 | J24: =MAX($D$7,MIN($E$7,_xlfn.NORM.INV(RAND(),$B$7,$C$7))) -> 0.02936945 | K24: =RAND() -> 0.45028213 | L24: =RAND() -> 0.79311309 | M24: =RAND() -> 0.12641255 | N24: =(IF(K24<$E$10,$B$10,IF(K24<$E$10+$F$10,$C$10,$D$10))+IF(L24<$E$11,$B$11,IF(L24<$E$11+$F$11,$C$11,$D$11))+IF(M24<$E$12,$B$12,IF(M24<$E$12+$F$12,$C$12,$D$12)))*MIN(2.5,MAX(0.5,(0.09-0.04)/MAX(0.025,(I24-J24)))) -> 1751281.9 | O24: =(N24-Assumptions!$C$22)/Assumptions!$C$25 -> 129.7032
A25: Prob(EV < $1.25T merger value) | B25: =COUNTIF(N2:N5001,"<1250000")/5000 -> 0.1852 | E25: $1.25-1.50T | F25: 1500000 | G25: =COUNTIFS($N$2:$N$5001,"<="&F25,$N$2:$N$5001,">"&F24) -> 299 | I25: =MAX($D$6,MIN($E$6,_xlfn.NORM.INV(RAND(),$B$6,$C$6))) -> 0.086599605 | J25: =MAX($D$7,MIN($E$7,_xlfn.NORM.INV(RAND(),$B$7,$C$7))) -> 0.05019762 | K25: =RAND() -> 0.71962089 | L25: =RAND() -> 0.43124403 | M25: =RAND() -> 0.35889477 | N25: =(IF(K25<$E$10,$B$10,IF(K25<$E$10+$F$10,$C$10,$D$10))+IF(L25<$E$11,$B$11,IF(L25<$E$11+$F$11,$C$11,$D$11))+IF(M25<$E$12,$B$12,IF(M25<$E$12+$F$12,$C$12,$D$12)))*MIN(2.5,MAX(0.5,(0.09-0.04)/MAX(0.025,(I25-J25)))) -> 3066334.7 | O25: =(N25-Assumptions!$C$22)/Assumptions!$C$25 -> 227.84147
A26: Prob(EV > $2.0T high IPO target) | B26: =COUNTIF(N2:N5001,">2000000")/5000 -> 0.5738 | E26: $1.50-1.75T | F26: 1750000 | G26: =COUNTIFS($N$2:$N$5001,"<="&F26,$N$2:$N$5001,">"&F25) -> 462 | I26: =MAX($D$6,MIN($E$6,_xlfn.NORM.INV(RAND(),$B$6,$C$6))) -> 0.088036825 | J26: =MAX($D$7,MIN($E$7,_xlfn.NORM.INV(RAND(),$B$7,$C$7))) -> 0.041785395 | K26: =RAND() -> 0.056178295 | L26: =RAND() -> 0.40392158 | M26: =RAND() -> 0.71741868 | N26: =(IF(K26<$E$10,$B$10,IF(K26<$E$10+$F$10,$C$10,$D$10))+IF(L26<$E$11,$B$11,IF(L26<$E$11+$F$11,$C$11,$D$11))+IF(M26<$E$12,$B$12,IF(M26<$E$12+$F$12,$C$12,$D$12)))*MIN(2.5,MAX(0.5,(0.09-0.04)/MAX(0.025,(I26-J26)))) -> 866307.07 | O26: =(N26-Assumptions!$C$22)/Assumptions!$C$25 -> 63.660304
E27: $1.75-2.00T | F27: 2000000 | G27: =COUNTIFS($N$2:$N$5001,"<="&F27,$N$2:$N$5001,">"&F26) -> 444 | I27: =MAX($D$6,MIN($E$6,_xlfn.NORM.INV(RAND(),$B$6,$C$6))) -> 0.081694123 | J27: =MAX($D$7,MIN($E$7,_xlfn.NORM.INV(RAND(),$B$7,$C$7))) -> 0.039097869 | K27: =RAND() -> 0.53911406 | L27: =RAND() -> 0.64348658 | M27: =RAND() -> 0.50643247 | N27: =(IF(K27<$E$10,$B$10,IF(K27<$E$10+$F$10,$C$10,$D$10))+IF(L27<$E$11,$B$11,IF(L27<$E$11+$F$11,$C$11,$D$11))+IF(M27<$E$12,$B$12,IF(M27<$E$12+$F$12,$C$12,$D$12)))*MIN(2.5,MAX(0.5,(0.09-0.04)/MAX(0.025,(I27-J27)))) -> 2620433.9 | O27: =(N27-Assumptions!$C$22)/Assumptions!$C$25 -> 194.56529
E28: $2.00-2.25T | F28: 2250000 | G28: =COUNTIFS($N$2:$N$5001,"<="&F28,$N$2:$N$5001,">"&F27) -> 386 | I28: =MAX($D$6,MIN($E$6,_xlfn.NORM.INV(RAND(),$B$6,$C$6))) -> 0.10369677 | J28: =MAX($D$7,MIN($E$7,_xlfn.NORM.INV(RAND(),$B$7,$C$7))) -> 0.048551842 | K28: =RAND() -> 0.12431192 | L28: =RAND() -> 0.45615801 | M28: =RAND() -> 0.70246147 | N28: =(IF(K28<$E$10,$B$10,IF(K28<$E$10+$F$10,$C$10,$D$10))+IF(L28<$E$11,$B$11,IF(L28<$E$11+$F$11,$C$11,$D$11))+IF(M28<$E$12,$B$12,IF(M28<$E$12+$F$12,$C$12,$D$12)))*MIN(2.5,MAX(0.5,(0.09-0.04)/MAX(0.025,(I28-J28)))) -> 726593.4 | O28: =(N28-Assumptions!$C$22)/Assumptions!$C$25 -> 53.23391
E29: $2.25-2.50T | F29: 2500000 | G29: =COUNTIFS($N$2:$N$5001,"<="&F29,$N$2:$N$5001,">"&F28) -> 326 | I29: =MAX($D$6,MIN($E$6,_xlfn.NORM.INV(RAND(),$B$6,$C$6))) -> 0.084920912 | J29: =MAX($D$7,MIN($E$7,_xlfn.NORM.INV(RAND(),$B$7,$C$7))) -> 0.042846009 | K29: =RAND() -> 0.62544583 | L29: =RAND() -> 0.085902358 | M29: =RAND() -> 0.29034297 | N29: =(IF(K29<$E$10,$B$10,IF(K29<$E$10+$F$10,$C$10,$D$10))+IF(L29<$E$11,$B$11,IF(L29<$E$11+$F$11,$C$11,$D$11))+IF(M29<$E$12,$B$12,IF(M29<$E$12+$F$12,$C$12,$D$12)))*MIN(2.5,MAX(0.5,(0.09-0.04)/MAX(0.025,(I29-J29)))) -> 2117507.4 | O29: =(N29-Assumptions!$C$22)/Assumptions!$C$25 -> 157.03346
E30: $2.50-2.75T | F30: 2750000 | G30: =COUNTIFS($N$2:$N$5001,"<="&F30,$N$2:$N$5001,">"&F29) -> 285 | I30: =MAX($D$6,MIN($E$6,_xlfn.NORM.INV(RAND(),$B$6,$C$6))) -> 0.10479354 | J30: =MAX($D$7,MIN($E$7,_xlfn.NORM.INV(RAND(),$B$7,$C$7))) -> 0.051822604 | K30: =RAND() -> 0.87668492 | L30: =RAND() -> 0.89084238 | M30: =RAND() -> 0.70887135 | N30: =(IF(K30<$E$10,$B$10,IF(K30<$E$10+$F$10,$C$10,$D$10))+IF(L30<$E$11,$B$11,IF(L30<$E$11+$F$11,$C$11,$D$11))+IF(M30<$E$12,$B$12,IF(M30<$E$12+$F$12,$C$12,$D$12)))*MIN(2.5,MAX(0.5,(0.09-0.04)/MAX(0.025,(I30-J30)))) -> 4656242.6 | O30: =(N30-Assumptions!$C$22)/Assumptions!$C$25 -> 346.49131
E31: $2.75-3.00T | F31: 3000000 | G31: =COUNTIFS($N$2:$N$5001,"<="&F31,$N$2:$N$5001,">"&F30) -> 239 | I31: =MAX($D$6,MIN($E$6,_xlfn.NORM.INV(RAND(),$B$6,$C$6))) -> 0.067453939 | J31: =MAX($D$7,MIN($E$7,_xlfn.NORM.INV(RAND(),$B$7,$C$7))) -> 0.048768334 | K31: =RAND() -> 0.40381451 | L31: =RAND() -> 0.5039653 | M31: =RAND() -> 0.59893832 | N31: =(IF(K31<$E$10,$B$10,IF(K31<$E$10+$F$10,$C$10,$D$10))+IF(L31<$E$11,$B$11,IF(L31<$E$11+$F$11,$C$11,$D$11))+IF(M31<$E$12,$B$12,IF(M31<$E$12+$F$12,$C$12,$D$12)))*MIN(2.5,MAX(0.5,(0.09-0.04)/MAX(0.025,(I31-J31)))) -> 4464826.8 | O31: =(N31-Assumptions!$C$22)/Assumptions!$C$25 -> 332.20655
E32: $3.00-3.25T | F32: 3250000 | G32: =COUNTIFS($N$2:$N$5001,"<="&F32,$N$2:$N$5001,">"&F31) -> 221 | I32: =MAX($D$6,MIN($E$6,_xlfn.NORM.INV(RAND(),$B$6,$C$6))) -> 0.10489451 | J32: =MAX($D$7,MIN($E$7,_xlfn.NORM.INV(RAND(),$B$7,$C$7))) -> 0.03273399 | K32: =RAND() -> 0.69276728 | L32: =RAND() -> 0.87668835 | M32: =RAND() -> 0.50635301 | N32: =(IF(K32<$E$10,$B$10,IF(K32<$E$10+$F$10,$C$10,$D$10))+IF(L32<$E$11,$B$11,IF(L32<$E$11+$F$11,$C$11,$D$11))+IF(M32<$E$12,$B$12,IF(M32<$E$12+$F$12,$C$12,$D$12)))*MIN(2.5,MAX(0.5,(0.09-0.04)/MAX(0.025,(I32-J32)))) -> 1957091.6 | O32: =(N32-Assumptions!$C$22)/Assumptions!$C$25 -> 145.06213
E33: $3.25-3.50T | F33: 3500000 | G33: =COUNTIFS($N$2:$N$5001,"<="&F33,$N$2:$N$5001,">"&F32) -> 189 | I33: =MAX($D$6,MIN($E$6,_xlfn.NORM.INV(RAND(),$B$6,$C$6))) -> 0.074170977 | J33: =MAX($D$7,MIN($E$7,_xlfn.NORM.INV(RAND(),$B$7,$C$7))) -> 0.039963975 | K33: =RAND() -> 0.13642616 | L33: =RAND() -> 0.21498166 | M33: =RAND() -> 0.21738423 | N33: =(IF(K33<$E$10,$B$10,IF(K33<$E$10+$F$10,$C$10,$D$10))+IF(L33<$E$11,$B$11,IF(L33<$E$11+$F$11,$C$11,$D$11))+IF(M33<$E$12,$B$12,IF(M33<$E$12+$F$12,$C$12,$D$12)))*MIN(2.5,MAX(0.5,(0.09-0.04)/MAX(0.025,(I33-J33)))) -> 477133.74 | O33: =(N33-Assumptions!$C$22)/Assumptions!$C$25 -> 34.617518
E34: $3.50-3.75T | F34: 3750000 | G34: =COUNTIFS($N$2:$N$5001,"<="&F34,$N$2:$N$5001,">"&F33) -> 249 | I34: =MAX($D$6,MIN($E$6,_xlfn.NORM.INV(RAND(),$B$6,$C$6))) -> 0.098213057 | J34: =MAX($D$7,MIN($E$7,_xlfn.NORM.INV(RAND(),$B$7,$C$7))) -> 0.04781567 | K34: =RAND() -> 0.2701586 | L34: =RAND() -> 0.67484025 | M34: =RAND() -> 0.47529201 | N34: =(IF(K34<$E$10,$B$10,IF(K34<$E$10+$F$10,$C$10,$D$10))+IF(L34<$E$11,$B$11,IF(L34<$E$11+$F$11,$C$11,$D$11))+IF(M34<$E$12,$B$12,IF(M34<$E$12+$F$12,$C$12,$D$12)))*MIN(2.5,MAX(0.5,(0.09-0.04)/MAX(0.025,(I34-J34)))) -> 2214810.7 | O34: =(N34-Assumptions!$C$22)/Assumptions!$C$25 -> 164.2949
E35: $3.75-4.00T | F35: 4000000 | G35: =COUNTIFS($N$2:$N$5001,"<="&F35,$N$2:$N$5001,">"&F34) -> 113 | I35: =MAX($D$6,MIN($E$6,_xlfn.NORM.INV(RAND(),$B$6,$C$6))) -> 0.10153173 | J35: =MAX($D$7,MIN($E$7,_xlfn.NORM.INV(RAND(),$B$7,$C$7))) -> 0.031563077 | K35: =RAND() -> 0.772277 | L35: =RAND() -> 0.56029911 | M35: =RAND() -> 0.77303148 | N35: =(IF(K35<$E$10,$B$10,IF(K35<$E$10+$F$10,$C$10,$D$10))+IF(L35<$E$11,$B$11,IF(L35<$E$11+$F$11,$C$11,$D$11))+IF(M35<$E$12,$B$12,IF(M35<$E$12+$F$12,$C$12,$D$12)))*MIN(2.5,MAX(0.5,(0.09-0.04)/MAX(0.025,(I35-J35)))) -> 1612730.1 | O35: =(N35-Assumptions!$C$22)/Assumptions!$C$25 -> 119.36351
E36: $4.00-4.25T | F36: 4250000 | G36: =COUNTIFS($N$2:$N$5001,"<="&F36,$N$2:$N$5001,">"&F35) -> 111 | I36: =MAX($D$6,MIN($E$6,_xlfn.NORM.INV(RAND(),$B$6,$C$6))) -> 0.086207433 | J36: =MAX($D$7,MIN($E$7,_xlfn.NORM.INV(RAND(),$B$7,$C$7))) -> 0.040331366 | K36: =RAND() -> 0.058989432 | L36: =RAND() -> 0.38142285 | M36: =RAND() -> 0.19331686 | N36: =(IF(K36<$E$10,$B$10,IF(K36<$E$10+$F$10,$C$10,$D$10))+IF(L36<$E$11,$B$11,IF(L36<$E$11+$F$11,$C$11,$D$11))+IF(M36<$E$12,$B$12,IF(M36<$E$12+$F$12,$C$12,$D$12)))*MIN(2.5,MAX(0.5,(0.09-0.04)/MAX(0.025,(I36-J36)))) -> 846804.67 | O36: =(N36-Assumptions!$C$22)/Assumptions!$C$25 -> 62.204901
E37: $4.25-4.50T | F37: 4500000 | G37: =COUNTIFS($N$2:$N$5001,"<="&F37,$N$2:$N$5001,">"&F36) -> 168 | I37: =MAX($D$6,MIN($E$6,_xlfn.NORM.INV(RAND(),$B$6,$C$6))) -> 0.10419748 | J37: =MAX($D$7,MIN($E$7,_xlfn.NORM.INV(RAND(),$B$7,$C$7))) -> 0.04595135 | K37: =RAND() -> 0.37278633 | L37: =RAND() -> 0.90156746 | M37: =RAND() -> 0.059915786 | N37: =(IF(K37<$E$10,$B$10,IF(K37<$E$10+$F$10,$C$10,$D$10))+IF(L37<$E$11,$B$11,IF(L37<$E$11+$F$11,$C$11,$D$11))+IF(M37<$E$12,$B$12,IF(M37<$E$12+$F$12,$C$12,$D$12)))*MIN(2.5,MAX(0.5,(0.09-0.04)/MAX(0.025,(I37-J37)))) -> 2424620.3 | O37: =(N37-Assumptions!$C$22)/Assumptions!$C$25 -> 179.95234
E38: $4.50-4.75T | F38: 4750000 | G38: =COUNTIFS($N$2:$N$5001,"<="&F38,$N$2:$N$5001,">"&F37) -> 85 | I38: =MAX($D$6,MIN($E$6,_xlfn.NORM.INV(RAND(),$B$6,$C$6))) -> 0.07887831 | J38: =MAX($D$7,MIN($E$7,_xlfn.NORM.INV(RAND(),$B$7,$C$7))) -> 0.02562574 | K38: =RAND() -> 0.12828747 | L38: =RAND() -> 0.82142985 | M38: =RAND() -> 0.99785878 | N38: =(IF(K38<$E$10,$B$10,IF(K38<$E$10+$F$10,$C$10,$D$10))+IF(L38<$E$11,$B$11,IF(L38<$E$11+$F$11,$C$11,$D$11))+IF(M38<$E$12,$B$12,IF(M38<$E$12+$F$12,$C$12,$D$12)))*MIN(2.5,MAX(0.5,(0.09-0.04)/MAX(0.025,(I38-J38)))) -> 1355602 | O38: =(N38-Assumptions!$C$22)/Assumptions!$C$25 -> 100.17485
... E59: $9.75-10.00T | F59: 10000000 | G59: =COUNTIFS($N$2:$N$5001,"<="&F59,$N$2:$N$5001,">"&F58) -> 12 | I59: =MAX($D$6,MIN($E$6,_xlfn.NORM.INV(RAND(),$B$6,$C$6))) -> 0.085194891 | J59: =MAX($D$7,MIN($E$7,_xlfn.NORM.INV(RAND(),$B$7,$C$7))) -> 0.038547824 | K59: =RAND() -> 0.35247752 | L59: =RAND() -> 0.63095019 | M59: =RAND() -> 0.51321359 | N59: =(IF(K59<$E$10,$B$10,IF(K59<$E$10+$F$10,$C$10,$D$10))+IF(L59<$E$11,$B$11,IF(L59<$E$11+$F$11,$C$11,$D$11))+IF(M59<$E$12,$B$12,IF(M59<$E$12+$F$12,$C$12,$D$12)))*MIN(2.5,MAX(0.5,(0.09-0.04)/MAX(0.025,(I59-J59)))) -> 2392876.5 | O59: =(N59-Assumptions!$C$22)/Assumptions!$C$25 -> 177.58339
E60: >$10T | F60: 100000000 | G60: =COUNTIFS($N$2:$N$5001,">"&F59) -> 0 | I60: =MAX($D$6,MIN($E$6,_xlfn.NORM.INV(RAND(),$B$6,$C$6))) -> 0.098540359 | J60: =MAX($D$7,MIN($E$7,_xlfn.NORM.INV(RAND(),$B$7,$C$7))) -> 0.046416117 | K60: =RAND() -> 0.23392267 | L60: =RAND() -> 0.16785159 | M60: =RAND() -> 0.011076954 | N60: =(IF(K60<$E$10,$B$10,IF(K60<$E$10+$F$10,$C$10,$D$10))+IF(L60<$E$11,$B$11,IF(L60<$E$11+$F$11,$C$11,$D$11))+IF(M60<$E$12,$B$12,IF(M60<$E$12+$F$12,$C$12,$D$12)))*MIN(2.5,MAX(0.5,(0.09-0.04)/MAX(0.025,(I60-J60)))) -> 1709260.7 | O60: =(N60-Assumptions!$C$22)/Assumptions!$C$25 -> 126.56729
I61: =MAX($D$6,MIN($E$6,_xlfn.NORM.INV(RAND(),$B$6,$C$6))) -> 0.13464681 | J61: =MAX($D$7,MIN($E$7,_xlfn.NORM.INV(RAND(),$B$7,$C$7))) -> 0.044565543 | K61: =RAND() -> 0.027658224 | L61: =RAND() -> 0.049400843 | M61: =RAND() -> 0.18949011 | N61: =(IF(K61<$E$10,$B$10,IF(K61<$E$10+$F$10,$C$10,$D$10))+IF(L61<$E$11,$B$11,IF(L61<$E$11+$F$11,$C$11,$D$11))+IF(M61<$E$12,$B$12,IF(M61<$E$12+$F$12,$C$12,$D$12)))*MIN(2.5,MAX(0.5,(0.09-0.04)/MAX(0.025,(I61-J61)))) -> 181184.34 | O61: =(N61-Assumptions!$C$22)/Assumptions!$C$25 -> 12.531742
I62: =MAX($D$6,MIN($E$6,_xlfn.NORM.INV(RAND(),$B$6,$C$6))) -> 0.10464018 | J62: =MAX($D$7,MIN($E$7,_xlfn.NORM.INV(RAND(),$B$7,$C$7))) -> 0.045957431 | K62: =RAND() -> 0.46645503 | L62: =RAND() -> 0.42115085 | M62: =RAND() -> 0.96135271 | N62: =(IF(K62<$E$10,$B$10,IF(K62<$E$10+$F$10,$C$10,$D$10))+IF(L62<$E$11,$B$11,IF(L62<$E$11+$F$11,$C$11,$D$11))+IF(M62<$E$12,$B$12,IF(M62<$E$12+$F$12,$C$12,$D$12)))*MIN(2.5,MAX(0.5,(0.09-0.04)/MAX(0.025,(I62-J62)))) -> 1965787.6 | O62: =(N62-Assumptions!$C$22)/Assumptions!$C$25 -> 145.71109
I63: =MAX($D$6,MIN($E$6,_xlfn.NORM.INV(RAND(),$B$6,$C$6))) -> 0.098197046 | J63: =MAX($D$7,MIN($E$7,_xlfn.NORM.INV(RAND(),$B$7,$C$7))) -> 0.045035339 | K63: =RAND() -> 0.59608097 | L63: =RAND() -> 0.98343924 | M63: =RAND() -> 0.72587353 | N63: =(IF(K63<$E$10,$B$10,IF(K63<$E$10+$F$10,$C$10,$D$10))+IF(L63<$E$11,$B$11,IF(L63<$E$11+$F$11,$C$11,$D$11))+IF(M63<$E$12,$B$12,IF(M63<$E$12+$F$12,$C$12,$D$12)))*MIN(2.5,MAX(0.5,(0.09-0.04)/MAX(0.025,(I63-J63)))) -> 2679459.1 | O63: =(N63-Assumptions!$C$22)/Assumptions!$C$25 -> 198.97015
I64: =MAX($D$6,MIN($E$6,_xlfn.NORM.INV(RAND(),$B$6,$C$6))) -> 0.089233381 | J64: =MAX($D$7,MIN($E$7,_xlfn.NORM.INV(RAND(),$B$7,$C$7))) -> 0.040125186 | K64: =RAND() -> 0.12037086 | L64: =RAND() -> 0.11243943 | M64: =RAND() -> 0.10434518 | N64: =(IF(K64<$E$10,$B$10,IF(K64<$E$10+$F$10,$C$10,$D$10))+IF(L64<$E$11,$B$11,IF(L64<$E$11+$F$11,$C$11,$D$11))+IF(M64<$E$12,$B$12,IF(M64<$E$12+$F$12,$C$12,$D$12)))*MIN(2.5,MAX(0.5,(0.09-0.04)/MAX(0.025,(I64-J64)))) -> 332354.2 | O64: =(N64-Assumptions!$C$22)/Assumptions!$C$25 -> 23.813075
I65: =MAX($D$6,MIN($E$6,_xlfn.NORM.INV(RAND(),$B$6,$C$6))) -> 0.074000274 | J65: =MAX($D$7,MIN($E$7,_xlfn.NORM.INV(RAND(),$B$7,$C$7))) -> 0.031676997 | K65: =RAND() -> 0.8349993 | L65: =RAND() -> 0.97217448 | M65: =RAND() -> 0.19264482 | N65: =(IF(K65<$E$10,$B$10,IF(K65<$E$10+$F$10,$C$10,$D$10))+IF(L65<$E$11,$B$11,IF(L65<$E$11+$F$11,$C$11,$D$11))+IF(M65<$E$12,$B$12,IF(M65<$E$12+$F$12,$C$12,$D$12)))*MIN(2.5,MAX(0.5,(0.09-0.04)/MAX(0.025,(I65-J65)))) -> 5798834.4 | O65: =(N65-Assumptions!$C$22)/Assumptions!$C$25 -> 431.75936
I66: =MAX($D$6,MIN($E$6,_xlfn.NORM.INV(RAND(),$B$6,$C$6))) -> 0.084636477 | J66: =MAX($D$7,MIN($E$7,_xlfn.NORM.INV(RAND(),$B$7,$C$7))) -> 0.022840959 | K66: =RAND() -> 0.11164029 | L66: =RAND() -> 0.73082488 | M66: =RAND() -> 0.30659015 | N66: =(IF(K66<$E$10,$B$10,IF(K66<$E$10+$F$10,$C$10,$D$10))+IF(L66<$E$11,$B$11,IF(L66<$E$11+$F$11,$C$11,$D$11))+IF(M66<$E$12,$B$12,IF(M66<$E$12+$F$12,$C$12,$D$12)))*MIN(2.5,MAX(0.5,(0.09-0.04)/MAX(0.025,(I66-J66)))) -> 628655.1 | O66: =(N66-Assumptions!$C$22)/Assumptions!$C$25 -> 45.925082
I67: =MAX($D$6,MIN($E$6,_xlfn.NORM.INV(RAND(),$B$6,$C$6))) -> 0.085402209 | J67: =MAX($D$7,MIN($E$7,_xlfn.NORM.INV(RAND(),$B$7,$C$7))) -> 0.042795329 | K67: =RAND() -> 0.058386774 | L67: =RAND() -> 0.89205224 | M67: =RAND() -> 0.47679743 | N67: =(IF(K67<$E$10,$B$10,IF(K67<$E$10+$F$10,$C$10,$D$10))+IF(L67<$E$11,$B$11,IF(L67<$E$11+$F$11,$C$11,$D$11))+IF(M67<$E$12,$B$12,IF(M67<$E$12+$F$12,$C$12,$D$12)))*MIN(2.5,MAX(0.5,(0.09-0.04)/MAX(0.025,(I67-J67)))) -> 1606598.4 | O67: =(N67-Assumptions!$C$22)/Assumptions!$C$25 -> 118.90592
I68: =MAX($D$6,MIN($E$6,_xlfn.NORM.INV(RAND(),$B$6,$C$6))) -> 0.088218959 | J68: =MAX($D$7,MIN($E$7,_xlfn.NORM.INV(RAND(),$B$7,$C$7))) -> 0.03546976 | K68: =RAND() -> 0.64834165 | L68: =RAND() -> 0.86183323 | M68: =RAND() -> 0.13983727 | N68: =(IF(K68<$E$10,$B$10,IF(K68<$E$10+$F$10,$C$10,$D$10))+IF(L68<$E$11,$B$11,IF(L68<$E$11+$F$11,$C$11,$D$11))+IF(M68<$E$12,$B$12,IF(M68<$E$12+$F$12,$C$12,$D$12)))*MIN(2.5,MAX(0.5,(0.09-0.04)/MAX(0.025,(I68-J68)))) -> 2677287 | O68: =(N68-Assumptions!$C$22)/Assumptions!$C$25 -> 198.80806
I69: =MAX($D$6,MIN($E$6,_xlfn.NORM.INV(RAND(),$B$6,$C$6))) -> 0.10397635 | J69: =MAX($D$7,MIN($E$7,_xlfn.NORM.INV(RAND(),$B$7,$C$7))) -> 0.034960613 | K69: =RAND() -> 0.12574829 | L69: =RAND() -> 0.61542946 | M69: =RAND() -> 0.49459767 | N69: =(IF(K69<$E$10,$B$10,IF(K69<$E$10+$F$10,$C$10,$D$10))+IF(L69<$E$11,$B$11,IF(L69<$E$11+$F$11,$C$11,$D$11))+IF(M69<$E$12,$B$12,IF(M69<$E$12+$F$12,$C$12,$D$12)))*MIN(2.5,MAX(0.5,(0.09-0.04)/MAX(0.025,(I69-J69)))) -> 562887.11 | O69: =(N69-Assumptions!$C$22)/Assumptions!$C$25 -> 41.017023
I70: =MAX($D$6,MIN($E$6,_xlfn.NORM.INV(RAND(),$B$6,$C$6))) -> 0.069669195 | J70: =MAX($D$7,MIN($E$7,_xlfn.NORM.INV(RAND(),$B$7,$C$7))) -> 0.042008112 | K70: =RAND() -> 0.57530095 | L70: =RAND() -> 0.036673625 | M70: =RAND() -> 0.80183271 | N70: =(IF(K70<$E$10,$B$10,IF(K70<$E$10+$F$10,$C$10,$D$10))+IF(L70<$E$11,$B$11,IF(L70<$E$11+$F$11,$C$11,$D$11))+IF(M70<$E$12,$B$12,IF(M70<$E$12+$F$12,$C$12,$D$12)))*MIN(2.5,MAX(0.5,(0.09-0.04)/MAX(0.025,(I70-J70)))) -> 3265012.8 | O70: =(N70-Assumptions!$C$22)/Assumptions!$C$25 -> 242.66819
I71: =MAX($D$6,MIN($E$6,_xlfn.NORM.INV(RAND(),$B$6,$C$6))) -> 0.11012096 | J71: =MAX($D$7,MIN($E$7,_xlfn.NORM.INV(RAND(),$B$7,$C$7))) -> 0.02 | K71: =RAND() -> 0.062411892 | L71: =RAND() -> 0.17052012 | M71: =RAND() -> 0.16486262 | N71: =(IF(K71<$E$10,$B$10,IF(K71<$E$10+$F$10,$C$10,$D$10))+IF(L71<$E$11,$B$11,IF(L71<$E$11+$F$11,$C$11,$D$11))+IF(M71<$E$12,$B$12,IF(M71<$E$12+$F$12,$C$12,$D$12)))*MIN(2.5,MAX(0.5,(0.09-0.04)/MAX(0.025,(I71-J71)))) -> 181104.54 | O71: =(N71-Assumptions!$C$22)/Assumptions!$C$25 -> 12.525787
I72: =MAX($D$6,MIN($E$6,_xlfn.NORM.INV(RAND(),$B$6,$C$6))) -> 0.12007512 | J72: =MAX($D$7,MIN($E$7,_xlfn.NORM.INV(RAND(),$B$7,$C$7))) -> 0.044177891 | K72: =RAND() -> 0.83859317 | L72: =RAND() -> 0.63184443 | M72: =RAND() -> 0.27553066 | N72: =(IF(K72<$E$10,$B$10,IF(K72<$E$10+$F$10,$C$10,$D$10))+IF(L72<$E$11,$B$11,IF(L72<$E$11+$F$11,$C$11,$D$11))+IF(M72<$E$12,$B$12,IF(M72<$E$12+$F$12,$C$12,$D$12)))*MIN(2.5,MAX(0.5,(0.09-0.04)/MAX(0.025,(I72-J72)))) -> 2843603.2 | O72: =(N72-Assumptions!$C$22)/Assumptions!$C$25 -> 211.21972
... I5001: =MAX($D$6,MIN($E$6,_xlfn.NORM.INV(RAND(),$B$6,$C$6))) -> 0.08393935 | J5001: =MAX($D$7,MIN($E$7,_xlfn.NORM.INV(RAND(),$B$7,$C$7))) -> 0.045705817 | K5001: =RAND() -> 0.37728548 | L5001: =RAND() -> 0.43921384 | M5001: =RAND() -> 0.10701772 | N5001: =(IF(K5001<$E$10,$B$10,IF(K5001<$E$10+$F$10,$C$10,$D$10))+IF(L5001<$E$11,$B$11,IF(L5001<$E$11+$F$11,$C$11,$D$11))+IF(M5001<$E$12,$B$12,IF(M5001<$E$12+$F$12,$C$12,$D$12)))*MIN(2.5,MAX(0.5,(0.09-0.04)/MAX(0.025,(I5001-J5001)))) -> 2919444.3 | O5001: =(N5001-Assumptions!$C$22)/Assumptions!$C$25 -> 216.8795

Sheet Comps
B2: COMPARABLE COMPANIES — Trading & Transaction
B5: Green = closest conceputal comparables
B6: TRADING COMPARABLES
B7: Company | C7: Bucket | D7: Mkt Cap ($Bn) | E7: Ent. Val ($Bn) | F7: Rev (LTM, $Bn) | G7: EBITDA (LTM, $Bn) | H7: EV/Revenue | I7: EV/EBITDA | J7: Rev growth (YoY) | K7: Source / Notes
B8: AI / High-growth Hardware
B9: NVIDIA | C9: AI compute | D9: 4250 | E9: 4200 | F9: 195.5 | G9: 132 | H9: =E9/F9 -> 21.483376 | I9: =E9/G9 -> 31.818182 | J9: 0.62 | K9: FY26 LTM Q3 rev $195.5B (4 qtrs), EBITDA ~67% margin per 10-Qs; SEC EDGAR. Market cap approx Q1 2026.
B10: Tesla | C10: Mobility / energy | D10: 1150 | E10: 1130 | F10: 98 | G10: 14.7 | H10: =E10/F10 -> 11.530612 | I10: =E10/G10 -> 76.870748 | J10: 0.05 | K10: 2024 rev $97.7B, Adj EBITDA ~15% mgn. Market cap approx Q1 2026; SEC 8-K Q4 2024.
B11: Trading peer median (AI/growth) | H11: =MEDIAN(H9:H10) -> 16.506994 | I11: =MEDIAN(I9:I10) -> 54.344465
B13: Defence primes & Neo primes
B14: Lockheed Martin | C14: Defence prime | D14: 108.5 | E14: 127 | F14: 71.8 | G14: 8.7 | H14: =E14/F14 -> 1.7688022 | I14: =E14/G14 -> 14.597701 | J14: 0.04 | K14: Capital One MarketView Q3 2025; 14.6x CY2025E EV/EBITDA
B15: Palantir | C15: AI software / Defense | D15: 355 | E15: 350 | F15: 7.5 | G15: 3.5 | H15: 46.7x | I15: 100.0x | J15: 0.45 | K15: 2026E from consensus; Gov + Commercial AIP
B16: Anduril | C16: AI software / Defense | D16: 61 | E16: 61 | F16: 2.2 | G16: n/m | H16: 27.7x | I16: n/m | J16: 1.1 | K16: Private; Series H May 2026 $5B raise at $61B post-money; 2025 rev $2.2B (~110% YoY); EBITDA negative (op. loss ~$1.2B); led by Thrive Capital & a16z
B17: Northrop Grumman | C17: Defence prime | D17: 72 | E17: 88.4 | F17: 41.95 | G17: 5.98 | H17: =E17/F17 -> 2.1072706 | I17: =E17/G17 -> 14.782609 | J17: 0.022 | K17: Macrotrends FY2025 rev $41.95B, EBITDA $5.98B; Capital One MarketView Q3 2025
B18: BAE Systems | C18: Defence prime | D18: 77.3 | E18: 86.2 | F18: 32.9 | G18: 4.3 | H18: =E18/F18 -> 2.6200608 | I18: =E18/G18 -> 20.046512 | J18: 0.07 | K18: Capital One MarketView Q3 2025
B19: Trading peer median (Defence) | H19: =MEDIAN(H14:H18) -> 2.1072706 | I19: =MEDIAN(I14:I18) -> 14.782609
B21: Satellite / space pure-plays
B22: AST SpaceMobile | C22: D2C satellite | D22: 41 | E22: 41 | F22: 0.17 | G22: -0.45 | H22: =E22/F22 -> 241.17647 | I22: n/m | J22: 0.95 | K22: FY26E rev ~$170M (mid of $150-200M guidance); EBITDA negative. Market cap May 2026; 24/7 Wall St.
B23: Rocket Lab | C23: Launch + space systems | D23: 72 | E23: 70 | F23: 0.91 | G23: -0.13 | H23: =E23/F23 -> 76.923077 | I23: n/m | J23: 0.51 | K23: FY26E rev $909M (IndexBox/analyst consensus); not yet EBITDA positive.
B24: Iridium | C24: Satellite comms | D24: 3.4 | E24: 5 | F24: 0.83 | G24: 0.44 | H24: =E24/F24 -> 6.0240964 | I24: =E24/G24 -> 11.363636 | J24: 0.05 | K24: FY2024 rev $830M, EBITDA $440M (~53% margin). Payload Space 2024.
B25: Viasat | C25: Satellite comms | D25: 2.6 | E25: 8.8 | F25: 4.6 | G25: 0.85 | H25: =E25/F25 -> 1.9130435 | I25: =E25/G25 -> 10.352941 | J25: 0.02 | K25: FY2024 rev ~$4.6B, EBITDA ~$0.85B. Heavily leveraged (EV>>cap).
B26: Trading peer median (Satellite) | H26: =MEDIAN(H22:H25) -> 41.473587 | I26: =MEDIAN(I24:I25) -> 10.858289
B27: Tech Mega-Cap Conglomerates
B28: Alphabet (Google) | C28: Mega-cap tech / AI | D28: 2820 | E28: 2821 | F28: 434 | G28: 200 | H28: =E28/F28 -> 6.5 | I28: =E28/G28 -> 14.105 | J28: 0.12 | K28: 2026E from consensus; Search + Cloud + AI
B29: Amazon | C29: Mega-cap tech / Cloud | D29: 1950 | E29: 1950 | F29: 697 | G29: 130 | H29: =E29/F29 -> 2.7977044 | I29: =E29/G29 -> 15 | J29: 0.11 | K29: 2026E from consensus; AWS + Retail + AI
B30: Trading peer median (Tech) | H30: =MEDIAN(H28:H29) -> 4.6488522 | I30: =MEDIAN(I28:I29) -> 14.5525
B31: AI Labs
B32: OpenAI | C32: AI lab (private) | D32: 852 | E32: 852 | F32: 30 | G32: n/m | H32: =E32/F32 -> 28.4 | I32: n/m | J32: 1.5 | K32: Private; 2025 tender ~$500B prior; latest 2026 secondary $850B
B33: Anthropic | C33: AI lab (private) | D33: 965 | E33: 965 | F33: 47 | G33: n/m | H33: =E33/F33 -> 20.531915 | I33: n/m | J33: 2 | K33: Private; latest secondary tender ~$0.95-1T; rev run-rate ~$47B
B34: Trading peer median (AI labs) | H34: =MEDIAN(H32:H33) -> 24.465957
B35: SpaceX - FYE 2026
B36: SpaceX — Our Conclusion | C36: Hybrid | D36: =Summary!E10/1000 -> 2408.2305 | E36: =Summary!D10/1000 -> 2421.4895 | F36: ='P&L_Consolidated'!C19/1000 -> 56.15935 | G36: ='P&L_Consolidated'!C35/1000 -> 30.968225 | H36: =E36/F36 -> 43.11819 | I36: =E36/G36 -> 78.192713 | J36: 0.33
B37: SpaceX — IPO ($1.75T) | C37: Hybrid | D37: 1750 | E37: =D37+Assumptions!C22/1000 -> 1763.259 | F37: =F36 -> 56.15935 | G37: =G36 -> 30.968225 | H37: =E37/F37 -> 31.397425 | I37: =E37/G37 -> 56.937684 | J37: 0.33 | K37: IPO low-end scenario; net debt $13.3B added to market cap for EV.
B38: SpaceX — IPO mid ($1.875T) | C38: Hybrid | D38: 1875 | E38: =D38+Assumptions!C22/1000 -> 1888.259 | F38: =F37 -> 56.15935 | G38: =G37 -> 30.968225 | H38: =E38/F38 -> 33.623235 | I38: =E38/G38 -> 60.974079 | J38: 0.33 | K38: IPO-up scenario.
B39: SpaceX — IPO Bull Run (2.75T) | C39: Hybrid | D39: 2750 | E39: =D39+Assumptions!C22/1000 -> 2763.259 | F39: =F38 -> 56.15935 | G39: =G38 -> 30.968225 | H39: =E39/F39 -> 49.203899 | I39: =E39/G39 -> 89.228847 | J39: 0.33 | K39: IPO high scenario + short-term bull run
B42: IMPLIED VALUATION — Apply peer multiples to SpaceX 2025 financials
B43: Method | C43: Multiple Applied | D43: Multiple Value | E43: Implied EV ($Bn) | F43: Implied Equity ($Bn) | G43: Implied $/share | H43: vs IPO mid | I43: vs Our DCF central | M43: Chart data | N43: Equity ($Bn)
B44: Defence median EV/Revenue | C44: EV/Revenue | D44: =H19 -> 2.1072706 | E44: =D44*F36 -> 118.34294 | F44: =E44-Assumptions!C22/1000 -> 105.08394 | G44: =F44*1000/Assumptions!C25 -> 7.8420854 | H44: =F44/1875-1 -> -0.94395523 | I44: =F44/D36-1 -> -0.95636467 | M44: Defence EV/Rev implied | N44: =F44 -> 105.08394
B45: Defence median EV/EBITDA | C45: EV/EBITDA | D45: =I19 -> 14.782609 | E45: =D45*G36 -> 457.79115 | F45: =E45-Assumptions!C22/1000 -> 444.53215 | G45: =F45*1000/Assumptions!C25 -> 33.174041 | H45: =F45/1875-1 -> -0.76291619 | I45: =F45/D36-1 -> -0.8154113 | M45: Defence EV/EBITDA implied | N45: =F45 -> 444.53215
B46: AI/growth median EV/Revenue | C46: EV/Revenue | D46: =H11 -> 16.506994 | E46: =D46*F36 -> 927.02206 | F46: =E46-Assumptions!C22/1000 -> 913.76306 | G46: =F46*1000/Assumptions!C25 -> 68.191273 | H46: =F46/1875-1 -> -0.5126597 | I46: =F46/D36-1 -> -0.62056662 | M46: 70/30 Defence/AI blend | N46: =F49 -> 812.08029
B47: AI/growth median EV/EBITDA | C47: EV/EBITDA | D47: =I11 -> 54.344465 | E47: =D47*G36 -> 1682.9516 | F47: =E47-Assumptions!C22/1000 -> 1669.6926 | G47: =F47*1000/Assumptions!C25 -> 124.60393 | H47: =F47/1875-1 -> -0.10949727 | I47: =F47/D36-1 -> -0.30667243 | M47: AI EV/Rev implied | N47: =F46 -> 913.76306
B48: Satellite median EV/Revenue | C48: EV/Revenue | D48: =H26 -> 41.473587 | E48: =D48*F36 -> 2329.1297 | F48: =E48-Assumptions!C22/1000 -> 2315.8707 | G48: =F48*1000/Assumptions!C25 -> 172.82617 | H48: =F48/1875-1 -> 0.23513102 | I48: =F48/D36-1 -> -0.038351755 | M48: AI EV/EBITDA implied | N48: =F47 -> 1669.6926
B49: 70/30 mix (Defence/AI EV/EBITDA blend) | C49: Blend | D49: =0.7*I19+0.3*I11 -> 26.651166 | E49: =D49*G36 -> 825.33929 | F49: =E49-Assumptions!C22/1000 -> 812.08029 | G49: =F49*1000/Assumptions!C25 -> 60.603007 | H49: =F49/1875-1 -> -0.56689051 | I49: =F49/D36-1 -> -0.66278964 | M49: Satellite EV/Rev implied | N49: =F48 -> 2315.8707
B50: Range (low-high across methods) | F50: ="$"&FIXED(MIN(F44:F49),1,TRUE)&"Bn – $"&FIXED(MAX(F44:F49),1,TRUE)&"Bn" -> $105.1Bn – $2315.9Bn | M50: IPO low ($1.75T) | N50: =D37 -> 1750
B51: Median across methods | F51: =MEDIAN(F44:F49) -> 862.92168 | G51: =F51*1000/Assumptions!C25 -> 64.39714 | H51: =F51/1875-1 -> -0.53977511 | I51: =F51/D36-1 -> -0.64167813 | M51: IPO mid ($1.875T) | N51: 1875
M52: IPO bull ($2.75T) | N52: =D39 -> 2750
M53: Our DCF central | N53: =D36 -> 2408.2305
M54: MC P50 | N54: =Monte_Carlo!B20/1000 -> 2241.3002
M55: MC P90 | N55: =Monte_Carlo!B23/1000 -> 4733.1182

Sheet Assumptions
B2: Global Assumptions
B3: These drive the DCF and feed into every business-line tab
B5: Discount rate & terminal value
B7: Risk-free rate (10Y UST) | C7: 0.043 | D7: 10Y Treasury yield, May 2026 (~4.3%)
B8: Equity risk premium | C8: 0.055 | D8: Damodaran 2026 implied ERP estimate
B9: SpaceX beta (relevered) | C9: 1.35 | D9: Composite: aerospace/defense (1.1) + tech (1.5), weighted
B10: Cost of equity | C10: =C7+C8*C9 -> 0.11725 | D10: Rf + β × ERP
B11: Pre-tax cost of debt | C11: 0.05 | D11: Estimated based on Musk-co credit spreads
B12: Effective tax rate | C12: 0.21 | D12: Federal corporate rate; SpaceX still NOL-rich
B13: After-tax cost of debt | C13: =C11*(1-C12) -> 0.0395
B14: Debt / Total cap (target) | C14: 0.35 | D14: Conservative — SpaceX is mostly equity-funded
B15: WACC | C15: =(1-C14)*C10 + C14*C13 -> 0.0900375 | D15: We × Ke + Wd × Kd(1-t)
B16: Terminal growth rate | C16: 0.04 | D16: Above long-run nominal GDP — reflects secular space/AI tailwinds
B18: Capital structure & share count
B20: Cash & equivalents ($M) | C20: 15852 | D20: Per S-1 cap table, 31 Mar 2026 (verified)
B21: Gross debt ($M) | C21: 29111 | D21: Per S-1 cap table, total LT debt 31 Mar 2026 (verified)
B22: Net debt position ($M) | C22: =C21-C20 -> 13259 | D22: Positive = net debt; negative = net cash
B23: Diluted shares pre-IPO (M) | C23: 12520 | D23: S-1 pro forma cap table (Class A + Class B, post Preferred Conversion)
B24: IPO new share issuance (M) | C24: 880 | D24: $75B raise ÷ ~$85 implied price
B25: Post-IPO diluted shares (M) | C25: =C23+C24 -> 13400
B27: Horizon end-years (reference only)
B29: 5-year horizon end | C29: 2030
B30: 10-year horizon end | C30: 2035
B31: 20-year horizon end | C31: 2045
B33: Horizon blending weights (Summary view)
B35: 5-year weight | C35: 0.55 | D35: Weight on 5-year horizon EV
B36: 10-year weight | C36: 0.35 | D36: Weight on 10-year horizon EV
B37: 20-year weight | C37: 0.1 | D37: Weight on 20-year horizon EV
B38: Sum (should = 100%) | C38: =SUM(C35:C37) -> 1 | D38: Must equal 100% — sanity check

Sheet Scenario_Engine
B2: Scenario Engine
B3: Per-line Bear / Base / Bull weights + probability of materialization. Weights must sum to 100%.
B5: Business Line | C5: Bear weight | D5: Base weight | E5: Bull weight | F5: Sum check | G5: Materialization | H5: Notes
A6: 1 | B6: Launch Services & Lunar Vehicles | C6: 0.1 | D6: 0.3 | E6: 0.6 | F6: =SUM(C6:E6) -> 1 | G6: 1 | H6: Falcon + Starship + HLS Artemis lunar lander (NASA Lunar absorbed)
A7: 2 | B7: Crewed Spaceflight | C7: 0.15 | D7: 0.6 | E7: 0.25 | F7: =SUM(C7:E7) -> 1 | G7: 1 | H7: NASA CCP/CRS + Polaris/Axiom + Starports/P2P (Recreational + Starports absorbed)
A8: 3 | B8: Other Space Services | C8: 0.3 | D8: 0.5 | E8: 0.2 | F8: =SUM(C8:E8) -> 1 | G8: 0.65 | H8: Satellite servicing + orbital tug + Rocketry IP licensing (Rocketry absorbed)
A9: 4 | B9: Starlink Connectivity | C9: 0.15 | D9: 0.6 | E9: 0.25 | F9: =SUM(C9:E9) -> 1 | G9: 1 | H9: Residential + business + aviation + maritime broadband (Starlink AvMar absorbed)
A10: 5 | B10: Starlink Direct-to-Cell | C10: 0.2 | D10: 0.6 | E10: 0.2 | F10: =SUM(C10:E10) -> 1 | G10: 0.98 | H10: Carrier deal scaling + spectrum policy
A11: 6 | B11: Starshield & Golden Dome (Defense) | C11: 0.1 | D11: 0.6 | E11: 0.3 | F11: =SUM(C11:E11) -> 1 | G11: 0.95 | H11: Defense contract pipeline (Golden Dome, NRO)
A12: 7 | B12: xAI Software (Grok + API) | C12: 0.15 | D12: 0.5 | E12: 0.35 | F12: =SUM(C12:E12) -> 1 | G12: 0.98 | H12: Grok subs, enterprise API revenue
A13: 8 | B13: Colossus Terrestrial Data Centres | C13: 0.15 | D13: 0.5 | E13: 0.35 | F13: =SUM(C13:E13) -> 1 | G13: 0.85 | H13: 1M GPU/yr × $30B per million mature pricing
A14: 9 | B14: Orbital Data Centres | C14: 0.15 | D14: 0.55 | E14: 0.3 | F14: =SUM(C14:E14) -> 1 | G14: 0.8 | H14: First commercial 2031 (base); long-dated
A15: 10 | B15: Deep Space Optionality | C15: 0.5 | D15: 0.4 | E15: 0.1 | F15: =SUM(C15:E15) -> 1 | G15: 0.35 | H15: Lunar Mfg + Asteroid + Mars/Moon (long-dated optionality, merged)
A16: 11 | B16: X Platform | C16: 0.3 | D16: 0.5 | E16: 0.2 | F16: =SUM(C16:E16) -> 1 | G16: 0.85 | H16: X.com social/ads/premium + Xmoney payments (merged)
A17: 12 | B17: Terafab — Semiconductor Manufacturing | C17: 0.25 | D17: 0.5 | E17: 0.25 | F17: =SUM(C17:E17) -> 1 | G17: 0.75 | H17: Creation of 3 types of chips for Tesla, XAI and SpaceX use-cases

Sheet P&L_Consolidated
B2: Consolidated P&L (Probability-Weighted)
B3: Sum of all business lines' expected (probability-weighted) financials, by year
B5: Revenue by business line ($M)
B6: Business line | C6: 2026 | D6: 2027 | E6: 2028 | F6: 2029 | G6: 2030 | H6: 2031 | I6: 2032 | J6: 2033 | K6: 2034 | L6: 2035 | M6: 2036 | N6: 2037 | O6: 2038 | P6: 2039 | Q6: 2040 | R6: 2041 | S6: 2042 | T6: 2043 | U6: 2044 | V6: 2045
A7: 1 | B7: Launch Services | C7: =Launch_Services!C34+Launch_Services!C45 -> 12091.95 | D7: =Launch_Services!D34+Launch_Services!D45 -> 17314.925 | E7: =Launch_Services!E34+Launch_Services!E45 -> 24923.316 | F7: =Launch_Services!F34+Launch_Services!F45 -> 36046.602 | G7: =Launch_Services!G34+Launch_Services!G45 -> 52361.288 | H7: =Launch_Services!H34+Launch_Services!H45 -> 68583.495 | I7: =Launch_Services!I34+Launch_Services!I45 -> 90115.319 | J7: =Launch_Services!J34+Launch_Services!J45 -> 118745.89 | ... V7: =Launch_Services!V34+Launch_Services!V45 -> 1753174.7
A8: 2 | B8: Crewed Spaceflight | C8: ='Crewed Trips'!C34+'Crewed Trips'!C45 -> 2447.8 | D8: ='Crewed Trips'!D34+'Crewed Trips'!D45 -> 3051.78 | E8: ='Crewed Trips'!E34+'Crewed Trips'!E45 -> 3818.218 | F8: ='Crewed Trips'!F34+'Crewed Trips'!F45 -> 4795.0428 | G8: ='Crewed Trips'!G34+'Crewed Trips'!G45 -> 6045.9067 | H8: ='Crewed Trips'!H34+'Crewed Trips'!H45 -> 7305.9298 | I8: ='Crewed Trips'!I34+'Crewed Trips'!I45 -> 8812.9815 | J8: ='Crewed Trips'!J34+'Crewed Trips'!J45 -> 10658.886 | ... V8: ='Crewed Trips'!V34+'Crewed Trips'!V45 -> 58265.392
A9: 3 | B9: Other Space Services | C9: =Other_Services!C34 -> 149.5 | D9: =Other_Services!D34 -> 206.7 | E9: =Other_Services!E34 -> 288.3075 | F9: =Other_Services!F34 -> 405.25387 | G9: =Other_Services!G34 -> 573.51036 | H9: =Other_Services!H34 -> 745.5117 | I9: =Other_Services!I34 -> 971.60232 | J9: =Other_Services!J34 -> 1269.2927 | ... V9: =Other_Services!V34 -> 15525.749
A10: 4 | B10: Starlink Connectivity (Consumer + Av/Mar) | C10: =Starlink!C34+Starlink!C45 -> 15010 | D10: =Starlink!D34+Starlink!D45 -> 21334 | E10: =Starlink!E34+Starlink!E45 -> 30534.1 | F10: =Starlink!F34+Starlink!F45 -> 43999.765 | G10: =Starlink!G34+Starlink!G45 -> 63825.515 | H10: =Starlink!H34+Starlink!H45 -> 83367.385 | I10: =Starlink!I34+Starlink!I45 -> 109232.51 | J10: =Starlink!J34+Starlink!J45 -> 143530.8 | ... V10: =Starlink!V34+Starlink!V45 -> 989981.58
A11: 5 | B11: Starlink Direct-to-Cell | C11: =Starlink_D2C!C34 -> 980 | D11: =Starlink_D2C!D34 -> 1724.8 | E11: =Starlink_D2C!E34 -> 3067.4 | F11: =Starlink_D2C!F34 -> 5509.756 | G11: =Starlink_D2C!G34 -> 9991.5116 | H11: =Starlink_D2C!H34 -> 15324.021 | I11: =Starlink_D2C!I34 -> 23762.315 | J11: =Starlink_D2C!J34 -> 37237.183 | ... V11: =Starlink_D2C!V34 -> 990791.62
A12: 6 | B12: Starshield & Golden Dome (Defense) | C12: =Starshield!C34 -> 3334.5 | D12: =Starshield!D34 -> 4846.425 | E12: =Starshield!E34 -> 7086.1687 | F12: =Starshield!F34 -> 10419.518 | G12: =Starshield!G34 -> 15401.722 | H12: =Starshield!H34 -> 20050.504 | I12: =Starshield!I34 -> 26186.86 | J12: =Starshield!J34 -> 34304.428 | ... V12: =Starshield!V34 -> 325904.38
A13: 7 | B13: xAI Software (Grok + API) | C13: =xAI_Software!C34 -> 2298.1 | D13: =xAI_Software!D34 -> 3450.825 | E13: =xAI_Software!E34 -> 5220.5212 | F13: =xAI_Software!F34 -> 7953.9771 | G13: =xAI_Software!G34 -> 12200.307 | H13: =xAI_Software!H34 -> 16976.795 | I13: =xAI_Software!I34 -> 23691.684 | J13: =xAI_Software!J34 -> 33149.213 | ... V13: =xAI_Software!V34 -> 326970.1
A14: 8 | B14: Colossus Terrestrial Data Centres | C14: =Colossus_DCs!C34 -> 15767.5 | D14: =Colossus_DCs!D34 -> 22467.625 | E14: =Colossus_DCs!E34 -> 32285.019 | F14: =Colossus_DCs!F34 -> 46753.809 | G14: =Colossus_DCs!G34 -> 68191.519 | H14: =Colossus_DCs!H34 -> 85855.154 | I14: =Colossus_DCs!I34 -> 108312.64 | J14: =Colossus_DCs!J34 -> 136906.42 | ... V14: =Colossus_DCs!V34 -> 797628.52
A15: 9 | B15: Orbital Data Centres | C15: =Orbital_DCs!C34 -> 0 | D15: =Orbital_DCs!D34 -> 0 | E15: =Orbital_DCs!E34 -> 0 | F15: =Orbital_DCs!F34 -> 0 | G15: =Orbital_DCs!G34 -> 0 | H15: =Orbital_DCs!H34 -> 8600 | I15: =Orbital_DCs!I34 -> 14300 | J15: =Orbital_DCs!J34 -> 23942 | ... V15: =Orbital_DCs!V34 -> 1960783.4
A16: 10 | B16: Deep Space Optionality | C16: ='Deep Space Option'!C34 -> 0 | D16: ='Deep Space Option'!D34 -> 0 | E16: ='Deep Space Option'!E34 -> 0 | F16: ='Deep Space Option'!F34 -> 0 | G16: ='Deep Space Option'!G34 -> 0 | H16: ='Deep Space Option'!H34 -> 23.5 | I16: ='Deep Space Option'!I34 -> 27.45 | J16: ='Deep Space Option'!J34 -> 32.325 | ... V16: ='Deep Space Option'!V34 -> 110622.97
A17: 11 | B17: X Platform | C17: ='X Platform'!C34 -> 4080 | D17: ='X Platform'!D34 -> 5678 | E17: ='X Platform'!E34 -> 7944.1 | F17: ='X Platform'!F34 -> 11169.17 | G17: ='X Platform'!G34 -> 15774.079 | H17: ='X Platform'!H34 -> 19372.702 | I17: ='X Platform'!I34 -> 23855.918 | J17: ='X Platform'!J34 -> 29453.278 | ... V17: ='X Platform'!V34 -> 227301.68
A18: 12 | B18: Terafab — Semiconductor Manufacturing | C18: =Terafab!C34 -> 0 | D18: =Terafab!D34 -> 0 | E18: =Terafab!E34 -> 0 | F18: =Terafab!F34 -> 0 | G18: =Terafab!G34 -> 0 | H18: =Terafab!H34 -> 4500 | I18: =Terafab!I34 -> 7443.75 | J18: =Terafab!J34 -> 12456.562 | ... V18: =Terafab!V34 -> 1085705.8
B19: Total revenue | C19: =SUM(C7:C18) -> 56159.35 | D19: =SUM(D7:D18) -> 80075.08 | E19: =SUM(E7:E18) -> 115167.15 | F19: =SUM(F7:F18) -> 167052.89 | G19: =SUM(G7:G18) -> 244365.36 | H19: =SUM(H7:H18) -> 330705 | I19: =SUM(I7:I18) -> 436713.03 | J19: =SUM(J7:J18) -> 581686.28 | ... V19: =SUM(V7:V18) -> 8642655.9
B21: EBITDA by business line ($M)
B22: Business line | C22: 2026 | D22: 2027 | E22: 2028 | F22: 2029 | G22: 2030 | H22: 2031 | I22: 2032 | J22: 2033 | K22: 2034 | L22: 2035 | M22: 2036 | N22: 2037 | O22: 2038 | P22: 2039 | Q22: 2040 | R22: 2041 | S22: 2042 | T22: 2043 | U22: 2044 | V22: 2045
B23: Launch Services & Lunar Vehicles | C23: =Launch_Services!C39+Launch_Services!C46 -> 5572.515 | D23: =Launch_Services!D39+Launch_Services!D46 -> 8120.514 | E23: =Launch_Services!E39+Launch_Services!E46 -> 11874.382 | F23: =Launch_Services!F39+Launch_Services!F46 -> 17417.466 | G23: =Launch_Services!G39+Launch_Services!G46 -> 25619.211 | H23: =Launch_Services!H39+Launch_Services!H46 -> 33981.027 | I23: =Launch_Services!I39+Launch_Services!I46 -> 45156.322 | J23: =Launch_Services!J39+Launch_Services!J46 -> 60107.711 | ... V23: =Launch_Services!V39+Launch_Services!V46 -> 941179.64
B24: Crewed Spaceflight | C24: ='Crewed Trips'!C39+'Crewed Trips'!C46 -> 1282.61 | D24: ='Crewed Trips'!D39+'Crewed Trips'!D46 -> 1612.371 | E24: ='Crewed Trips'!E39+'Crewed Trips'!E46 -> 2033.3081 | F24: ='Crewed Trips'!F39+'Crewed Trips'!F46 -> 2572.6514 | G24: ='Crewed Trips'!G39+'Crewed Trips'!G46 -> 3266.5247 | H24: ='Crewed Trips'!H39+'Crewed Trips'!H46 -> 3969.2073 | I24: ='Crewed Trips'!I39+'Crewed Trips'!I46 -> 4825.23 | J24: ='Crewed Trips'!J39+'Crewed Trips'!J46 -> 5878.7236 | ... V24: ='Crewed Trips'!V39+'Crewed Trips'!V46 -> 32929.062
B25: Other Space Services | C25: =Other_Services!C39 -> 78.325 | D25: =Other_Services!D39 -> 110.37 | E25: =Other_Services!E39 -> 156.62888 | F25: =Other_Services!F39 -> 223.64379 | G25: =Other_Services!G39 -> 321.03717 | H25: =Other_Services!H39 -> 421.18665 | I25: =Other_Services!I39 -> 553.70978 | J25: =Other_Services!J39 -> 729.30516 | ... V25: =Other_Services!V39 -> 9727.4812
B26: Starlink Connectivity (Consumer + Av/Mar) | C26: =Starlink!C39+Starlink!C46 -> 9336.6 | D26: =Starlink!D39+Starlink!D46 -> 13377.24 | E26: =Starlink!E39+Starlink!E46 -> 19293.861 | F26: =Starlink!F39+Starlink!F46 -> 28007.747 | G26: =Starlink!G39+Starlink!G46 -> 40913.857 | H26: =Starlink!H39+Starlink!H46 -> 53622.672 | I26: =Starlink!I39+Starlink!I46 -> 70473.121 | J26: =Starlink!J39+Starlink!J46 -> 92851.904 | ... V26: =Starlink!V39+Starlink!V46 -> 662963.86
B27: Starlink Direct-to-Cell | C27: =Starlink_D2C!C39 -> 568.4 | D27: =Starlink_D2C!D39 -> 1016.26 | E27: =Starlink_D2C!E39 -> 1834.658 | F27: =Starlink_D2C!F39 -> 3342.829 | G27: =Starlink_D2C!G39 -> 6144.4599 | H27: =Starlink_D2C!H39 -> 9559.9657 | I27: =Starlink_D2C!I39 -> 15027.138 | J27: =Starlink_D2C!J39 -> 23849.481 | ... V27: =Starlink_D2C!V39 -> 682820.18
B28: Starshield & Golden Dome (Defense) | C28: =Starshield!C39 -> 1520.475 | D28: =Starshield!D39 -> 2250.0038 | E28: =Starshield!E39 -> 3345.6613 | F28: =Starshield!F39 -> 4996.9782 | G28: =Starshield!G39 -> 7493.6724 | H28: =Starshield!H39 -> 9865.6852 | I28: =Starshield!I39 -> 13019.964 | J28: =Starshield!J39 -> 17220.936 | ... V28: =Starshield!V39 -> 173347.51
B29: xAI Software (Grok + API) | C29: =xAI_Software!C39 -> 1093.925 | D29: =xAI_Software!D39 -> 1684.4362 | E29: =xAI_Software!E39 -> 2609.8288 | F29: =xAI_Software!F39 -> 4067.0706 | G29: =xAI_Software!G39 -> 6372.1721 | H29: =xAI_Software!H39 -> 8983.2593 | I29: =xAI_Software!I39 -> 12689.289 | J29: =xAI_Software!J39 -> 17956.423 | ... V29: =xAI_Software!V39 -> 193500.23
B30: Colossus Terrestrial Data Centres | C30: =Colossus_DCs!C39 -> 10763.125 | D30: =Colossus_DCs!D39 -> 15492.844 | E30: =Colossus_DCs!E39 -> 22468.608 | F30: =Colossus_DCs!F39 -> 32810.567 | G30: =Colossus_DCs!G39 -> 48216.02 | H30: =Colossus_DCs!H39 -> 60945.122 | I30: =Colossus_DCs!I39 -> 77172.574 | J30: =Colossus_DCs!J39 -> 97886.48 | ... V30: =Colossus_DCs!V39 -> 581889.08
B31: Orbital Data Centres | C31: =Orbital_DCs!C39 -> 0 | D31: =Orbital_DCs!D39 -> 0 | E31: =Orbital_DCs!E39 -> 0 | F31: =Orbital_DCs!F39 -> 0 | G31: =Orbital_DCs!G39 -> 0 | H31: =Orbital_DCs!H39 -> 4530 | I31: =Orbital_DCs!I39 -> 7653 | J31: =Orbital_DCs!J39 -> 13005.3 | ... V31: =Orbital_DCs!V39 -> 1191820.7
B32: Deep Space Optionality | C32: ='Deep Space Option'!C39 -> 0 | D32: ='Deep Space Option'!D39 -> 0 | E32: ='Deep Space Option'!E39 -> 0 | F32: ='Deep Space Option'!F39 -> 0 | G32: ='Deep Space Option'!G39 -> 0 | H32: ='Deep Space Option'!H39 -> 10.525 | I32: ='Deep Space Option'!I39 -> 12.6975 | J32: ='Deep Space Option'!J39 -> 15.43575 | ... V32: ='Deep Space Option'!V39 -> 71322.971
B33: X Platform | C33: ='X Platform'!C39 -> 752.25 | D33: ='X Platform'!D39 -> 1073.55 | E33: ='X Platform'!E39 -> 1538.16 | F33: ='X Platform'!F39 -> 2211.717 | G33: ='X Platform'!G39 -> 3190.4529 | H33: ='X Platform'!H39 -> 3993.4117 | I33: ='X Platform'!I39 -> 5009.5953 | J33: ='X Platform'!J39 -> 6297.7559 | ... V33: ='X Platform'!V39 -> 54538.524
B34: Terafab — Semiconductor Manufacturing | C34: =Terafab!C39 -> 0 | D34: =Terafab!D39 -> 0 | E34: =Terafab!E39 -> 0 | F34: =Terafab!F39 -> 0 | G34: =Terafab!G39 -> 0 | H34: =Terafab!H39 -> 1968.75 | I34: =Terafab!I39 -> 3340.3125 | J34: =Terafab!J39 -> 5723.0156 | ... V34: =Terafab!V39 -> 565272.03
B35: Total EBITDA | C35: =SUM(C23:C34) -> 30968.225 | D35: =SUM(D23:D34) -> 44737.589 | E35: =SUM(E23:E34) -> 65155.096 | F35: =SUM(F23:F34) -> 95650.67 | G35: =SUM(G23:G34) -> 141537.41 | H35: =SUM(H23:H34) -> 191850.81 | I35: =SUM(I23:I34) -> 254932.95 | J35: =SUM(J23:J34) -> 341522.47 | ... V35: =SUM(V23:V34) -> 5161311.3
B36: Group EBITDA margin | C36: =IFERROR(C35/C19,0) -> 0.55143489 | D36: =IFERROR(D35/D19,0) -> 0.55869552 | E36: =IFERROR(E35/E19,0) -> 0.56574375 | F36: =IFERROR(F35/F19,0) -> 0.57257715 | G36: =IFERROR(G35/G19,0) -> 0.57920406 | H36: =IFERROR(H35/H19,0) -> 0.58012674 | I36: =IFERROR(I35/I19,0) -> 0.58375395 | J36: =IFERROR(J35/J19,0) -> 0.58712485 | ... V36: =IFERROR(V35/V19,0) -> 0.59719043
B38: UFCF by business line ($M) — feeds DCF
B39: Business line | C39: 2026 | D39: 2027 | E39: 2028 | F39: 2029 | G39: 2030 | H39: 2031 | I39: 2032 | J39: 2033 | K39: 2034 | L39: 2035 | M39: 2036 | N39: 2037 | O39: 2038 | P39: 2039 | Q39: 2040 | R39: 2041 | S39: 2042 | T39: 2043 | U39: 2044 | V39: 2045
B40: Launch Services & Lunar Vehicles | C40: =Launch_Services!C43+Launch_Services!C47 -> 1089.6319 | D40: =Launch_Services!D43+Launch_Services!D47 -> 1728.2956 | E40: =Launch_Services!E43+Launch_Services!E47 -> 2709.997 | F40: =Launch_Services!F43+Launch_Services!F47 -> 4212.6132 | G40: =Launch_Services!G43+Launch_Services!G47 -> 6504.7916 | H40: =Launch_Services!H43+Launch_Services!H47 -> 8945.0379 | I40: =Launch_Services!I43+Launch_Services!I47 -> 12261.643 | J40: =Launch_Services!J43+Launch_Services!J47 -> 16764.666 | ... V40: =Launch_Services!V43+Launch_Services!V47 -> 298554.25
B41: Crewed Spaceflight | C41: ='Crewed Trips'!C43+'Crewed Trips'!C47 -> 872.7819 | D41: ='Crewed Trips'!D43+'Crewed Trips'!D47 -> 1099.6651 | E41: ='Crewed Trips'!E43+'Crewed Trips'!E47 -> 1389.7456 | F41: ='Crewed Trips'!F43+'Crewed Trips'!F47 -> 1761.9821 | G41: ='Crewed Trips'!G43+'Crewed Trips'!G47 -> 2241.5364 | H41: ='Crewed Trips'!H43+'Crewed Trips'!H47 -> 2715.1365 | I41: ='Crewed Trips'!I43+'Crewed Trips'!I47 -> 3305.2894 | J41: ='Crewed Trips'!J43+'Crewed Trips'!J47 -> 4031.2236 | ... V41: ='Crewed Trips'!V43+'Crewed Trips'!V47 -> 21692.026
B42: Other Space Services | C42: =Other_Services!C43 -> 31.97675 | D42: =Other_Services!D43 -> 45.8523 | E42: =Other_Services!E43 -> 66.075311 | F42: =Other_Services!F43 -> 95.627822 | G42: =Other_Services!G43 -> 138.91729 | H42: =Other_Services!H43 -> 183.63511 | I42: =Other_Services!I43 -> 243.11026 | J42: =Other_Services!J43 -> 322.29253 | ... V42: =Other_Services!V43 -> 4579.5603
B43: Starlink Connectivity (Consumer + Av/Mar) | C43: =Starlink!C43+Starlink!C47 -> 5133.914 | D43: =Starlink!D43+Starlink!D47 -> 7394.5196 | E43: =Starlink!E43+Starlink!E47 -> 10716.94 | F43: =Starlink!F43+Starlink!F47 -> 15626.86 | G43: =Starlink!G43+Starlink!G47 -> 22921.768 | H43: =Starlink!H43+Starlink!H47 -> 29934.99 | I43: =Starlink!I43+Starlink!I47 -> 39204.622 | J43: =Starlink!J43+Starlink!J47 -> 51478.57 | ... V43: =Starlink!V43+Starlink!V47 -> 371404.42
B44: Starlink Direct-to-Cell | C44: =Starlink_D2C!C43 -> 311.836 | D44: =Starlink_D2C!D43 -> 566.6654 | E44: =Starlink_D2C!E43 -> 1038.4658 | F44: =Starlink_D2C!F43 -> 1918.5259 | G44: =Starlink_D2C!G43 -> 3571.7727 | H44: =Starlink_D2C!H43 -> 5631.0211 | I44: =Starlink_D2C!I43 -> 8959.7136 | J44: =Starlink_D2C!J43 -> 14378.522 | ... V44: =Starlink_D2C!V43 -> 436770.8
B45: Starshield & Golden Dome (Defense) | C45: =Starshield!C43 -> 832.95525 | D45: =Starshield!D43 -> 1247.2035 | E45: =Starshield!E43 -> 1874.3576 | F45: =Starshield!F43 -> 2826.3755 | G45: =Starshield!G43 -> 4275.0098 | H45: =Starshield!H43 -> 5664.8308 | I45: =Starshield!I43 -> 7520.2237 | J45: =Starshield!J43 -> 10000.008 | ... V45: =Starshield!V43 -> 103745.5
B46: xAI Software (Grok + API) | C46: =xAI_Software!C43 -> 230.38575 | D46: =xAI_Software!D43 -> 359.58589 | E46: =xAI_Software!E43 -> 564.52382 | F46: =xAI_Software!F43 -> 890.97147 | G46: =xAI_Software!G43 -> 1412.9594 | H46: =xAI_Software!H43 -> 2005.2754 | I46: =xAI_Software!I43 -> 2850.7444 | J46: =xAI_Software!J43 -> 4058.8748 | ... V46: =xAI_Software!V43 -> 46130.855
B47: Colossus Terrestrial Data Centres | C47: =Colossus_DCs!C43 -> 1209.8687 | D47: =Colossus_DCs!D43 -> 1982.3966 | E47: =Colossus_DCs!E43 -> 3192.2077 | F47: =Colossus_DCs!F43 -> 5080.3816 | G47: =Colossus_DCs!G43 -> 8020.228 | H47: =Colossus_DCs!H43 -> 10505.52 | I47: =Colossus_DCs!I43 -> 13741.273 | J47: =Colossus_DCs!J43 -> 17952.503 | ... V47: =Colossus_DCs!V43 -> 124659.66
B48: Orbital Data Centres | C48: =Orbital_DCs!C43 -> 0 | D48: =Orbital_DCs!D43 -> 0 | E48: =Orbital_DCs!E43 -> 0 | F48: =Orbital_DCs!F43 -> 0 | G48: =Orbital_DCs!G43 -> 0 | H48: =Orbital_DCs!H43 -> -51.3 | I48: =Orbital_DCs!I43 -> 102.87 | J48: =Orbital_DCs!J43 -> 463.887 | ... V48: =Orbital_DCs!V43 -> 212328.38
B49: Deep Space Optionality | C49: ='Deep Space Option'!C43 -> 0 | D49: ='Deep Space Option'!D43 -> 0 | E49: ='Deep Space Option'!E43 -> 0 | F49: ='Deep Space Option'!F43 -> 0 | G49: ='Deep Space Option'!G43 -> 0 | H49: ='Deep Space Option'!H43 -> 0.51475 | I49: ='Deep Space Option'!I43 -> 0.671025 | J49: ='Deep Space Option'!J43 -> 0.8767425 | ... V49: ='Deep Space Option'!V43 -> 6883.9335
B50: X Platform | C50: ='X Platform'!C43 -> 288.2775 | D50: ='X Platform'!D43 -> 429.0545 | E50: ='X Platform'!E43 -> 637.9114 | F50: ='X Platform'!F43 -> 947.77193 | G50: ='X Platform'!G43 -> 1407.5366 | H50: ='X Platform'!H43 -> 1805.031 | I50: ='X Platform'!I43 -> 2316.1541 | J50: ='X Platform'!J43 -> 2973.8041 | ... V50: ='X Platform'!V43 -> 28923.69
B51: Terafab — Semiconductor Manufacturing | C51: =Terafab!C43 -> 0 | D51: =Terafab!D43 -> 0 | E51: =Terafab!E43 -> 0 | F51: =Terafab!F43 -> 0 | G51: =Terafab!G43 -> 0 | H51: =Terafab!H43 -> 419.0625 | I51: =Terafab!I43 -> 818.59688 | J51: =Terafab!J43 -> 1567.3261 | ... V51: =Terafab!V43 -> 232064.26
B52: Total UFCF | C52: =SUM(C40:C51) -> 10001.628 | D52: =SUM(D40:D51) -> 14853.238 | E52: =SUM(E40:E51) -> 22190.225 | F52: =SUM(F40:F51) -> 33361.11 | G52: =SUM(G40:G51) -> 50494.52 | H52: =SUM(H40:H51) -> 67758.755 | I52: =SUM(I40:I51) -> 91324.912 | J52: =SUM(J40:J51) -> 123992.55 | ... V52: =SUM(V40:V51) -> 1887737.3

Sheet Launch_Services
X1: TEST
B2: Launch Services
B3: Falcon 9 / Heavy commercial launches + Starship cargo ramp
B5: Scenario weights (from Scenario_Engine)
B6: Bear weight | C6: =Scenario_Engine!$C$6 -> 0.1
B7: Base weight | C7: =Scenario_Engine!$D$6 -> 0.3
B8: Bull weight | C8: =Scenario_Engine!$E$6 -> 0.6
B9: Probability of materialization | C9: =Scenario_Engine!$G$6 -> 1
B11: Substantiation & Sources
B12: Bear ($6.8B): commercial Falcon 9 ~80 launches × $74M = $5.9B + residual govt
B13: Base ($9.5B): NSSL Phase 3 Lane 2 $5.92B/28 missions + NRO proliferated arch ~$1.2B + commercial ~$5.9B + intl/rideshare
B14: Bull ($13B): Starship operational cargo-as-a-service opens $150B TAM (SpaceX mgmt)
B15: Sources: NSSL Phase 3 Lane 2 award (DoD May 2026); SpaceNexus 2026 launch prices; Aviation Outlook 2026
B17: Scenario assumptions (edit blue cells)
B18: Driver | C18: Bear | D18: Base | E18: Bull
B19: 2026 starting revenue ($M) | C19: 6800 | D19: 9500 | E19: 13000
B20: CAGR 2026→2030 (ramp) | C20: 0.2 | D20: 0.3 | E20: 0.5
B21: CAGR 2030→2035 (mid) | C21: 0.1 | D21: 0.2 | E21: 0.35
B22: CAGR 2035→2045 (mature) | C22: 0.07 | D22: 0.15 | E22: 0.25
B23: Mid-phase seed 2031 ($M, optional) | C23: 0 | D23: 0 | E23: 0
B24: Mature-phase seed 2036 ($M, optional) | C24: 0 | D24: 0 | E24: 0
B25: EBITDA margin | C25: 0.15 | D25: 0.35 | E25: 0.55
B26: CapEx (% of revenue) | C26: 0.35 | D26: 0.35 | E26: 0.25
B28: Revenue build ($M, by scenario)
B29: Year | C29: 2026 | D29: 2027 | E29: 2028 | F29: 2029 | G29: 2030 | H29: 2031 | I29: 2032 | J29: 2033 | K29: 2034 | L29: 2035 | M29: 2036 | N29: 2037 | O29: 2038 | P29: 2039 | Q29: 2040 | R29: 2041 | S29: 2042 | T29: 2043 | U29: 2044 | V29: 2045
B30: Bear revenue | C30: =$C$19 -> 6800 | D30: =C30*(1+$C$20) -> 8160 | E30: =D30*(1+$C$20) -> 9792 | F30: =E30*(1+$C$20) -> 11750.4 | G30: =F30*(1+$C$20) -> 14100.48 | H30: =IF($C$23>0,$C$23,G30*(1+$C$21)) -> 15510.528 | I30: =H30*(1+$C$21) -> 17061.581 | J30: =I30*(1+$C$21) -> 18767.739 | K30: =J30*(1+$C$21) -> 20644.513 | L30: =K30*(1+$C$21) -> 22708.964 | M30: =IF($C$24>0,$C$24,L30*(1+$C$22)) -> 24298.592 | N30: =M30*(1+$C$22) -> 25999.493 | O30: =N30*(1+$C$22) -> 27819.457 | P30: =O30*(1+$C$22) -> 29766.819 | Q30: =P30*(1+$C$22) -> 31850.497 | R30: =Q30*(1+$C$22) -> 34080.032 | S30: =R30*(1+$C$22) -> 36465.634 | T30: =S30*(1+$C$22) -> 39018.228 | U30: =T30*(1+$C$22) -> 41749.504 | V30: =U30*(1+$C$22) -> 44671.969
B31: Base revenue | C31: =$D$19 -> 9500 | D31: =C31*(1+$D$20) -> 12350 | E31: =D31*(1+$D$20) -> 16055 | F31: =E31*(1+$D$20) -> 20871.5 | G31: =F31*(1+$D$20) -> 27132.95 | H31: =IF($D$23>0,$D$23,G31*(1+$D$21)) -> 32559.54 | I31: =H31*(1+$D$21) -> 39071.448 | J31: =I31*(1+$D$21) -> 46885.738 | K31: =J31*(1+$D$21) -> 56262.885 | L31: =K31*(1+$D$21) -> 67515.462 | M31: =IF($D$24>0,$D$24,L31*(1+$D$22)) -> 77642.781 | N31: =M31*(1+$D$22) -> 89289.199 | O31: =N31*(1+$D$22) -> 102682.58 | P31: =O31*(1+$D$22) -> 118084.97 | Q31: =P31*(1+$D$22) -> 135797.71 | R31: =Q31*(1+$D$22) -> 156167.37 | S31: =R31*(1+$D$22) -> 179592.47 | T31: =S31*(1+$D$22) -> 206531.34 | U31: =T31*(1+$D$22) -> 237511.04 | V31: =U31*(1+$D$22) -> 273137.7
B32: Bull revenue | C32: =$E$19 -> 13000 | D32: =C32*(1+$E$20) -> 19500 | E32: =D32*(1+$E$20) -> 29250 | F32: =E32*(1+$E$20) -> 43875 | G32: =F32*(1+$E$20) -> 65812.5 | H32: =IF($E$23>0,$E$23,G32*(1+$E$21)) -> 88846.875 | I32: =H32*(1+$E$21) -> 119943.28 | J32: =I32*(1+$E$21) -> 161923.43 | K32: =J32*(1+$E$21) -> 218596.63 | L32: =K32*(1+$E$21) -> 295105.45 | M32: =IF($E$24>0,$E$24,L32*(1+$E$22)) -> 368881.81 | N32: =M32*(1+$E$22) -> 461102.27 | O32: =N32*(1+$E$22) -> 576377.83 | P32: =O32*(1+$E$22) -> 720472.29 | Q32: =P32*(1+$E$22) -> 900590.36 | R32: =Q32*(1+$E$22) -> 1125738 | S32: =R32*(1+$E$22) -> 1407172.4 | T32: =S32*(1+$E$22) -> 1758965.6 | U32: =T32*(1+$E$22) -> 2198706.9 | V32: =U32*(1+$E$22) -> 2748383.7
B33: Scenario-weighted revenue | C33: =C30*$C$6+C31*$C$7+C32*$C$8 -> 11330 | D33: =D30*$C$6+D31*$C$7+D32*$C$8 -> 16221 | E33: =E30*$C$6+E31*$C$7+E32*$C$8 -> 23345.7 | F33: =F30*$C$6+F31*$C$7+F32*$C$8 -> 33761.49 | G33: =G30*$C$6+G31*$C$7+G32*$C$8 -> 49037.433 | H33: =H30*$C$6+H31*$C$7+H32*$C$8 -> 64627.04 | I33: =I30*$C$6+I31*$C$7+I32*$C$8 -> 85393.561 | J33: =J30*$C$6+J31*$C$7+J32*$C$8 -> 113096.55 | ... V33: =V30*$C$6+V31*$C$7+V32*$C$8 -> 1735438.7
B34: Expected revenue (× materialization) | C34: =C33*$C$9 -> 11330 | D34: =D33*$C$9 -> 16221 | E34: =E33*$C$9 -> 23345.7 | F34: =F33*$C$9 -> 33761.49 | G34: =G33*$C$9 -> 49037.433 | H34: =H33*$C$9 -> 64627.04 | I34: =I33*$C$9 -> 85393.561 | J34: =J33*$C$9 -> 113096.55 | ... V34: =V33*$C$9 -> 1735438.7
B36: Economics ($M)
B37: Year | C37: 2026 | D37: 2027 | E37: 2028 | F37: 2029 | G37: 2030 | H37: 2031 | I37: 2032 | J37: 2033 | K37: 2034 | L37: 2035 | M37: 2036 | N37: 2037 | O37: 2038 | P37: 2039 | Q37: 2040 | R37: 2041 | S37: 2042 | T37: 2043 | U37: 2044 | V37: 2045
B38: Blended EBITDA margin | C38: =IFERROR((C30*$C$6*$C$25+C31*$C$7*$D$25+C32*$C$8*$E$25)/C33,0) -> 0.47568402 | D38: =IFERROR((D30*$C$6*$C$25+D31*$C$7*$D$25+D32*$C$8*$E$25)/D33,0) -> 0.48419641 | E38: =IFERROR((E30*$C$6*$C$25+E31*$C$7*$D$25+E32*$C$8*$E$25)/E33,0) -> 0.49196019 | F38: =IFERROR((F30*$C$6*$C$25+F31*$C$7*$D$25+F32*$C$8*$E$25)/F33,0) -> 0.49898608 | G38: =IFERROR((G30*$C$6*$C$25+G31*$C$7*$D$25+G32*$C$8*$E$25)/G33,0) -> 0.50529953 | H38: =IFERROR((H30*$C$6*$C$25+H31*$C$7*$D$25+H32*$C$8*$E$25)/H33,0) -> 0.51017157 | I38: =IFERROR((I30*$C$6*$C$25+I31*$C$7*$D$25+I32*$C$8*$E$25)/I33,0) -> 0.51455529 | J38: =IFERROR((J30*$C$6*$C$25+J31*$C$7*$D$25+J32*$C$8*$E$25)/J33,0) -> 0.5184884 | ... V38: =IFERROR((V30*$C$6*$C$25+V31*$C$7*$D$25+V32*$C$8*$E$25)/V33,0) -> 0.53952706
B39: Expected EBITDA | C39: =C34*C38 -> 5389.5 | D39: =D34*D38 -> 7854.15 | E39: =E34*E38 -> 11485.155 | F39: =F34*F38 -> 16846.514 | G39: =G34*G38 -> 24778.592 | H39: =H34*H38 -> 32970.878 | I39: =I34*I38 -> 43939.709 | J39: =J34*J38 -> 58639.25 | ... V39: =V34*V38 -> 936316.15
B40: Blended CapEx (% of revenue) | C40: =IFERROR((C30*$C$6*$C$26+C31*$C$7*$D$26+C32*$C$8*$E$26)/C33,0) -> 0.28115622 | D40: =IFERROR((D30*$C$6*$C$26+D31*$C$7*$D$26+D32*$C$8*$E$26)/D33,0) -> 0.27787128 | E40: =IFERROR((E30*$C$6*$C$26+E31*$C$7*$D$26+E32*$C$8*$E$26)/E33,0) -> 0.27482556 | F40: =IFERROR((F30*$C$6*$C$26+F31*$C$7*$D$26+F32*$C$8*$E$26)/F33,0) -> 0.27202655 | G40: =IFERROR((G30*$C$6*$C$26+G31*$C$7*$D$26+G32*$C$8*$E$26)/G33,0) -> 0.26947478 | H40: =IFERROR((H30*$C$6*$C$26+H31*$C$7*$D$26+H32*$C$8*$E$26)/H33,0) -> 0.26751421 | I40: =IFERROR((I30*$C$6*$C$26+I31*$C$7*$D$26+I32*$C$8*$E$26)/I33,0) -> 0.26572436 | J40: =IFERROR((J30*$C$6*$C$26+J31*$C$7*$D$26+J32*$C$8*$E$26)/J33,0) -> 0.26409636 | ... V40: =IFERROR((V30*$C$6*$C$26+V31*$C$7*$D$26+V32*$C$8*$E$26)/V33,0) -> 0.25497906
B41: Expected CapEx | C41: =C34*C40 -> 3185.5 | D41: =D34*D40 -> 4507.35 | E41: =E34*E40 -> 6415.995 | F41: =F34*F40 -> 9184.0215 | G41: =G34*G40 -> 13214.352 | H41: =H34*H40 -> 17288.651 | I41: =I34*I40 -> 22691.15 | J41: =J34*J40 -> 29868.388 | ... V41: =V34*V40 -> 442500.53
B42: Tax on EBITDA (at Assumptions!$C$12) | C42: =MAX(0,C39)*Assumptions!$C$12 -> 1131.795 | D42: =MAX(0,D39)*Assumptions!$C$12 -> 1649.3715 | E42: =MAX(0,E39)*Assumptions!$C$12 -> 2411.8825 | F42: =MAX(0,F39)*Assumptions!$C$12 -> 3537.7678 | G42: =MAX(0,G39)*Assumptions!$C$12 -> 5203.5043 | H42: =MAX(0,H39)*Assumptions!$C$12 -> 6923.8845 | I42: =MAX(0,I39)*Assumptions!$C$12 -> 9227.3388 | J42: =MAX(0,J39)*Assumptions!$C$12 -> 12314.243 | ... V42: =MAX(0,V39)*Assumptions!$C$12 -> 196626.39
B43: Unlevered Free Cash Flow | C43: =C39-C42-C41 -> 1072.205 | D43: =D39-D42-D41 -> 1697.4285 | E43: =E39-E42-E41 -> 2657.2774 | F43: =F39-F42-F41 -> 4124.7242 | G43: =G39-G42-G41 -> 6360.7361 | H43: =H39-H42-H41 -> 8758.3425 | I43: =I39-I42-I41 -> 12021.22 | J43: =J39-J42-J41 -> 16456.62 | ... V43: =V39-V42-V41 -> 297189.23
B45: Consolidation adjustment — Revenue ($M) | C45: 761.95 | D45: 1093.925 | E45: 1577.6163 | F45: 2285.1119 | G45: 3323.8545 | H45: 3956.4551 | I45: 4721.7579 | J45: 5649.3368 | K45: 6775.6294 | L45: 8145.5744 | M45: 8781.9674 | N45: 9473.751 | O45: 10226.065 | P45: 11044.544 | Q45: 11935.364 | R45: 12905.298 | S45: 13961.774 | T45: 15112.938 | U45: 16367.725 | V45: 17735.938
B46: Consolidation adjustment — EBITDA ($M) | C46: 183.015 | D46: 266.364 | E46: 389.2266 | F46: 570.9528 | G46: 840.6192 | H46: 1010.1488 | I46: 1216.613 | J46: 1468.4605 | K46: 1776.1363 | L46: 2152.563 | M46: 2330.1621 | N46: 2523.7373 | O46: 2734.7988 | P46: 2965.0037 | Q46: 3216.1704 | R46: 3490.2942 | S46: 3789.565 | T46: 4116.3863 | U46: 4473.3966 | V46: 4863.4924
B47: Consolidation adjustment — UFCF ($M) | C47: 17.4269 | D47: 30.8671 | E47: 52.7196 | F47: 87.889 | G47: 144.0555 | H47: 186.6954 | I47: 240.4229 | J47: 308.0457 | K47: 393.0774 | L47: 499.9144 | M47: 553.7653 | N47: 613.1076 | O47: 678.4938 | P47: 750.5323 | Q47: 829.892 | R47: 917.309 | S47: 1013.5935 | T47: 1119.6364 | U47: 1236.4181 | V47: 1365.0172

Sheet Starlink
B2: Starlink Connectivity
B3: Residential, fixed business and residential broadband, aviation, maritime connectivity & ISP provision
B5: Scenario weights (from Scenario_Engine)
B6: Bear weight | C6: =Scenario_Engine!$C$9 -> 0.15
B7: Base weight | C7: =Scenario_Engine!$D$9 -> 0.6
B8: Bull weight | C8: =Scenario_Engine!$E$9 -> 0.25
B9: Probability of materialization | C9: =Scenario_Engine!$G$9 -> 1
B11: Substantiation & Sources
B12: Bear ($5.5B): 7-8M residential subs × $66 ARPU × 12 = ~$5.5B; Kuiper/Eutelsat eat into growth
B13: Base ($9.8B): Quilty 2026 Starlink total $20B − AvMar $4.2B − D2C $1.0B − Govt $1.5B → ~$13B residential/biz; 9.8 prob-weighted base
B14: Bull ($13.5B): Lightreading 100M subs by 2034 trajectory; 30-50M subs by 2030 @ $50-60 blended ARPU = $18-36B
B15: Sources: Quilty Space 2026 forecast; Lightreading 100M sub projection; The Information ARPU $66 / 4× subs; Skift $11.4B + zero churn
B17: Scenario assumptions (edit blue cells)
B18: Driver | C18: Bear | D18: Base | E18: Bull
B19: 2026 starting revenue ($M) | C19: 6500 | D19: 9800 | E19: 13500
B20: CAGR 2026→2030 (ramp) | C20: 0.2 | D20: 0.4 | E20: 0.6
B21: CAGR 2030→2035 (mid) | C21: 0.15 | D21: 0.35 | E21: 0.35
B22: CAGR 2035→2045 (mature) | C22: 0.05 | D22: 0.1 | E22: 0.2
B23: Mid-phase seed 2031 ($M, optional) | C23: 0 | D23: 0 | E23: 0
B24: Mature-phase seed 2036 ($M, optional) | C24: 0 | D24: 0 | E24: 0
B25: EBITDA margin | C25: 0.5 | D25: 0.62 | E25: 0.7
B26: CapEx (% of revenue) | C26: 0.25 | D26: 0.2 | E26: 0.15
B28: Revenue build ($M, by scenario)
B29: Year | C29: 2026 | D29: 2027 | E29: 2028 | F29: 2029 | G29: 2030 | H29: 2031 | I29: 2032 | J29: 2033 | K29: 2034 | L29: 2035 | M29: 2036 | N29: 2037 | O29: 2038 | P29: 2039 | Q29: 2040 | R29: 2041 | S29: 2042 | T29: 2043 | U29: 2044 | V29: 2045
B30: Bear revenue | C30: =$C$19 -> 6500 | D30: =C30*(1+$C$20) -> 7800 | E30: =D30*(1+$C$20) -> 9360 | F30: =E30*(1+$C$20) -> 11232 | G30: =F30*(1+$C$20) -> 13478.4 | H30: =IF($C$23>0,$C$23,G30*(1+$C$21)) -> 15500.16 | I30: =H30*(1+$C$21) -> 17825.184 | J30: =I30*(1+$C$21) -> 20498.962 | K30: =J30*(1+$C$21) -> 23573.806 | L30: =K30*(1+$C$21) -> 27109.877 | M30: =IF($C$24>0,$C$24,L30*(1+$C$22)) -> 28465.371 | N30: =M30*(1+$C$22) -> 29888.639 | O30: =N30*(1+$C$22) -> 31383.071 | P30: =O30*(1+$C$22) -> 32952.225 | Q30: =P30*(1+$C$22) -> 34599.836 | R30: =Q30*(1+$C$22) -> 36329.828 | S30: =R30*(1+$C$22) -> 38146.319 | T30: =S30*(1+$C$22) -> 40053.635 | U30: =T30*(1+$C$22) -> 42056.317 | V30: =U30*(1+$C$22) -> 44159.133
B31: Base revenue | C31: =$D$19 -> 9800 | D31: =C31*(1+$D$20) -> 13720 | E31: =D31*(1+$D$20) -> 19208 | F31: =E31*(1+$D$20) -> 26891.2 | G31: =F31*(1+$D$20) -> 37647.68 | H31: =IF($D$23>0,$D$23,G31*(1+$D$21)) -> 50824.368 | I31: =H31*(1+$D$21) -> 68612.897 | J31: =I31*(1+$D$21) -> 92627.411 | K31: =J31*(1+$D$21) -> 125047 | L31: =K31*(1+$D$21) -> 168813.46 | M31: =IF($D$24>0,$D$24,L31*(1+$D$22)) -> 185694.8 | N31: =M31*(1+$D$22) -> 204264.28 | O31: =N31*(1+$D$22) -> 224690.71 | P31: =O31*(1+$D$22) -> 247159.78 | Q31: =P31*(1+$D$22) -> 271875.76 | R31: =Q31*(1+$D$22) -> 299063.33 | S31: =R31*(1+$D$22) -> 328969.67 | T31: =S31*(1+$D$22) -> 361866.64 | U31: =T31*(1+$D$22) -> 398053.3 | V31: =U31*(1+$D$22) -> 437858.63
B32: Bull revenue | C32: =$E$19 -> 13500 | D32: =C32*(1+$E$20) -> 21600 | E32: =D32*(1+$E$20) -> 34560 | F32: =E32*(1+$E$20) -> 55296 | G32: =F32*(1+$E$20) -> 88473.6 | H32: =IF($E$23>0,$E$23,G32*(1+$E$21)) -> 119439.36 | I32: =H32*(1+$E$21) -> 161243.14 | J32: =I32*(1+$E$21) -> 217678.23 | K32: =J32*(1+$E$21) -> 293865.62 | L32: =K32*(1+$E$21) -> 396718.58 | M32: =IF($E$24>0,$E$24,L32*(1+$E$22)) -> 476062.3 | N32: =M32*(1+$E$22) -> 571274.76 | O32: =N32*(1+$E$22) -> 685529.71 | P32: =O32*(1+$E$22) -> 822635.65 | Q32: =P32*(1+$E$22) -> 987162.78 | R32: =Q32*(1+$E$22) -> 1184595.3 | S32: =R32*(1+$E$22) -> 1421514.4 | T32: =S32*(1+$E$22) -> 1705817.3 | U32: =T32*(1+$E$22) -> 2046980.7 | V32: =U32*(1+$E$22) -> 2456376.9
B33: Scenario-weighted revenue | C33: =C30*$C$6+C31*$C$7+C32*$C$8 -> 10230 | D33: =D30*$C$6+D31*$C$7+D32*$C$8 -> 14802 | E33: =E30*$C$6+E31*$C$7+E32*$C$8 -> 21568.8 | F33: =F30*$C$6+F31*$C$7+F32*$C$8 -> 31643.52 | G33: =G30*$C$6+G31*$C$7+G32*$C$8 -> 46728.768 | H33: =H30*$C$6+H31*$C$7+H32*$C$8 -> 62679.485 | I33: =I30*$C$6+I31*$C$7+I32*$C$8 -> 84152.3 | J33: =J30*$C$6+J31*$C$7+J32*$C$8 -> 113070.85 | ... V33: =V30*$C$6+V31*$C$7+V32*$C$8 -> 883433.27
B34: Expected revenue (× materialization) | C34: =C33*$C$9 -> 10230 | D34: =D33*$C$9 -> 14802 | E34: =E33*$C$9 -> 21568.8 | F34: =F33*$C$9 -> 31643.52 | G34: =G33*$C$9 -> 46728.768 | H34: =H33*$C$9 -> 62679.485 | I34: =I33*$C$9 -> 84152.3 | J34: =J33*$C$9 -> 113070.85 | ... V34: =V33*$C$9 -> 883433.27
B36: Economics ($M)
B37: Year | C37: 2026 | D37: 2027 | E37: 2028 | F37: 2029 | G37: 2030 | H37: 2031 | I37: 2032 | J37: 2033 | K37: 2034 | L37: 2035 | M37: 2036 | N37: 2037 | O37: 2038 | P37: 2039 | Q37: 2040 | R37: 2041 | S37: 2042 | T37: 2043 | U37: 2044 | V37: 2045
B38: Blended EBITDA margin | C38: =IFERROR((C30*$C$6*$C$25+C31*$C$7*$D$25+C32*$C$8*$E$25)/C33,0) -> 0.63495601 | D38: =IFERROR((D30*$C$6*$C$25+D31*$C$7*$D$25+D32*$C$8*$E$25)/D33,0) -> 0.63970004 | E38: =IFERROR((E30*$C$6*$C$25+E31*$C$7*$D$25+E32*$C$8*$E$25)/E33,0) -> 0.64423501 | F38: =IFERROR((F30*$C$6*$C$25+F31*$C$7*$D$25+F32*$C$8*$E$25)/F33,0) -> 0.64856016 | G38: =IFERROR((G30*$C$6*$C$25+G31*$C$7*$D$25+G32*$C$8*$E$25)/G33,0) -> 0.65267496 | H38: =IFERROR((H30*$C$6*$C$25+H31*$C$7*$D$25+H32*$C$8*$E$25)/H33,0) -> 0.65365989 | I38: =IFERROR((I30*$C$6*$C$25+I31*$C$7*$D$25+I32*$C$8*$E$25)/I33,0) -> 0.65450897 | J38: =IFERROR((J30*$C$6*$C$25+J31*$C$7*$D$25+J32*$C$8*$E$25)/J33,0) -> 0.6552397 | ... V38: =IFERROR((V30*$C$6*$C$25+V31*$C$7*$D$25+V32*$C$8*$E$25)/V33,0) -> 0.67471004
B39: Expected EBITDA | C39: =C34*C38 -> 6495.6 | D39: =D34*D38 -> 9468.84 | E39: =E34*E38 -> 13895.376 | F39: =F34*F38 -> 20522.726 | G39: =G34*G38 -> 30498.697 | H39: =H34*H38 -> 40971.065 | I39: =I34*I38 -> 55078.435 | J39: =J34*J38 -> 74088.51 | ... V39: =V34*V38 -> 596061.3
B40: Blended CapEx (% of revenue) | C40: =IFERROR((C30*$C$6*$C$26+C31*$C$7*$D$26+C32*$C$8*$E$26)/C33,0) -> 0.18826979 | D40: =IFERROR((D30*$C$6*$C$26+D31*$C$7*$D$26+D32*$C$8*$E$26)/D33,0) -> 0.18571139 | E40: =IFERROR((E30*$C$6*$C$26+E31*$C$7*$D$26+E32*$C$8*$E$26)/E33,0) -> 0.18322577 | F40: =IFERROR((F30*$C$6*$C$26+F31*$C$7*$D$26+F32*$C$8*$E$26)/F33,0) -> 0.18081882 | G40: =IFERROR((G30*$C$6*$C$26+G31*$C$7*$D$26+G32*$C$8*$E$26)/G33,0) -> 0.1784965 | H40: =IFERROR((H30*$C$6*$C$26+H31*$C$7*$D$26+H32*$C$8*$E$26)/H33,0) -> 0.17803522 | I40: =IFERROR((I30*$C$6*$C$26+I31*$C$7*$D$26+I32*$C$8*$E$26)/I33,0) -> 0.17763757 | J40: =IFERROR((J30*$C$6*$C$26+J31*$C$7*$D$26+J32*$C$8*$E$26)/J33,0) -> 0.17729534 | ... V40: =IFERROR((V30*$C$6*$C$26+V31*$C$7*$D$26+V32*$C$8*$E$26)/V33,0) -> 0.16561878
B41: Expected CapEx | C41: =C34*C40 -> 1926 | D41: =D34*D40 -> 2748.9 | E41: =E34*E40 -> 3951.96 | F41: =F34*F40 -> 5721.744 | G41: =G34*G40 -> 8340.9216 | H41: =H34*H40 -> 11159.156 | I41: =I34*I40 -> 14948.61 | J41: =J34*J40 -> 20046.934 | ... V41: =V34*V40 -> 146313.14
B42: Tax on EBITDA (at Assumptions!$C$12) | C42: =MAX(0,C39)*Assumptions!$C$12 -> 1364.076 | D42: =MAX(0,D39)*Assumptions!$C$12 -> 1988.4564 | E42: =MAX(0,E39)*Assumptions!$C$12 -> 2918.029 | F42: =MAX(0,F39)*Assumptions!$C$12 -> 4309.7725 | G42: =MAX(0,G39)*Assumptions!$C$12 -> 6404.7264 | H42: =MAX(0,H39)*Assumptions!$C$12 -> 8603.9236 | I42: =MAX(0,I39)*Assumptions!$C$12 -> 11566.471 | J42: =MAX(0,J39)*Assumptions!$C$12 -> 15558.587 | ... V42: =MAX(0,V39)*Assumptions!$C$12 -> 125172.87
B43: Unlevered Free Cash Flow | C43: =C39-C42-C41 -> 3205.524 | D43: =D39-D42-D41 -> 4731.4836 | E43: =E39-E42-E41 -> 7025.387 | F43: =F39-F42-F41 -> 10491.21 | G43: =G39-G42-G41 -> 15753.049 | H43: =H39-H42-H41 -> 21207.985 | I43: =I39-I42-I41 -> 28563.354 | J43: =J39-J42-J41 -> 38482.989 | ... V43: =V39-V42-V41 -> 324575.29
B45: Consolidation adjustment — Revenue ($M) | C45: 4780 | D45: 6532 | E45: 8965.3 | F45: 12356.245 | G45: 17096.747 | H45: 20687.9 | I45: 25080.214 | J45: 30459.951 | K45: 37057.872 | L45: 45160.055 | M45: 49143.142 | N45: 53494.073 | O45: 58247.851 | P45: 63442.872 | Q45: 69121.26 | R45: 75329.234 | S45: 82117.508 | T45: 89541.735 | U45: 97662.991 | V45: 106548.31
B46: Consolidation adjustment — EBITDA ($M) | C46: 2841 | D46: 3908.4 | E46: 5398.485 | F46: 7485.0202 | G46: 10415.16 | H46: 12651.607 | I46: 15394.686 | J46: 18763.394 | K46: 22905.344 | L46: 28003.75 | M46: 30516.056 | N46: 33262.989 | O46: 36267.035 | P46: 39552.873 | Q46: 43147.585 | R46: 47080.899 | S46: 51385.446 | T46: 56097.047 | U46: 61255.028 | V46: 66902.565
B47: Consolidation adjustment — UFCF ($M) | C47: 1928.39 | D47: 2663.036 | E47: 3691.5532 | F47: 5135.6505 | G47: 7168.7187 | H47: 8727.005 | I47: 10641.268 | J47: 12995.581 | K47: 15894.309 | L47: 19467.069 | M47: 21229.843 | N47: 23158.244 | O47: 25268.208 | P47: 27577.226 | Q47: 30104.5 | R47: 32871.109 | S47: 35900.196 | T47: 39217.171 | U47: 42849.936 | V47: 46829.13

Sheet Starshield
B2: Starshield & Golden Dome
B3: DoD Space Force, NRO, allied government satellite networks
B5: Scenario weights (from Scenario_Engine)
B6: Bear weight | C6: =Scenario_Engine!$C$11 -> 0.1
B7: Base weight | C7: =Scenario_Engine!$D$11 -> 0.6
B8: Bull weight | C8: =Scenario_Engine!$E$11 -> 0.3
B9: Probability of materialization | C9: =Scenario_Engine!$G$11 -> 0.95
B11: Substantiation & Sources
B12: Bear ($1.8B): existing NRO classified vintage ~$1.8B + USSF commercial-only, no Golden Dome execution
B13: Base ($2.3B): $2.29B SDN Backbone contract (FFP OTA, awarded May 26 2026) pro-rata + NRO 13 launches/yr + USSF PLEO IDIQ allocations + allied govt
B14: Bull ($4.0B): Golden Dome $175B/decade program ramp; Starshield = de facto US/allied milspace backbone + USSF PLEO $13B ceiling utilization
B15: Sources: SpaceNews $2.29B SDN award (May 2026); DefenseScoop backbone SATCOM (May 2026); AIAA NRO 13 proliferated missions
B17: Scenario assumptions (edit blue cells)
B18: Driver | C18: Bear | D18: Base | E18: Bull
B19: 2026 starting revenue ($M) | C19: 1800 | D19: 2300 | E19: 6500
B20: CAGR 2026→2030 (ramp) | C20: 0.2 | D20: 0.35 | E20: 0.55
B21: CAGR 2030→2035 (mid) | C21: 0.1 | D21: 0.2 | E21: 0.35
B22: CAGR 2035→2045 (mature) | C22: 0.05 | D22: 0.1 | E22: 0.2
B23: Mid-phase seed 2031 ($M, optional) | C23: 0 | D23: 0 | E23: 0
B24: Mature-phase seed 2036 ($M, optional) | C24: 0 | D24: 0 | E24: 0
B25: EBITDA margin | C25: 0.25 | D25: 0.35 | E25: 0.55
B26: CapEx (% of revenue) | C26: 0.15 | D26: 0.12 | E26: 0.1
B28: Revenue build ($M, by scenario)
B29: Year | C29: 2026 | D29: 2027 | E29: 2028 | F29: 2029 | G29: 2030 | H29: 2031 | I29: 2032 | J29: 2033 | K29: 2034 | L29: 2035 | M29: 2036 | N29: 2037 | O29: 2038 | P29: 2039 | Q29: 2040 | R29: 2041 | S29: 2042 | T29: 2043 | U29: 2044 | V29: 2045
B30: Bear revenue | C30: =$C$19 -> 1800 | D30: =C30*(1+$C$20) -> 2160 | E30: =D30*(1+$C$20) -> 2592 | F30: =E30*(1+$C$20) -> 3110.4 | G30: =F30*(1+$C$20) -> 3732.48 | H30: =IF($C$23>0,$C$23,G30*(1+$C$21)) -> 4105.728 | I30: =H30*(1+$C$21) -> 4516.3008 | J30: =I30*(1+$C$21) -> 4967.9309 | K30: =J30*(1+$C$21) -> 5464.724 | L30: =K30*(1+$C$21) -> 6011.1964 | M30: =IF($C$24>0,$C$24,L30*(1+$C$22)) -> 6311.7562 | N30: =M30*(1+$C$22) -> 6627.344 | O30: =N30*(1+$C$22) -> 6958.7112 | P30: =O30*(1+$C$22) -> 7306.6468 | Q30: =P30*(1+$C$22) -> 7671.9791 | R30: =Q30*(1+$C$22) -> 8055.578 | S30: =R30*(1+$C$22) -> 8458.3569 | T30: =S30*(1+$C$22) -> 8881.2748 | U30: =T30*(1+$C$22) -> 9325.3385 | V30: =U30*(1+$C$22) -> 9791.6055
B31: Base revenue | C31: =$D$19 -> 2300 | D31: =C31*(1+$D$20) -> 3105 | E31: =D31*(1+$D$20) -> 4191.75 | F31: =E31*(1+$D$20) -> 5658.8625 | G31: =F31*(1+$D$20) -> 7639.4644 | H31: =IF($D$23>0,$D$23,G31*(1+$D$21)) -> 9167.3573 | I31: =H31*(1+$D$21) -> 11000.829 | J31: =I31*(1+$D$21) -> 13200.994 | K31: =J31*(1+$D$21) -> 15841.193 | L31: =K31*(1+$D$21) -> 19009.432 | M31: =IF($D$24>0,$D$24,L31*(1+$D$22)) -> 20910.375 | N31: =M31*(1+$D$22) -> 23001.413 | O31: =N31*(1+$D$22) -> 25301.554 | P31: =O31*(1+$D$22) -> 27831.709 | Q31: =P31*(1+$D$22) -> 30614.88 | R31: =Q31*(1+$D$22) -> 33676.368 | S31: =R31*(1+$D$22) -> 37044.005 | T31: =S31*(1+$D$22) -> 40748.406 | U31: =T31*(1+$D$22) -> 44823.246 | V31: =U31*(1+$D$22) -> 49305.571
B32: Bull revenue | C32: =$E$19 -> 6500 | D32: =C32*(1+$E$20) -> 10075 | E32: =D32*(1+$E$20) -> 15616.25 | F32: =E32*(1+$E$20) -> 24205.188 | G32: =F32*(1+$E$20) -> 37518.041 | H32: =IF($E$23>0,$E$23,G32*(1+$E$21)) -> 50649.355 | I32: =H32*(1+$E$21) -> 68376.629 | J32: =I32*(1+$E$21) -> 92308.449 | K32: =J32*(1+$E$21) -> 124616.41 | L32: =K32*(1+$E$21) -> 168232.15 | M32: =IF($E$24>0,$E$24,L32*(1+$E$22)) -> 201878.58 | N32: =M32*(1+$E$22) -> 242254.29 | O32: =N32*(1+$E$22) -> 290705.15 | P32: =O32*(1+$E$22) -> 348846.18 | Q32: =P32*(1+$E$22) -> 418615.42 | R32: =Q32*(1+$E$22) -> 502338.5 | S32: =R32*(1+$E$22) -> 602806.21 | T32: =S32*(1+$E$22) -> 723367.45 | U32: =T32*(1+$E$22) -> 868040.94 | V32: =U32*(1+$E$22) -> 1041649.1
B33: Scenario-weighted revenue | C33: =C30*$C$6+C31*$C$7+C32*$C$8 -> 3510 | D33: =D30*$C$6+D31*$C$7+D32*$C$8 -> 5101.5 | E33: =E30*$C$6+E31*$C$7+E32*$C$8 -> 7459.125 | F33: =F30*$C$6+F31*$C$7+F32*$C$8 -> 10967.914 | G33: =G30*$C$6+G31*$C$7+G32*$C$8 -> 16212.339 | H33: =H30*$C$6+H31*$C$7+H32*$C$8 -> 21105.794 | I33: =I30*$C$6+I31*$C$7+I32*$C$8 -> 27565.116 | J33: =J30*$C$6+J31*$C$7+J32*$C$8 -> 36109.925 | ... V33: =V30*$C$6+V31*$C$7+V32*$C$8 -> 343057.24
B34: Expected revenue (× materialization) | C34: =C33*$C$9 -> 3334.5 | D34: =D33*$C$9 -> 4846.425 | E34: =E33*$C$9 -> 7086.1687 | F34: =F33*$C$9 -> 10419.518 | G34: =G33*$C$9 -> 15401.722 | H34: =H33*$C$9 -> 20050.504 | I34: =I33*$C$9 -> 26186.86 | J34: =J33*$C$9 -> 34304.428 | ... V34: =V33*$C$9 -> 325904.38
B36: Economics ($M)
B37: Year | C37: 2026 | D37: 2027 | E37: 2028 | F37: 2029 | G37: 2030 | H37: 2031 | I37: 2032 | J37: 2033 | K37: 2034 | L37: 2035 | M37: 2036 | N37: 2037 | O37: 2038 | P37: 2039 | Q37: 2040 | R37: 2041 | S37: 2042 | T37: 2043 | U37: 2044 | V37: 2045
B38: Blended EBITDA margin | C38: =IFERROR((C30*$C$6*$C$25+C31*$C$7*$D$25+C32*$C$8*$E$25)/C33,0) -> 0.45598291 | D38: =IFERROR((D30*$C$6*$C$25+D31*$C$7*$D$25+D32*$C$8*$E$25)/D33,0) -> 0.46426051 | E38: =IFERROR((E30*$C$6*$C$25+E31*$C$7*$D$25+E32*$C$8*$E$25)/E33,0) -> 0.47213966 | F38: =IFERROR((F30*$C$6*$C$25+F31*$C$7*$D$25+F32*$C$8*$E$25)/F33,0) -> 0.47957863 | G38: =IFERROR((G30*$C$6*$C$25+G31*$C$7*$D$25+G32*$C$8*$E$25)/G33,0) -> 0.4865477 | H38: =IFERROR((H30*$C$6*$C$25+H31*$C$7*$D$25+H32*$C$8*$E$25)/H33,0) -> 0.49204176 | I38: =IFERROR((I30*$C$6*$C$25+I31*$C$7*$D$25+I32*$C$8*$E$25)/I33,0) -> 0.49719455 | J38: =IFERROR((J30*$C$6*$C$25+J31*$C$7*$D$25+J32*$C$8*$E$25)/J33,0) -> 0.5020033 | ... V38: =IFERROR((V30*$C$6*$C$25+V31*$C$7*$D$25+V32*$C$8*$E$25)/V33,0) -> 0.53189685
B39: Expected EBITDA | C39: =C34*C38 -> 1520.475 | D39: =D34*D38 -> 2250.0038 | E39: =E34*E38 -> 3345.6613 | F39: =F34*F38 -> 4996.9782 | G39: =G34*G38 -> 7493.6724 | H39: =H34*H38 -> 9865.6852 | I39: =I34*I38 -> 13019.964 | J39: =J34*J38 -> 17220.936 | ... V39: =V34*V38 -> 173347.51
B40: Blended CapEx (% of revenue) | C40: =IFERROR((C30*$C$6*$C$26+C31*$C$7*$D$26+C32*$C$8*$E$26)/C33,0) -> 0.11042735 | D40: =IFERROR((D30*$C$6*$C$26+D31*$C$7*$D$26+D32*$C$8*$E$26)/D33,0) -> 0.10942076 | E40: =IFERROR((E30*$C$6*$C$26+E31*$C$7*$D$26+E32*$C$8*$E$26)/E33,0) -> 0.10848102 | F40: =IFERROR((F30*$C$6*$C$26+F31*$C$7*$D$26+F32*$C$8*$E$26)/F33,0) -> 0.10760932 | G40: =IFERROR((G30*$C$6*$C$26+G31*$C$7*$D$26+G32*$C$8*$E$26)/G33,0) -> 0.10680568 | H40: =IFERROR((H30*$C$6*$C$26+H31*$C$7*$D$26+H32*$C$8*$E$26)/H33,0) -> 0.10618489 | I40: =IFERROR((I30*$C$6*$C$26+I31*$C$7*$D$26+I32*$C$8*$E$26)/I33,0) -> 0.10560823 | J40: =IFERROR((J30*$C$6*$C$26+J31*$C$7*$D$26+J32*$C$8*$E$26)/J33,0) -> 0.10507483 | ... V40: =IFERROR((V30*$C$6*$C$26+V31*$C$7*$D$26+V32*$C$8*$E$26)/V33,0) -> 0.1018674
B41: Expected CapEx | C41: =C34*C40 -> 368.22 | D41: =D34*D40 -> 530.2995 | E41: =E34*E40 -> 768.71482 | F41: =F34*F40 -> 1121.2372 | G41: =G34*G40 -> 1644.9914 | H41: =H34*H40 -> 2129.0605 | I41: =I34*I40 -> 2765.5479 | J41: =J34*J40 -> 3604.5318 | ... V41: =V34*V40 -> 33199.031
B42: Tax on EBITDA (at Assumptions!$C$12) | C42: =MAX(0,C39)*Assumptions!$C$12 -> 319.29975 | D42: =MAX(0,D39)*Assumptions!$C$12 -> 472.50079 | E42: =MAX(0,E39)*Assumptions!$C$12 -> 702.58888 | F42: =MAX(0,F39)*Assumptions!$C$12 -> 1049.3654 | G42: =MAX(0,G39)*Assumptions!$C$12 -> 1573.6712 | H42: =MAX(0,H39)*Assumptions!$C$12 -> 2071.7939 | I42: =MAX(0,I39)*Assumptions!$C$12 -> 2734.1925 | J42: =MAX(0,J39)*Assumptions!$C$12 -> 3616.3966 | ... V42: =MAX(0,V39)*Assumptions!$C$12 -> 36402.978
B43: Unlevered Free Cash Flow | C43: =C39-C42-C41 -> 832.95525 | D43: =D39-D42-D41 -> 1247.2035 | E43: =E39-E42-E41 -> 1874.3576 | F43: =F39-F42-F41 -> 2826.3755 | G43: =G39-G42-G41 -> 4275.0098 | H43: =H39-H42-H41 -> 5664.8308 | I43: =I39-I42-I41 -> 7520.2237 | J43: =J39-J42-J41 -> 10000.008 | ... V43: =V39-V42-V41 -> 103745.5
B45: Scenario rationale
B46: Bear: Political headwinds limit DoD reliance on one contractor. Base: Golden Dome multi-billion follow-ons. Bull: Starshield becomes the de facto US/allied milspace backbone.

Sheet xAI_Software
B2: xAI Software (Grok + API)
B3: Consumer Grok subs, enterprise API revenue, X integration
B5: Scenario weights (from Scenario_Engine)
B6: Bear weight | C6: 0.15
B7: Base weight | C7: 0.6
B8: Bull weight | C8: 0.25
B9: Probability of materialization | C9: 0.98
B11: Substantiation & Sources
B12: Bear ($1.2B): consumer Grok subs only ($30 SuperGrok / $300 Heavy); no fed share; constrained API uptake
B13: Base ($2.0B): Quilty 2026 xAI/Grok forecast = $2B (vs $350M 2025, 5.7× growth); Grok 4.1 API + DoD $200M ceiling + GSA OneGov
B14: Bull ($3.5B): Grok captures meaningful share of $200-500B AI SW TAM by 2030; frontier + price advantage ($0.20/$0.50 per 1M tokens)
B15: Sources: Quilty 2026 forecast; Sacra xAI valuation tearsheet; xAI API pricing page; Mem0 Grok pricing; aibusinessweekly Grok stats
B17: Scenario assumptions (edit blue cells)
B18: Driver | C18: Bear | D18: Base | E18: Bull
B19: 2026 starting revenue ($M) | C19: 1800 | D19: 2000 | E19: 3500
B20: CAGR 2026→2030 (ramp) | C20: 0.25 | D20: 0.45 | E20: 0.65
B21: CAGR 2030→2035 (mid) | C21: 0.15 | D21: 0.35 | E21: 0.45
B22: CAGR 2035→2045 (mature) | C22: 0.06 | D22: 0.12 | E22: 0.2
B23: Mid-phase seed 2031 ($M, optional) | C23: 0 | D23: 0 | E23: 0
B24: Mature-phase seed 2036 ($M, optional) | C24: 0 | D24: 0 | E24: 0
B25: EBITDA margin | C25: 0.25 | D25: 0.4 | E25: 0.65
B26: CapEx (% of revenue) | C26: 0.15 | D26: 0.25 | E26: 0.35
B28: Revenue build ($M, by scenario)
B29: Year | C29: 2026 | D29: 2027 | E29: 2028 | F29: 2029 | G29: 2030 | H29: 2031 | I29: 2032 | J29: 2033 | K29: 2034 | L29: 2035 | M29: 2036 | N29: 2037 | O29: 2038 | P29: 2039 | Q29: 2040 | R29: 2041 | S29: 2042 | T29: 2043 | U29: 2044 | V29: 2045
B30: Bear revenue | C30: =$C$19 -> 1800 | D30: =C30*(1+$C$20) -> 2250 | E30: =D30*(1+$C$20) -> 2812.5 | F30: =E30*(1+$C$20) -> 3515.625 | G30: =F30*(1+$C$20) -> 4394.5312 | H30: =IF($C$23>0,$C$23,G30*(1+$C$21)) -> 5053.7109 | I30: =H30*(1+$C$21) -> 5811.7676 | J30: =I30*(1+$C$21) -> 6683.5327 | K30: =J30*(1+$C$21) -> 7686.0626 | L30: =K30*(1+$C$21) -> 8838.972 | M30: =IF($C$24>0,$C$24,L30*(1+$C$22)) -> 9369.3103 | N30: =M30*(1+$C$22) -> 9931.469 | O30: =N30*(1+$C$22) -> 10527.357 | P30: =O30*(1+$C$22) -> 11158.999 | Q30: =P30*(1+$C$22) -> 11828.538 | R30: =Q30*(1+$C$22) -> 12538.251 | S30: =R30*(1+$C$22) -> 13290.546 | T30: =S30*(1+$C$22) -> 14087.979 | U30: =T30*(1+$C$22) -> 14933.257 | V30: =U30*(1+$C$22) -> 15829.253
B31: Base revenue | C31: =$D$19 -> 2000 | D31: =C31*(1+$D$20) -> 2900 | E31: =D31*(1+$D$20) -> 4205 | F31: =E31*(1+$D$20) -> 6097.25 | G31: =F31*(1+$D$20) -> 8841.0125 | H31: =IF($D$23>0,$D$23,G31*(1+$D$21)) -> 11935.367 | I31: =H31*(1+$D$21) -> 16112.745 | J31: =I31*(1+$D$21) -> 21752.206 | K31: =J31*(1+$D$21) -> 29365.478 | L31: =K31*(1+$D$21) -> 39643.396 | M31: =IF($D$24>0,$D$24,L31*(1+$D$22)) -> 44400.603 | N31: =M31*(1+$D$22) -> 49728.676 | O31: =N31*(1+$D$22) -> 55696.117 | P31: =O31*(1+$D$22) -> 62379.651 | Q31: =P31*(1+$D$22) -> 69865.209 | R31: =Q31*(1+$D$22) -> 78249.034 | S31: =R31*(1+$D$22) -> 87638.918 | T31: =S31*(1+$D$22) -> 98155.588 | U31: =T31*(1+$D$22) -> 109934.26 | V31: =U31*(1+$D$22) -> 123126.37
B32: Bull revenue | C32: =$E$19 -> 3500 | D32: =C32*(1+$E$20) -> 5775 | E32: =D32*(1+$E$20) -> 9528.75 | F32: =E32*(1+$E$20) -> 15722.438 | G32: =F32*(1+$E$20) -> 25942.022 | H32: =IF($E$23>0,$E$23,G32*(1+$E$21)) -> 37615.932 | I32: =H32*(1+$E$21) -> 54543.101 | J32: =I32*(1+$E$21) -> 79087.496 | K32: =J32*(1+$E$21) -> 114676.87 | L32: =K32*(1+$E$21) -> 166281.46 | M32: =IF($E$24>0,$E$24,L32*(1+$E$22)) -> 199537.75 | N32: =M32*(1+$E$22) -> 239445.3 | O32: =N32*(1+$E$22) -> 287334.37 | P32: =O32*(1+$E$22) -> 344801.24 | Q32: =P32*(1+$E$22) -> 413761.49 | R32: =Q32*(1+$E$22) -> 496513.78 | S32: =R32*(1+$E$22) -> 595816.54 | T32: =S32*(1+$E$22) -> 714979.85 | U32: =T32*(1+$E$22) -> 857975.82 | V32: =U32*(1+$E$22) -> 1029571
B33: Scenario-weighted revenue | C33: =C30*$C$6+C31*$C$7+C32*$C$8 -> 2345 | D33: =D30*$C$6+D31*$C$7+D32*$C$8 -> 3521.25 | E33: =E30*$C$6+E31*$C$7+E32*$C$8 -> 5327.0625 | F33: =F30*$C$6+F31*$C$7+F32*$C$8 -> 8116.3031 | G33: =G30*$C$6+G31*$C$7+G32*$C$8 -> 12449.293 | H33: =H30*$C$6+H31*$C$7+H32*$C$8 -> 17323.26 | I33: =I30*$C$6+I31*$C$7+I32*$C$8 -> 24175.188 | J33: =J30*$C$6+J31*$C$7+J32*$C$8 -> 33825.728 | ... V33: =V30*$C$6+V31*$C$7+V32*$C$8 -> 333642.95
B34: Expected revenue (× materialization) | C34: =C33*$C$9 -> 2298.1 | D34: =D33*$C$9 -> 3450.825 | E34: =E33*$C$9 -> 5220.5212 | F34: =F33*$C$9 -> 7953.9771 | G34: =G33*$C$9 -> 12200.307 | H34: =H33*$C$9 -> 16976.795 | I34: =I33*$C$9 -> 23691.684 | J34: =J33*$C$9 -> 33149.213 | ... V34: =V33*$C$9 -> 326970.1
B36: Economics ($M)
B37: Year | C37: 2026 | D37: 2027 | E37: 2028 | F37: 2029 | G37: 2030 | H37: 2031 | I37: 2032 | J37: 2033 | K37: 2034 | L37: 2035 | M37: 2036 | N37: 2037 | O37: 2038 | P37: 2039 | Q37: 2040 | R37: 2041 | S37: 2042 | T37: 2043 | U37: 2044 | V37: 2045
B38: Blended EBITDA margin | C38: =IFERROR((C30*$C$6*$C$25+C31*$C$7*$D$25+C32*$C$8*$E$25)/C33,0) -> 0.47601279 | D38: =IFERROR((D30*$C$6*$C$25+D31*$C$7*$D$25+D32*$C$8*$E$25)/D33,0) -> 0.48812567 | E38: =IFERROR((E30*$C$6*$C$25+E31*$C$7*$D$25+E32*$C$8*$E$25)/E33,0) -> 0.49991729 | F38: =IFERROR((F30*$C$6*$C$25+F31*$C$7*$D$25+F32*$C$8*$E$25)/F33,0) -> 0.51132541 | G38: =IFERROR((G30*$C$6*$C$25+G31*$C$7*$D$25+G32*$C$8*$E$25)/G33,0) -> 0.52229606 | H38: =IFERROR((H30*$C$6*$C$25+H31*$C$7*$D$25+H32*$C$8*$E$25)/H33,0) -> 0.52914932 | I38: =IFERROR((I30*$C$6*$C$25+I31*$C$7*$D$25+I32*$C$8*$E$25)/I33,0) -> 0.53560098 | J38: =IFERROR((J30*$C$6*$C$25+J31*$C$7*$D$25+J32*$C$8*$E$25)/J33,0) -> 0.54168473 | ... V38: =IFERROR((V30*$C$6*$C$25+V31*$C$7*$D$25+V32*$C$8*$E$25)/V33,0) -> 0.59179793
B39: Expected EBITDA | C39: =C34*C38 -> 1093.925 | D39: =D34*D38 -> 1684.4362 | E39: =E34*E38 -> 2609.8288 | F39: =F34*F38 -> 4067.0706 | G39: =G34*G38 -> 6372.1721 | H39: =H34*H38 -> 8983.2593 | I39: =I34*I38 -> 12689.289 | J39: =J34*J38 -> 17956.423 | ... V39: =V34*V38 -> 193500.23
B40: Blended CapEx (% of revenue) | C40: =IFERROR((C30*$C$6*$C$26+C31*$C$7*$D$26+C32*$C$8*$E$26)/C33,0) -> 0.27579957 | D40: =IFERROR((D30*$C$6*$C$26+D31*$C$7*$D$26+D32*$C$8*$E$26)/D33,0) -> 0.2814164 | E40: =IFERROR((E30*$C$6*$C$26+E31*$C$7*$D$26+E32*$C$8*$E$26)/E33,0) -> 0.28679913 | F40: =IFERROR((F30*$C$6*$C$26+F31*$C$7*$D$26+F32*$C$8*$E$26)/F33,0) -> 0.29193123 | G40: =IFERROR((G30*$C$6*$C$26+G31*$C$7*$D$26+G32*$C$8*$E$26)/G33,0) -> 0.29680046 | H40: =IFERROR((H30*$C$6*$C$26+H31*$C$7*$D$26+H32*$C$8*$E$26)/H33,0) -> 0.29990935 | I40: =IFERROR((I30*$C$6*$C$26+I31*$C$7*$D$26+I32*$C$8*$E$26)/I33,0) -> 0.30279798 | J40: =IFERROR((J30*$C$6*$C$26+J31*$C$7*$D$26+J32*$C$8*$E$26)/J33,0) -> 0.30548837 | ... V40: =IFERROR((V30*$C$6*$C$26+V31*$C$7*$D$26+V32*$C$8*$E$26)/V33,0) -> 0.32643451
B41: Expected CapEx | C41: =C34*C40 -> 633.815 | D41: =D34*D40 -> 971.11875 | E41: =E34*E40 -> 1497.2409 | F41: =F34*F40 -> 2322.0143 | G41: =G34*G40 -> 3621.0566 | H41: =H34*H40 -> 5091.4994 | I41: =I34*I40 -> 7173.7939 | J41: =J34*J40 -> 10126.699 | ... V41: =V34*V40 -> 106734.32
B42: Tax on EBITDA (at Assumptions!$C$12) | C42: =MAX(0,C39)*Assumptions!$C$12 -> 229.72425 | D42: =MAX(0,D39)*Assumptions!$C$12 -> 353.73161 | E42: =MAX(0,E39)*Assumptions!$C$12 -> 548.06405 | F42: =MAX(0,F39)*Assumptions!$C$12 -> 854.08482 | G42: =MAX(0,G39)*Assumptions!$C$12 -> 1338.1562 | H42: =MAX(0,H39)*Assumptions!$C$12 -> 1886.4845 | I42: =MAX(0,I39)*Assumptions!$C$12 -> 2664.7507 | J42: =MAX(0,J39)*Assumptions!$C$12 -> 3770.8487 | ... V42: =MAX(0,V39)*Assumptions!$C$12 -> 40635.047
B43: Unlevered Free Cash Flow | C43: =C39-C42-C41 -> 230.38575 | D43: =D39-D42-D41 -> 359.58589 | E43: =E39-E42-E41 -> 564.52382 | F43: =F39-F42-F41 -> 890.97147 | G43: =G39-G42-G41 -> 1412.9594 | H43: =H39-H42-H41 -> 2005.2754 | I43: =I39-I42-I41 -> 2850.7444 | J43: =J39-J42-J41 -> 4058.8748 | ... V43: =V39-V42-V41 -> 46130.855
B45: Scenario rationale
B46: Bear: Commoditization, intense AI competition crushes margins. Base: Top-3 frontier lab; reasonable enterprise share. Bull: Wins consumer AI category via X distribution + space brand.

Sheet Colossus_DCs
B2: Colossus Terrestrial Data Centres
B3: Memphis + new sites; ~1M GPU equivalents added each year for 20 years at ~$30B/M-GPU mature pricing
B5: Scenario weights (from Scenario_Engine)
B6: Bear weight | C6: =Scenario_Engine!C13 -> 0.15
B7: Base weight | C7: =Scenario_Engine!D13 -> 0.5
B8: Bull weight | C8: =Scenario_Engine!E13 -> 0.35
B9: Probability of materialization | C9: =Scenario_Engine!G13 -> 0.85
B11: Substantiation & Sources
B12: Bear ($12B): Anthropic terminates ~70% of contract via 90-day clause; Cursor and smaller tenants offset partially
B13: Base ($16B): Anthropic $1.25B/mo × 12 = $15B/yr run-rate confirmed S-1; 2026 partial = ~$10-12B + Cursor + smaller
B14: Bull ($22B): 1M GPU/yr cohort adds; mature pricing ~$30B/M GPU; Colossus II GB200 ramp + new hyperscaler clients including Google
B15: Sources: Axios $15B/yr Anthropic (May 2026); Tesery $45B full breakdown S-1; TechCrunch termination clauses; HotHardware pre-IPO context
B17: Scenario assumptions (edit blue cells)
B18: Driver | C18: Bear | D18: Base | E18: Bull
B19: 2026 starting revenue ($M) | C19: 12000 | D19: 16000 | E19: 25000
B20: CAGR 2026→2030 (ramp) | C20: 0.15 | D20: 0.35 | E20: 0.55
B21: CAGR 2030→2035 (mid) | C21: 0.1 | D21: 0.2 | E21: 0.3
B22: CAGR 2035→2045 (mature) | C22: 0.05 | D22: 0.1 | E22: 0.15
B23: Mid-phase seed 2031 ($M, optional) | C23: 0 | D23: 0 | E23: 0
B24: Mature-phase seed 2036 ($M, optional) | C24: 0 | D24: 0 | E24: 0
B25: EBITDA margin | C25: 0.5 | D25: 0.65 | E25: 0.75
B26: CapEx (% of revenue) | C26: 0.6 | D26: 0.5 | E26: 0.4
B28: Revenue build ($M, by scenario)
B29: Year | C29: 2026 | D29: 2027 | E29: 2028 | F29: 2029 | G29: 2030 | H29: 2031 | I29: 2032 | J29: 2033 | K29: 2034 | L29: 2035 | M29: 2036 | N29: 2037 | O29: 2038 | P29: 2039 | Q29: 2040 | R29: 2041 | S29: 2042 | T29: 2043 | U29: 2044 | V29: 2045
B30: Bear revenue | C30: =$C$19 -> 12000 | D30: =C30*(1+$C$20) -> 13800 | E30: =D30*(1+$C$20) -> 15870 | F30: =E30*(1+$C$20) -> 18250.5 | G30: =F30*(1+$C$20) -> 20988.075 | H30: =IF($C$23>0,$C$23,G30*(1+$C$21)) -> 23086.882 | I30: =H30*(1+$C$21) -> 25395.571 | J30: =I30*(1+$C$21) -> 27935.128 | K30: =J30*(1+$C$21) -> 30728.641 | L30: =K30*(1+$C$21) -> 33801.505 | M30: =IF($C$24>0,$C$24,L30*(1+$C$22)) -> 35491.58 | N30: =M30*(1+$C$22) -> 37266.159 | O30: =N30*(1+$C$22) -> 39129.467 | P30: =O30*(1+$C$22) -> 41085.94 | Q30: =P30*(1+$C$22) -> 43140.237 | R30: =Q30*(1+$C$22) -> 45297.249 | S30: =R30*(1+$C$22) -> 47562.112 | T30: =S30*(1+$C$22) -> 49940.217 | U30: =T30*(1+$C$22) -> 52437.228 | V30: =U30*(1+$C$22) -> 55059.089
B31: Base revenue | C31: =$D$19 -> 16000 | D31: =C31*(1+$D$20) -> 21600 | E31: =D31*(1+$D$20) -> 29160 | F31: =E31*(1+$D$20) -> 39366 | G31: =F31*(1+$D$20) -> 53144.1 | H31: =IF($D$23>0,$D$23,G31*(1+$D$21)) -> 63772.92 | I31: =H31*(1+$D$21) -> 76527.504 | J31: =I31*(1+$D$21) -> 91833.005 | K31: =J31*(1+$D$21) -> 110199.61 | L31: =K31*(1+$D$21) -> 132239.53 | M31: =IF($D$24>0,$D$24,L31*(1+$D$22)) -> 145463.48 | N31: =M31*(1+$D$22) -> 160009.83 | O31: =N31*(1+$D$22) -> 176010.81 | P31: =O31*(1+$D$22) -> 193611.89 | Q31: =P31*(1+$D$22) -> 212973.08 | R31: =Q31*(1+$D$22) -> 234270.39 | S31: =R31*(1+$D$22) -> 257697.43 | T31: =S31*(1+$D$22) -> 283467.17 | U31: =T31*(1+$D$22) -> 311813.89 | V31: =U31*(1+$D$22) -> 342995.28
B32: Bull revenue | C32: =$E$19 -> 25000 | D32: =C32*(1+$E$20) -> 38750 | E32: =D32*(1+$E$20) -> 60062.5 | F32: =E32*(1+$E$20) -> 93096.875 | G32: =F32*(1+$E$20) -> 144300.16 | H32: =IF($E$23>0,$E$23,G32*(1+$E$21)) -> 187590.2 | I32: =H32*(1+$E$21) -> 243867.26 | J32: =I32*(1+$E$21) -> 317027.44 | K32: =J32*(1+$E$21) -> 412135.68 | L32: =K32*(1+$E$21) -> 535776.38 | M32: =IF($E$24>0,$E$24,L32*(1+$E$22)) -> 616142.84 | N32: =M32*(1+$E$22) -> 708564.26 | O32: =N32*(1+$E$22) -> 814848.9 | P32: =O32*(1+$E$22) -> 937076.24 | Q32: =P32*(1+$E$22) -> 1077637.7 | R32: =Q32*(1+$E$22) -> 1239283.3 | S32: =R32*(1+$E$22) -> 1425175.8 | T32: =S32*(1+$E$22) -> 1638952.2 | U32: =T32*(1+$E$22) -> 1884795 | V32: =U32*(1+$E$22) -> 2167514.3
B33: Scenario-weighted revenue | C33: =C30*$C$6+C31*$C$7+C32*$C$8 -> 18550 | D33: =D30*$C$6+D31*$C$7+D32*$C$8 -> 26432.5 | E33: =E30*$C$6+E31*$C$7+E32*$C$8 -> 37982.375 | F33: =F30*$C$6+F31*$C$7+F32*$C$8 -> 55004.481 | G33: =G30*$C$6+G31*$C$7+G32*$C$8 -> 80225.316 | H33: =H30*$C$6+H31*$C$7+H32*$C$8 -> 101006.06 | I33: =I30*$C$6+I31*$C$7+I32*$C$8 -> 127426.63 | J33: =J30*$C$6+J31*$C$7+J32*$C$8 -> 161066.38 | ... V33: =V30*$C$6+V31*$C$7+V32*$C$8 -> 938386.5
B34: Expected revenue (× materialization) | C34: =C33*$C$9 -> 15767.5 | D34: =D33*$C$9 -> 22467.625 | E34: =E33*$C$9 -> 32285.019 | F34: =F33*$C$9 -> 46753.809 | G34: =G33*$C$9 -> 68191.519 | H34: =H33*$C$9 -> 85855.154 | I34: =I33*$C$9 -> 108312.64 | J34: =J33*$C$9 -> 136906.42 | ... V34: =V33*$C$9 -> 797628.52
B36: Economics ($M)
B37: Year | C37: 2026 | D37: 2027 | E37: 2028 | F37: 2029 | G37: 2030 | H37: 2031 | I37: 2032 | J37: 2033 | K37: 2034 | L37: 2035 | M37: 2036 | N37: 2037 | O37: 2038 | P37: 2039 | Q37: 2040 | R37: 2041 | S37: 2042 | T37: 2043 | U37: 2044 | V37: 2045
B38: Blended EBITDA margin | C38: =IFERROR((C30*$C$6*$C$25+C31*$C$7*$D$25+C32*$C$8*$E$25)/C33,0) -> 0.68261456 | D38: =IFERROR((D30*$C$6*$C$25+D31*$C$7*$D$25+D32*$C$8*$E$25)/D33,0) -> 0.68956304 | E38: =IFERROR((E30*$C$6*$C$25+E31*$C$7*$D$25+E32*$C$8*$E$25)/E33,0) -> 0.69594532 | F38: =IFERROR((F30*$C$6*$C$25+F31*$C$7*$D$25+F32*$C$8*$E$25)/F33,0) -> 0.70177313 | G38: =IFERROR((G30*$C$6*$C$25+G31*$C$7*$D$25+G32*$C$8*$E$25)/G33,0) -> 0.70706769 | H38: =IFERROR((H30*$C$6*$C$25+H31*$C$7*$D$25+H32*$C$8*$E$25)/H33,0) -> 0.7098598 | I38: =IFERROR((I30*$C$6*$C$25+I31*$C$7*$D$25+I32*$C$8*$E$25)/I33,0) -> 0.71249835 | J38: =IFERROR((J30*$C$6*$C$25+J31*$C$7*$D$25+J32*$C$8*$E$25)/J33,0) -> 0.71498824 | ... V38: =IFERROR((V30*$C$6*$C$25+V31*$C$7*$D$25+V32*$C$8*$E$25)/V33,0) -> 0.72952392
B39: Expected EBITDA | C39: =C34*C38 -> 10763.125 | D39: =D34*D38 -> 15492.844 | E39: =E34*E38 -> 22468.608 | F39: =F34*F38 -> 32810.567 | G39: =G34*G38 -> 48216.02 | H39: =H34*H38 -> 60945.122 | I39: =I34*I38 -> 77172.574 | J39: =J34*J38 -> 97886.48 | ... V39: =V34*V38 -> 581889.08
B40: Blended CapEx (% of revenue) | C40: =IFERROR((C30*$C$6*$C$26+C31*$C$7*$D$26+C32*$C$8*$E$26)/C33,0) -> 0.46253369 | D40: =IFERROR((D30*$C$6*$C$26+D31*$C$7*$D$26+D32*$C$8*$E$26)/D33,0) -> 0.45652133 | E40: =IFERROR((E30*$C$6*$C$26+E31*$C$7*$D$26+E32*$C$8*$E$26)/E33,0) -> 0.45092099 | F40: =IFERROR((F30*$C$6*$C$26+F31*$C$7*$D$26+F32*$C$8*$E$26)/F33,0) -> 0.44573836 | G40: =IFERROR((G30*$C$6*$C$26+G31*$C$7*$D$26+G32*$C$8*$E$26)/G33,0) -> 0.4409702 | H40: =IFERROR((H30*$C$6*$C$26+H31*$C$7*$D$26+H32*$C$8*$E$26)/H33,0) -> 0.43842594 | I40: =IFERROR((I30*$C$6*$C$26+I31*$C$7*$D$26+I32*$C$8*$E$26)/I33,0) -> 0.43600693 | J40: =IFERROR((J30*$C$6*$C$26+J31*$C$7*$D$26+J32*$C$8*$E$26)/J33,0) -> 0.43371097 | ... V40: =IFERROR((V30*$C$6*$C$26+V31*$C$7*$D$26+V32*$C$8*$E$26)/V33,0) -> 0.42003603
B41: Expected CapEx | C41: =C34*C40 -> 7293 | D41: =D34*D40 -> 10256.95 | E41: =E34*E40 -> 14557.993 | F41: =F34*F40 -> 20839.966 | G41: =G34*G40 -> 30070.428 | H41: =H34*H40 -> 37641.126 | I41: =I34*I40 -> 47225.06 | J41: =J34*J40 -> 59377.817 | ... V41: =V34*V40 -> 335032.72
B42: Tax on EBITDA (at Assumptions!$C$12) | C42: =MAX(0,C39)*Assumptions!$C$12 -> 2260.2562 | D42: =MAX(0,D39)*Assumptions!$C$12 -> 3253.4972 | E42: =MAX(0,E39)*Assumptions!$C$12 -> 4718.4076 | F42: =MAX(0,F39)*Assumptions!$C$12 -> 6890.2191 | G42: =MAX(0,G39)*Assumptions!$C$12 -> 10125.364 | H42: =MAX(0,H39)*Assumptions!$C$12 -> 12798.476 | I42: =MAX(0,I39)*Assumptions!$C$12 -> 16206.241 | J42: =MAX(0,J39)*Assumptions!$C$12 -> 20556.161 | ... V42: =MAX(0,V39)*Assumptions!$C$12 -> 122196.71
B43: Unlevered Free Cash Flow | C43: =C39-C42-C41 -> 1209.8687 | D43: =D39-D42-D41 -> 1982.3966 | E43: =E39-E42-E41 -> 3192.2077 | F43: =F39-F42-F41 -> 5080.3816 | G43: =G39-G42-G41 -> 8020.228 | H43: =H39-H42-H41 -> 10505.52 | I43: =I39-I42-I41 -> 13741.273 | J43: =J39-J42-J41 -> 17952.503 | ... V43: =V39-V42-V41 -> 124659.66
B45: Scenario rationale
B46: Bear: Capacity additions slow due to power; external customer adoption weak. Base: 1M GPU/yr cadence, mature pricing reached by 2030s. Bull: Demand outstrips supply, premium pricing extends.

Sheet Crewed Trips
B2: Crew & Cargo Dragon
B3: NASA CCP, CRS, Axiom, Polaris private spaceflight
B5: Scenario weights (from Scenario_Engine)
B6: Bear weight | C6: =Scenario_Engine!$C$7 -> 0.15
B7: Base weight | C7: =Scenario_Engine!$D$7 -> 0.6
B8: Bull weight | C8: =Scenario_Engine!$E$7 -> 0.25
B9: Probability of materialization | C9: =Scenario_Engine!$G$7 -> 1
B11: Substantiation & Sources
B12: Bear ($700M): NASA CCP base recognition only (4 missions @ $280M); no PCM extension; limited private
B13: Base ($900M): NASA CCP ~$300M + CRS-2 cargo ~$700M + Polaris/Axiom private ~$200M = $1.2B annualized (prob-weighted)
B14: Bull ($1.1B): 6-mission PCM extension recognition (~$1.7B over 4 yrs) + Vast Haven-1 first crew 2027 + Axiom uplift
B15: Sources: NASA procurement intent May 2026 (6 PCMs sole-source); SpaceNews Crew Dragon extension; Polaris II Q4'25; Axiom Ax-5 Feb'26
B17: Scenario assumptions (edit blue cells)
B18: Driver | C18: Bear | D18: Base | E18: Bull
B19: 2026 starting revenue ($M) | C19: 700 | D19: 2000 | E19: 4000
B20: CAGR 2026→2030 (ramp) | C20: 0.1 | D20: 0.2 | E20: 0.3
B21: CAGR 2030→2035 (mid) | C21: 0.05 | D21: 0.15 | E21: 0.25
B22: CAGR 2035→2045 (mature) | C22: 0.02 | D22: 0.1 | E22: 0.15
B23: Mid-phase seed 2031 ($M, optional) | C23: 0 | D23: 0 | E23: 0
B24: Mature-phase seed 2036 ($M, optional) | C24: 0 | D24: 0 | E24: 0
B25: EBITDA margin | C25: 0.35 | D25: 0.45 | E25: 0.65
B26: CapEx (% of revenue) | C26: 0.08 | D26: 0.06 | E26: 0.05
B28: Revenue build ($M, by scenario)
B29: Year | C29: 2026 | D29: 2027 | E29: 2028 | F29: 2029 | G29: 2030 | H29: 2031 | I29: 2032 | J29: 2033 | K29: 2034 | L29: 2035 | M29: 2036 | N29: 2037 | O29: 2038 | P29: 2039 | Q29: 2040 | R29: 2041 | S29: 2042 | T29: 2043 | U29: 2044 | V29: 2045
B30: Bear revenue | C30: =$C$19 -> 700 | D30: =C30*(1+$C$20) -> 770 | E30: =D30*(1+$C$20) -> 847 | F30: =E30*(1+$C$20) -> 931.7 | G30: =F30*(1+$C$20) -> 1024.87 | H30: =IF($C$23>0,$C$23,G30*(1+$C$21)) -> 1076.1135 | I30: =H30*(1+$C$21) -> 1129.9192 | J30: =I30*(1+$C$21) -> 1186.4151 | K30: =J30*(1+$C$21) -> 1245.7359 | L30: =K30*(1+$C$21) -> 1308.0227 | M30: =IF($C$24>0,$C$24,L30*(1+$C$22)) -> 1334.1831 | N30: =M30*(1+$C$22) -> 1360.8668 | O30: =N30*(1+$C$22) -> 1388.0841 | P30: =O30*(1+$C$22) -> 1415.8458 | Q30: =P30*(1+$C$22) -> 1444.1627 | R30: =Q30*(1+$C$22) -> 1473.046 | S30: =R30*(1+$C$22) -> 1502.5069 | T30: =S30*(1+$C$22) -> 1532.557 | U30: =T30*(1+$C$22) -> 1563.2082 | V30: =U30*(1+$C$22) -> 1594.4724
B31: Base revenue | C31: =$D$19 -> 2000 | D31: =C31*(1+$D$20) -> 2400 | E31: =D31*(1+$D$20) -> 2880 | F31: =E31*(1+$D$20) -> 3456 | G31: =F31*(1+$D$20) -> 4147.2 | H31: =IF($D$23>0,$D$23,G31*(1+$D$21)) -> 4769.28 | I31: =H31*(1+$D$21) -> 5484.672 | J31: =I31*(1+$D$21) -> 6307.3728 | K31: =J31*(1+$D$21) -> 7253.4787 | L31: =K31*(1+$D$21) -> 8341.5005 | M31: =IF($D$24>0,$D$24,L31*(1+$D$22)) -> 9175.6506 | N31: =M31*(1+$D$22) -> 10093.216 | O31: =N31*(1+$D$22) -> 11102.537 | P31: =O31*(1+$D$22) -> 12212.791 | Q31: =P31*(1+$D$22) -> 13434.07 | R31: =Q31*(1+$D$22) -> 14777.477 | S31: =R31*(1+$D$22) -> 16255.225 | T31: =S31*(1+$D$22) -> 17880.747 | U31: =T31*(1+$D$22) -> 19668.822 | V31: =U31*(1+$D$22) -> 21635.704
B32: Bull revenue | C32: =$E$19 -> 4000 | D32: =C32*(1+$E$20) -> 5200 | E32: =D32*(1+$E$20) -> 6760 | F32: =E32*(1+$E$20) -> 8788 | G32: =F32*(1+$E$20) -> 11424.4 | H32: =IF($E$23>0,$E$23,G32*(1+$E$21)) -> 14280.5 | I32: =H32*(1+$E$21) -> 17850.625 | J32: =I32*(1+$E$21) -> 22313.281 | K32: =J32*(1+$E$21) -> 27891.602 | L32: =K32*(1+$E$21) -> 34864.502 | M32: =IF($E$24>0,$E$24,L32*(1+$E$22)) -> 40094.177 | N32: =M32*(1+$E$22) -> 46108.304 | O32: =N32*(1+$E$22) -> 53024.549 | P32: =O32*(1+$E$22) -> 60978.232 | Q32: =P32*(1+$E$22) -> 70124.967 | R32: =Q32*(1+$E$22) -> 80643.712 | S32: =R32*(1+$E$22) -> 92740.268 | T32: =S32*(1+$E$22) -> 106651.31 | U32: =T32*(1+$E$22) -> 122649 | V32: =U32*(1+$E$22) -> 141046.36
B33: Scenario-weighted revenue | C33: =C30*$C$6+C31*$C$7+C32*$C$8 -> 2305 | D33: =D30*$C$6+D31*$C$7+D32*$C$8 -> 2855.5 | E33: =E30*$C$6+E31*$C$7+E32*$C$8 -> 3545.05 | F33: =F30*$C$6+F31*$C$7+F32*$C$8 -> 4410.355 | G33: =G30*$C$6+G31*$C$7+G32*$C$8 -> 5498.1505 | H33: =H30*$C$6+H31*$C$7+H32*$C$8 -> 6593.11 | I33: =I30*$C$6+I31*$C$7+I32*$C$8 -> 7922.9473 | J33: =J30*$C$6+J31*$C$7+J32*$C$8 -> 9540.7063 | ... V33: =V30*$C$6+V31*$C$7+V32*$C$8 -> 48482.182
B34: Expected revenue (× materialization) | C34: =C33*$C$9 -> 2305 | D34: =D33*$C$9 -> 2855.5 | E34: =E33*$C$9 -> 3545.05 | F34: =F33*$C$9 -> 4410.355 | G34: =G33*$C$9 -> 5498.1505 | H34: =H33*$C$9 -> 6593.11 | I34: =I33*$C$9 -> 7922.9473 | J34: =J33*$C$9 -> 9540.7063 | ... V34: =V33*$C$9 -> 48482.182
B36: Economics ($M)
B37: Year | C37: 2026 | D37: 2027 | E37: 2028 | F37: 2029 | G37: 2030 | H37: 2031 | I37: 2032 | J37: 2033 | K37: 2034 | L37: 2035 | M37: 2036 | N37: 2037 | O37: 2038 | P37: 2039 | Q37: 2040 | R37: 2041 | S37: 2042 | T37: 2043 | U37: 2044 | V37: 2045
B38: Blended EBITDA margin | C38: =IFERROR((C30*$C$6*$C$25+C31*$C$7*$D$25+C32*$C$8*$E$25)/C33,0) -> 0.53221258 | D38: =IFERROR((D30*$C$6*$C$25+D31*$C$7*$D$25+D32*$C$8*$E$25)/D33,0) -> 0.53700753 | E38: =IFERROR((E30*$C$6*$C$25+E31*$C$7*$D$25+E32*$C$8*$E$25)/E33,0) -> 0.54176034 | F38: =IFERROR((F30*$C$6*$C$25+F31*$C$7*$D$25+F32*$C$8*$E$25)/F33,0) -> 0.54646038 | G38: =IFERROR((G30*$C$6*$C$25+G31*$C$7*$D$25+G32*$C$8*$E$25)/G33,0) -> 0.55109708 | H38: =IFERROR((H30*$C$6*$C$25+H31*$C$7*$D$25+H32*$C$8*$E$25)/H33,0) -> 0.55585039 | I38: =IFERROR((I30*$C$6*$C$25+I31*$C$7*$D$25+I32*$C$8*$E$25)/I33,0) -> 0.56051222 | J38: =IFERROR((J30*$C$6*$C$25+J31*$C$7*$D$25+J32*$C$8*$E$25)/J33,0) -> 0.56507197 | ... V38: =IFERROR((V30*$C$6*$C$25+V31*$C$7*$D$25+V32*$C$8*$E$25)/V33,0) -> 0.59496874
B39: Expected EBITDA | C39: =C34*C38 -> 1226.75 | D39: =D34*D38 -> 1533.425 | E39: =E34*E38 -> 1920.5675 | F39: =F34*F38 -> 2410.0842 | G39: =G34*G38 -> 3030.0147 | H39: =H34*H38 -> 3664.7828 | I39: =I34*I38 -> 4440.9088 | J39: =J34*J38 -> 5391.1857 | ... V39: =V34*V38 -> 28845.383
B40: Blended CapEx (% of revenue) | C40: =IFERROR((C30*$C$6*$C$26+C31*$C$7*$D$26+C32*$C$8*$E$26)/C33,0) -> 0.056572668 | D40: =IFERROR((D30*$C$6*$C$26+D31*$C$7*$D$26+D32*$C$8*$E$26)/D33,0) -> 0.056256347 | E40: =IFERROR((E30*$C$6*$C$26+E31*$C$7*$D$26+E32*$C$8*$E$26)/E33,0) -> 0.055949563 | F40: =IFERROR((F30*$C$6*$C$26+F31*$C$7*$D$26+F32*$C$8*$E$26)/F33,0) -> 0.0556523 | G40: =IFERROR((G30*$C$6*$C$26+G31*$C$7*$D$26+G32*$C$8*$E$26)/G33,0) -> 0.055364552 | H40: =IFERROR((H30*$C$6*$C$26+H31*$C$7*$D$26+H32*$C$8*$E$26)/H33,0) -> 0.055074721 | I40: =IFERROR((I30*$C$6*$C$26+I31*$C$7*$D$26+I32*$C$8*$E$26)/I33,0) -> 0.05479527 | J40: =IFERROR((J30*$C$6*$C$26+J31*$C$7*$D$26+J32*$C$8*$E$26)/J33,0) -> 0.054526196 | ... V40: =IFERROR((V30*$C$6*$C$26+V31*$C$7*$D$26+V32*$C$8*$E$26)/V33,0) -> 0.052825561
B41: Expected CapEx | C41: =C34*C40 -> 130.4 | D41: =D34*D40 -> 160.64 | E41: =E34*E40 -> 198.344 | F41: =F34*F40 -> 245.4464 | G41: =G34*G40 -> 304.40264 | H41: =H34*H40 -> 363.11369 | I41: =I34*I40 -> 434.14003 | J41: =J34*J40 -> 520.21842 | ... V41: =V34*V40 -> 2561.0985
B42: Tax on EBITDA (at Assumptions!$C$12) | C42: =MAX(0,C39)*Assumptions!$C$12 -> 257.6175 | D42: =MAX(0,D39)*Assumptions!$C$12 -> 322.01925 | E42: =MAX(0,E39)*Assumptions!$C$12 -> 403.31918 | F42: =MAX(0,F39)*Assumptions!$C$12 -> 506.11769 | G42: =MAX(0,G39)*Assumptions!$C$12 -> 636.30308 | H42: =MAX(0,H39)*Assumptions!$C$12 -> 769.60439 | I42: =MAX(0,I39)*Assumptions!$C$12 -> 932.59084 | J42: =MAX(0,J39)*Assumptions!$C$12 -> 1132.149 | ... V42: =MAX(0,V39)*Assumptions!$C$12 -> 6057.5304
B43: Unlevered Free Cash Flow | C43: =C39-C42-C41 -> 838.7325 | D43: =D39-D42-D41 -> 1050.7658 | E43: =E39-E42-E41 -> 1318.9043 | F43: =F39-F42-F41 -> 1658.5202 | G43: =G39-G42-G41 -> 2089.309 | H43: =H39-H42-H41 -> 2532.0647 | I43: =I39-I42-I41 -> 3074.1779 | J43: =J39-J42-J41 -> 3738.8182 | ... V43: =V39-V42-V41 -> 20226.754
B45: Consolidation adjustment — Revenue ($M) | C45: 142.8 | D45: 196.28 | E45: 273.168 | F45: 384.6878 | G45: 547.7562 | H45: 712.8198 | I45: 890.0342 | J45: 1118.1794 | K45: 1413.8351 | L45: 1799.7202 | M45: 2080.7161 | N45: 2405.36 | O45: 2794.9114 | P45: 3266.332 | Q45: 3842.0649 | R45: 4552.0333 | S45: 5436.4093 | T45: 6549.4564 | U45: 7964.8703 | V45: 9783.2102
B46: Consolidation adjustment — EBITDA ($M) | C46: 55.86 | D46: 78.946 | E46: 112.7406 | F46: 162.5672 | G46: 236.51 | H46: 304.4245 | I46: 384.3212 | J46: 487.5379 | K46: 621.5452 | L46: 796.4661 | M46: 914.2865 | N46: 1056.4855 | O46: 1225.6241 | P46: 1428.2529 | Q46: 1672.929 | R46: 1970.9277 | S46: 2337.2258 | T46: 2791.8628 | U46: 3361.8274 | V46: 4083.6798
B47: Consolidation adjustment — UFCF ($M) | C47: 34.0494 | D47: 48.8993 | E47: 70.8413 | F47: 103.4619 | G47: 152.2274 | H47: 183.0718 | I47: 231.1115 | J47: 292.4054 | K47: 370.6459 | L47: 470.5208 | M47: 523.9872 | N47: 592.9343 | O47: 670.2562 | P47: 756.598 | Q47: 852.4758 | R47: 958.1691 | S47: 1073.5631 | T47: 1197.9172 | U47: 1329.5324 | V47: 1465.2721

Sheet Starlink_D2C
B2: Starlink Direct-to-Cell
B3: Satellite-to-mobile partnerships (T-Mobile, KDDI, Optus, Rogers...)
B5: Scenario weights (from Scenario_Engine)
B6: Bear weight | C6: =Scenario_Engine!$C$10 -> 0.2
B7: Base weight | C7: =Scenario_Engine!$D$10 -> 0.6
B8: Bull weight | C8: =Scenario_Engine!$E$10 -> 0.2
B9: Probability of materialization | C9: =Scenario_Engine!$G$10 -> 0.98
B11: Substantiation & Sources
B12: Bear ($500M): T-Mobile launch only; 2-3% sub penetration; minimal int'l
B13: Base ($1.0B): T-Mobile commercial Jul'25; 5% of 116M sub penetration × $15/mo = $1.04B; intl (Optus, KDDI, Rogers, Salt) adds
B14: Bull ($1.5B): T-Mobile 1-yr exclusivity through Jul'26 + intl rollouts + Gen2 v2 mini D2C constellation scaling
B15: Sources: TAM: ~400bln annually across global celular. SatelliteInternet T-Mobile D2C 2026 guide; Teslarati Big-3 JV response (May 14, 2026)
B17: Scenario assumptions (edit blue cells)
B18: Driver | C18: Bear | D18: Base | E18: Bull
B19: 2026 starting revenue ($M) | C19: 500 | D19: 1000 | E19: 1500
B20: CAGR 2026→2030 (ramp) | C20: 0.4 | D20: 0.7 | E20: 1
B21: CAGR 2030→2035 (mid) | C21: 0.2 | D21: 0.4 | E21: 0.7
B22: CAGR 2035→2045 (mature) | C22: 0.05 | D22: 0.1 | E22: 0.3
B23: Mid-phase seed 2031 ($M, optional) | C23: 0 | D23: 0 | E23: 0
B24: Mature-phase seed 2036 ($M, optional) | C24: 0 | D24: 0 | E24: 0
B25: EBITDA margin | C25: 0.4 | D25: 0.55 | E25: 0.7
B26: CapEx (% of revenue) | C26: 0.2 | D26: 0.15 | E26: 0.1
B28: Revenue build ($M, by scenario)
B29: Year | C29: 2026 | D29: 2027 | E29: 2028 | F29: 2029 | G29: 2030 | H29: 2031 | I29: 2032 | J29: 2033 | K29: 2034 | L29: 2035 | M29: 2036 | N29: 2037 | O29: 2038 | P29: 2039 | Q29: 2040 | R29: 2041 | S29: 2042 | T29: 2043 | U29: 2044 | V29: 2045
B30: Bear revenue | C30: =$C$19 -> 500 | D30: =C30*(1+$C$20) -> 700 | E30: =D30*(1+$C$20) -> 980 | F30: =E30*(1+$C$20) -> 1372 | G30: =F30*(1+$C$20) -> 1920.8 | H30: =IF($C$23>0,$C$23,G30*(1+$C$21)) -> 2304.96 | I30: =H30*(1+$C$21) -> 2765.952 | J30: =I30*(1+$C$21) -> 3319.1424 | K30: =J30*(1+$C$21) -> 3982.9709 | L30: =K30*(1+$C$21) -> 4779.5651 | M30: =IF($C$24>0,$C$24,L30*(1+$C$22)) -> 5018.5433 | N30: =M30*(1+$C$22) -> 5269.4705 | O30: =N30*(1+$C$22) -> 5532.944 | P30: =O30*(1+$C$22) -> 5809.5912 | Q30: =P30*(1+$C$22) -> 6100.0708 | R30: =Q30*(1+$C$22) -> 6405.0743 | S30: =R30*(1+$C$22) -> 6725.328 | T30: =S30*(1+$C$22) -> 7061.5944 | U30: =T30*(1+$C$22) -> 7414.6741 | V30: =U30*(1+$C$22) -> 7785.4078
B31: Base revenue | C31: =$D$19 -> 1000 | D31: =C31*(1+$D$20) -> 1700 | E31: =D31*(1+$D$20) -> 2890 | F31: =E31*(1+$D$20) -> 4913 | G31: =F31*(1+$D$20) -> 8352.1 | H31: =IF($D$23>0,$D$23,G31*(1+$D$21)) -> 11692.94 | I31: =H31*(1+$D$21) -> 16370.116 | J31: =I31*(1+$D$21) -> 22918.162 | K31: =J31*(1+$D$21) -> 32085.427 | L31: =K31*(1+$D$21) -> 44919.598 | M31: =IF($D$24>0,$D$24,L31*(1+$D$22)) -> 49411.558 | N31: =M31*(1+$D$22) -> 54352.714 | O31: =N31*(1+$D$22) -> 59787.985 | P31: =O31*(1+$D$22) -> 65766.784 | Q31: =P31*(1+$D$22) -> 72343.462 | R31: =Q31*(1+$D$22) -> 79577.808 | S31: =R31*(1+$D$22) -> 87535.589 | T31: =S31*(1+$D$22) -> 96289.148 | U31: =T31*(1+$D$22) -> 105918.06 | V31: =U31*(1+$D$22) -> 116509.87
B32: Bull revenue | C32: =$E$19 -> 1500 | D32: =C32*(1+$E$20) -> 3000 | E32: =D32*(1+$E$20) -> 6000 | F32: =E32*(1+$E$20) -> 12000 | G32: =F32*(1+$E$20) -> 24000 | H32: =IF($E$23>0,$E$23,G32*(1+$E$21)) -> 40800 | I32: =H32*(1+$E$21) -> 69360 | J32: =I32*(1+$E$21) -> 117912 | K32: =J32*(1+$E$21) -> 200450.4 | L32: =K32*(1+$E$21) -> 340765.68 | M32: =IF($E$24>0,$E$24,L32*(1+$E$22)) -> 442995.38 | N32: =M32*(1+$E$22) -> 575894 | O32: =N32*(1+$E$22) -> 748662.2 | P32: =O32*(1+$E$22) -> 973260.86 | Q32: =P32*(1+$E$22) -> 1265239.1 | R32: =Q32*(1+$E$22) -> 1644810.9 | S32: =R32*(1+$E$22) -> 2138254.1 | T32: =S32*(1+$E$22) -> 2779730.3 | U32: =T32*(1+$E$22) -> 3613649.4 | V32: =U32*(1+$E$22) -> 4697744.3
B33: Scenario-weighted revenue | C33: =C30*$C$6+C31*$C$7+C32*$C$8 -> 1000 | D33: =D30*$C$6+D31*$C$7+D32*$C$8 -> 1760 | E33: =E30*$C$6+E31*$C$7+E32*$C$8 -> 3130 | F33: =F30*$C$6+F31*$C$7+F32*$C$8 -> 5622.2 | G33: =G30*$C$6+G31*$C$7+G32*$C$8 -> 10195.42 | H33: =H30*$C$6+H31*$C$7+H32*$C$8 -> 15636.756 | I33: =I30*$C$6+I31*$C$7+I32*$C$8 -> 24247.26 | J33: =J30*$C$6+J31*$C$7+J32*$C$8 -> 37997.126 | ... V33: =V30*$C$6+V31*$C$7+V32*$C$8 -> 1011011.9
B34: Expected revenue (× materialization) | C34: =C33*$C$9 -> 980 | D34: =D33*$C$9 -> 1724.8 | E34: =E33*$C$9 -> 3067.4 | F34: =F33*$C$9 -> 5509.756 | G34: =G33*$C$9 -> 9991.5116 | H34: =H33*$C$9 -> 15324.021 | I34: =I33*$C$9 -> 23762.315 | J34: =J33*$C$9 -> 37237.183 | ... V34: =V33*$C$9 -> 990791.62
B36: Economics ($M)
B37: Year | C37: 2026 | D37: 2027 | E37: 2028 | F37: 2029 | G37: 2030 | H37: 2031 | I37: 2032 | J37: 2033 | K37: 2034 | L37: 2035 | M37: 2036 | N37: 2037 | O37: 2038 | P37: 2039 | Q37: 2040 | R37: 2041 | S37: 2042 | T37: 2043 | U37: 2044 | V37: 2045
B38: Blended EBITDA margin | C38: =IFERROR((C30*$C$6*$C$25+C31*$C$7*$D$25+C32*$C$8*$E$25)/C33,0) -> 0.58 | D38: =IFERROR((D30*$C$6*$C$25+D31*$C$7*$D$25+D32*$C$8*$E$25)/D33,0) -> 0.58920455 | E38: =IFERROR((E30*$C$6*$C$25+E31*$C$7*$D$25+E32*$C$8*$E$25)/E33,0) -> 0.59811502 | F38: =IFERROR((F30*$C$6*$C$25+F31*$C$7*$D$25+F32*$C$8*$E$25)/F33,0) -> 0.6067109 | G38: =IFERROR((G30*$C$6*$C$25+G31*$C$7*$D$25+G32*$C$8*$E$25)/G33,0) -> 0.614968 | H38: =IFERROR((H30*$C$6*$C$25+H31*$C$7*$D$25+H32*$C$8*$E$25)/H33,0) -> 0.62385491 | I38: =IFERROR((I30*$C$6*$C$25+I31*$C$7*$D$25+I32*$C$8*$E$25)/I33,0) -> 0.6323937 | J38: =IFERROR((J30*$C$6*$C$25+J31*$C$7*$D$25+J32*$C$8*$E$25)/J33,0) -> 0.64047489 | ... V38: =IFERROR((V30*$C$6*$C$25+V31*$C$7*$D$25+V32*$C$8*$E$25)/V33,0) -> 0.68916629
B39: Expected EBITDA | C39: =C34*C38 -> 568.4 | D39: =D34*D38 -> 1016.26 | E39: =E34*E38 -> 1834.658 | F39: =F34*F38 -> 3342.829 | G39: =G34*G38 -> 6144.4599 | H39: =H34*H38 -> 9559.9657 | I39: =I34*I38 -> 15027.138 | J39: =J34*J38 -> 23849.481 | ... V39: =V34*V38 -> 682820.18
B40: Blended CapEx (% of revenue) | C40: =IFERROR((C30*$C$6*$C$26+C31*$C$7*$D$26+C32*$C$8*$E$26)/C33,0) -> 0.14 | D40: =IFERROR((D30*$C$6*$C$26+D31*$C$7*$D$26+D32*$C$8*$E$26)/D33,0) -> 0.13693182 | E40: =IFERROR((E30*$C$6*$C$26+E31*$C$7*$D$26+E32*$C$8*$E$26)/E33,0) -> 0.13396166 | F40: =IFERROR((F30*$C$6*$C$26+F31*$C$7*$D$26+F32*$C$8*$E$26)/F33,0) -> 0.13109637 | G40: =IFERROR((G30*$C$6*$C$26+G31*$C$7*$D$26+G32*$C$8*$E$26)/G33,0) -> 0.128344 | H40: =IFERROR((H30*$C$6*$C$26+H31*$C$7*$D$26+H32*$C$8*$E$26)/H33,0) -> 0.1253817 | I40: =IFERROR((I30*$C$6*$C$26+I31*$C$7*$D$26+I32*$C$8*$E$26)/I33,0) -> 0.12253543 | J40: =IFERROR((J30*$C$6*$C$26+J31*$C$7*$D$26+J32*$C$8*$E$26)/J33,0) -> 0.1198417 | ... V40: =IFERROR((V30*$C$6*$C$26+V31*$C$7*$D$26+V32*$C$8*$E$26)/V33,0) -> 0.10361124
B41: Expected CapEx | C41: =C34*C40 -> 137.2 | D41: =D34*D40 -> 236.18 | E41: =E34*E40 -> 410.914 | F41: =F34*F40 -> 722.309 | G41: =G34*G40 -> 1282.3506 | H41: =H34*H40 -> 1921.3517 | I41: =I34*I40 -> 2911.7255 | J41: =J34*J40 -> 4462.5675 | ... V41: =V34*V40 -> 102657.15
B42: Tax on EBITDA (at Assumptions!$C$12) | C42: =MAX(0,C39)*Assumptions!$C$12 -> 119.364 | D42: =MAX(0,D39)*Assumptions!$C$12 -> 213.4146 | E42: =MAX(0,E39)*Assumptions!$C$12 -> 385.27818 | F42: =MAX(0,F39)*Assumptions!$C$12 -> 701.99409 | G42: =MAX(0,G39)*Assumptions!$C$12 -> 1290.3366 | H42: =MAX(0,H39)*Assumptions!$C$12 -> 2007.5928 | I42: =MAX(0,I39)*Assumptions!$C$12 -> 3155.699 | J42: =MAX(0,J39)*Assumptions!$C$12 -> 5008.391 | ... V42: =MAX(0,V39)*Assumptions!$C$12 -> 143392.24
B43: Unlevered Free Cash Flow | C43: =C39-C42-C41 -> 311.836 | D43: =D39-D42-D41 -> 566.6654 | E43: =E39-E42-E41 -> 1038.4658 | F43: =F39-F42-F41 -> 1918.5259 | G43: =G39-G42-G41 -> 3571.7727 | H43: =H39-H42-H41 -> 5631.0211 | I43: =I39-I42-I41 -> 8959.7136 | J43: =J39-J42-J41 -> 14378.522 | ... V43: =V39-V42-V41 -> 436770.8
B45: Scenario rationale
B46: Bear: Spectrum policy delays, slow international rollout. Base: Major carriers worldwide; voice + light data by 2027. Bull: D2C becomes default backup; LEO broadband-to-phone.

Sheet Other_Services
B2: Other Services
B3: Other services related to launch and orbital logistics
B5: Scenario weights (from Scenario_Engine)
B6: Bear weight | C6: =Scenario_Engine!C8 -> 0.3
B7: Base weight | C7: =Scenario_Engine!D8 -> 0.5
B8: Bull weight | C8: =Scenario_Engine!E8 -> 0.2
B9: Probability of materialization | C9: =Scenario_Engine!G8 -> 0.65
B11: Substantiation & Sources
B17: Scenario assumptions (edit blue cells)
B18: Driver | C18: Bear | D18: Base | E18: Bull
B19: 2026 starting revenue ($M) | C19: 100 | D19: 200 | E19: 500
B20: CAGR 2026→2030 (ramp) | C20: 0.1 | D20: 0.35 | E20: 0.5
B21: CAGR 2030→2035 (mid) | C21: 0.1 | D21: 0.25 | E21: 0.35
B22: CAGR 2035→2045 (mature) | C22: 0.05 | D22: 0.1 | E22: 0.25
B23: Mid-phase seed 2031 ($M, optional) | C23: 0 | D23: 0 | E23: 0
B24: Mature-phase seed 2036 ($M, optional) | C24: 0 | D24: 0 | E24: 0
B25: EBITDA margin | C25: 0.35 | D25: 0.45 | E25: 0.65
B26: CapEx (% of revenue) | C26: 0.2 | D26: 0.2 | E26: 0.2
B28: Revenue build ($M, by scenario)
B29: Year | C29: 2026 | D29: 2027 | E29: 2028 | F29: 2029 | G29: 2030 | H29: 2031 | I29: 2032 | J29: 2033 | K29: 2034 | L29: 2035 | M29: 2036 | N29: 2037 | O29: 2038 | P29: 2039 | Q29: 2040 | R29: 2041 | S29: 2042 | T29: 2043 | U29: 2044 | V29: 2045
B30: Bear revenue | C30: =$C$19 -> 100 | D30: =C30*(1+$C$20) -> 110 | E30: =D30*(1+$C$20) -> 121 | F30: =E30*(1+$C$20) -> 133.1 | G30: =F30*(1+$C$20) -> 146.41 | H30: =IF($C$23>0,$C$23,G30*(1+$C$21)) -> 161.051 | I30: =H30*(1+$C$21) -> 177.1561 | J30: =I30*(1+$C$21) -> 194.87171 | K30: =J30*(1+$C$21) -> 214.35888 | L30: =K30*(1+$C$21) -> 235.79477 | M30: =IF($C$24>0,$C$24,L30*(1+$C$22)) -> 247.58451 | N30: =M30*(1+$C$22) -> 259.96373 | O30: =N30*(1+$C$22) -> 272.96192 | P30: =O30*(1+$C$22) -> 286.61002 | Q30: =P30*(1+$C$22) -> 300.94052 | R30: =Q30*(1+$C$22) -> 315.98754 | S30: =R30*(1+$C$22) -> 331.78692 | T30: =S30*(1+$C$22) -> 348.37627 | U30: =T30*(1+$C$22) -> 365.79508 | V30: =U30*(1+$C$22) -> 384.08483
B31: Base revenue | C31: =$D$19 -> 200 | D31: =C31*(1+$D$20) -> 270 | E31: =D31*(1+$D$20) -> 364.5 | F31: =E31*(1+$D$20) -> 492.075 | G31: =F31*(1+$D$20) -> 664.30125 | H31: =IF($D$23>0,$D$23,G31*(1+$D$21)) -> 830.37656 | I31: =H31*(1+$D$21) -> 1037.9707 | J31: =I31*(1+$D$21) -> 1297.4634 | K31: =J31*(1+$D$21) -> 1621.8292 | L31: =K31*(1+$D$21) -> 2027.2865 | M31: =IF($D$24>0,$D$24,L31*(1+$D$22)) -> 2230.0152 | N31: =M31*(1+$D$22) -> 2453.0167 | O31: =N31*(1+$D$22) -> 2698.3184 | P31: =O31*(1+$D$22) -> 2968.1502 | Q31: =P31*(1+$D$22) -> 3264.9652 | R31: =Q31*(1+$D$22) -> 3591.4618 | S31: =R31*(1+$D$22) -> 3950.6079 | T31: =S31*(1+$D$22) -> 4345.6687 | U31: =T31*(1+$D$22) -> 4780.2356 | V31: =U31*(1+$D$22) -> 5258.2592
B32: Bull revenue | C32: =$E$19 -> 500 | D32: =C32*(1+$E$20) -> 750 | E32: =D32*(1+$E$20) -> 1125 | F32: =E32*(1+$E$20) -> 1687.5 | G32: =F32*(1+$E$20) -> 2531.25 | H32: =IF($E$23>0,$E$23,G32*(1+$E$21)) -> 3417.1875 | I32: =H32*(1+$E$21) -> 4613.2031 | J32: =I32*(1+$E$21) -> 6227.8242 | K32: =J32*(1+$E$21) -> 8407.5627 | L32: =K32*(1+$E$21) -> 11350.21 | M32: =IF($E$24>0,$E$24,L32*(1+$E$22)) -> 14187.762 | N32: =M32*(1+$E$22) -> 17734.703 | O32: =N32*(1+$E$22) -> 22168.378 | P32: =O32*(1+$E$22) -> 27710.473 | Q32: =P32*(1+$E$22) -> 34638.091 | R32: =Q32*(1+$E$22) -> 43297.614 | S32: =R32*(1+$E$22) -> 54122.017 | T32: =S32*(1+$E$22) -> 67652.521 | U32: =T32*(1+$E$22) -> 84565.652 | V32: =U32*(1+$E$22) -> 105707.06
B33: Scenario-weighted revenue | C33: =C30*$C$6+C31*$C$7+C32*$C$8 -> 230 | D33: =D30*$C$6+D31*$C$7+D32*$C$8 -> 318 | E33: =E30*$C$6+E31*$C$7+E32*$C$8 -> 443.55 | F33: =F30*$C$6+F31*$C$7+F32*$C$8 -> 623.4675 | G33: =G30*$C$6+G31*$C$7+G32*$C$8 -> 882.32362 | H33: =H30*$C$6+H31*$C$7+H32*$C$8 -> 1146.9411 | I33: =I30*$C$6+I31*$C$7+I32*$C$8 -> 1494.7728 | J33: =J30*$C$6+J31*$C$7+J32*$C$8 -> 1952.758 | ... V33: =V30*$C$6+V31*$C$7+V32*$C$8 -> 23885.768
B34: Expected revenue (× materialization) | C34: =C33*$C$9 -> 149.5 | D34: =D33*$C$9 -> 206.7 | E34: =E33*$C$9 -> 288.3075 | F34: =F33*$C$9 -> 405.25387 | G34: =G33*$C$9 -> 573.51036 | H34: =H33*$C$9 -> 745.5117 | I34: =I33*$C$9 -> 971.60232 | J34: =J33*$C$9 -> 1269.2927 | ... V34: =V33*$C$9 -> 15525.749
B36: Economics ($M)
B37: Year | C37: 2026 | D37: 2027 | E37: 2028 | F37: 2029 | G37: 2030 | H37: 2031 | I37: 2032 | J37: 2033 | K37: 2034 | L37: 2035 | M37: 2036 | N37: 2037 | O37: 2038 | P37: 2039 | Q37: 2040 | R37: 2041 | S37: 2042 | T37: 2043 | U37: 2044 | V37: 2045
B38: Blended EBITDA margin | C38: =IFERROR((C30*$C$6*$C$25+C31*$C$7*$D$25+C32*$C$8*$E$25)/C33,0) -> 0.52391304 | D38: =IFERROR((D30*$C$6*$C$25+D31*$C$7*$D$25+D32*$C$8*$E$25)/D33,0) -> 0.53396226 | E38: =IFERROR((E30*$C$6*$C$25+E31*$C$7*$D$25+E32*$C$8*$E$25)/E33,0) -> 0.54327021 | F38: =IFERROR((F30*$C$6*$C$25+F31*$C$7*$D$25+F32*$C$8*$E$25)/F33,0) -> 0.55186096 | G38: =IFERROR((G30*$C$6*$C$25+G31*$C$7*$D$25+G32*$C$8*$E$25)/G33,0) -> 0.55977571 | H38: =IFERROR((H30*$C$6*$C$25+H31*$C$7*$D$25+H32*$C$8*$E$25)/H33,0) -> 0.56496316 | I38: =IFERROR((I30*$C$6*$C$25+I31*$C$7*$D$25+I32*$C$8*$E$25)/I33,0) -> 0.56989343 | J38: =IFERROR((J30*$C$6*$C$25+J31*$C$7*$D$25+J32*$C$8*$E$25)/J33,0) -> 0.57457602 | ... V38: =IFERROR((V30*$C$6*$C$25+V31*$C$7*$D$25+V32*$C$8*$E$25)/V33,0) -> 0.6265386
B39: Expected EBITDA | C39: =C34*C38 -> 78.325 | D39: =D34*D38 -> 110.37 | E39: =E34*E38 -> 156.62888 | F39: =F34*F38 -> 223.64379 | G39: =G34*G38 -> 321.03717 | H39: =H34*H38 -> 421.18665 | I39: =I34*I38 -> 553.70978 | J39: =J34*J38 -> 729.30516 | ... V39: =V34*V38 -> 9727.4812
B40: Blended CapEx (% of revenue) | C40: =IFERROR((C30*$C$6*$C$26+C31*$C$7*$D$26+C32*$C$8*$E$26)/C33,0) -> 0.2 | D40: =IFERROR((D30*$C$6*$C$26+D31*$C$7*$D$26+D32*$C$8*$E$26)/D33,0) -> 0.2 | E40: =IFERROR((E30*$C$6*$C$26+E31*$C$7*$D$26+E32*$C$8*$E$26)/E33,0) -> 0.2 | F40: =IFERROR((F30*$C$6*$C$26+F31*$C$7*$D$26+F32*$C$8*$E$26)/F33,0) -> 0.2 | G40: =IFERROR((G30*$C$6*$C$26+G31*$C$7*$D$26+G32*$C$8*$E$26)/G33,0) -> 0.2 | H40: =IFERROR((H30*$C$6*$C$26+H31*$C$7*$D$26+H32*$C$8*$E$26)/H33,0) -> 0.2 | I40: =IFERROR((I30*$C$6*$C$26+I31*$C$7*$D$26+I32*$C$8*$E$26)/I33,0) -> 0.2 | J40: =IFERROR((J30*$C$6*$C$26+J31*$C$7*$D$26+J32*$C$8*$E$26)/J33,0) -> 0.2 | ... V40: =IFERROR((V30*$C$6*$C$26+V31*$C$7*$D$26+V32*$C$8*$E$26)/V33,0) -> 0.2
B41: Expected CapEx | C41: =C34*C40 -> 29.9 | D41: =D34*D40 -> 41.34 | E41: =E34*E40 -> 57.6615 | F41: =F34*F40 -> 81.050775 | G41: =G34*G40 -> 114.70207 | H41: =H34*H40 -> 149.10234 | I41: =I34*I40 -> 194.32046 | J41: =J34*J40 -> 253.85855 | ... V41: =V34*V40 -> 3105.1498
B42: Tax on EBITDA (at Assumptions!$C$12) | C42: =MAX(0,C39)*Assumptions!$C$12 -> 16.44825 | D42: =MAX(0,D39)*Assumptions!$C$12 -> 23.1777 | E42: =MAX(0,E39)*Assumptions!$C$12 -> 32.892064 | F42: =MAX(0,F39)*Assumptions!$C$12 -> 46.965197 | G42: =MAX(0,G39)*Assumptions!$C$12 -> 67.417805 | H42: =MAX(0,H39)*Assumptions!$C$12 -> 88.449196 | I42: =MAX(0,I39)*Assumptions!$C$12 -> 116.27905 | J42: =MAX(0,J39)*Assumptions!$C$12 -> 153.15408 | ... V42: =MAX(0,V39)*Assumptions!$C$12 -> 2042.771
B43: Unlevered Free Cash Flow | C43: =C39-C42-C41 -> 31.97675 | D43: =D39-D42-D41 -> 45.8523 | E43: =E39-E42-E41 -> 66.075311 | F43: =F39-F42-F41 -> 95.627822 | G43: =G39-G42-G41 -> 138.91729 | H43: =H39-H42-H41 -> 183.63511 | I43: =I39-I42-I41 -> 243.11026 | J43: =J39-J42-J41 -> 322.29253 | ... V43: =V39-V42-V41 -> 4579.5603
B45: Scenario rationale
B46: Bear: satellite-servicing / orbital-tug demand stays niche; little IP licensing. Base: steady orbit-to-orbit logistics plus component sales and rocketry IP/know-how licensing. Bull: SpaceX becomes the default in-space logistics and manufacturing-IP provider as launch cadence scales.

Sheet X Platform
B2: XPlatform: X.com + XMoney
B3: X.com advertising, subscription rev + XMoney integration
B5: Scenario weights (from Scenario_Engine)
B6: Bear weight | C6: =Scenario_Engine!C16 -> 0.3
B7: Base weight | C7: =Scenario_Engine!D16 -> 0.5
B8: Bull weight | C8: =Scenario_Engine!E16 -> 0.2
B9: Probability of materialization | C9: =Scenario_Engine!G16 -> 0.85
B11: Substantiation & Sources
B17: Scenario assumptions (edit blue cells)
B18: Driver | C18: Bear | D18: Base | E18: Bull
B19: 2026 starting revenue ($M) | C19: 3000 | D19: 5000 | E19: 7000
B20: CAGR 2026→2030 (ramp) | C20: 0.2 | D20: 0.4 | E20: 0.5
B21: CAGR 2030→2035 (mid) | C21: 0.1 | D21: 0.2 | E21: 0.3
B22: CAGR 2035→2045 (mature) | C22: 0.1 | D22: 0.15 | E22: 0.2
B23: Mid-phase seed 2031 ($M, optional) | C23: 0 | D23: 0 | E23: 0
B24: Mature-phase seed 2036 ($M, optional) | C24: 0 | D24: 0 | E24: 0
B25: EBITDA margin | C25: 0.1 | D25: 0.15 | E25: 0.3
B26: CapEx (% of revenue) | C26: 0.1 | D26: 0.08 | E26: 0.05
B28: Revenue build ($M, by scenario)
B29: Year | C29: 2026 | D29: 2027 | E29: 2028 | F29: 2029 | G29: 2030 | H29: 2031 | I29: 2032 | J29: 2033 | K29: 2034 | L29: 2035 | M29: 2036 | N29: 2037 | O29: 2038 | P29: 2039 | Q29: 2040 | R29: 2041 | S29: 2042 | T29: 2043 | U29: 2044 | V29: 2045
B30: Bear revenue | C30: =$C$19 -> 3000 | D30: =C30*(1+$C$20) -> 3600 | E30: =D30*(1+$C$20) -> 4320 | F30: =E30*(1+$C$20) -> 5184 | G30: =F30*(1+$C$20) -> 6220.8 | H30: =IF($C$23>0,$C$23,G30*(1+$C$21)) -> 6842.88 | I30: =H30*(1+$C$21) -> 7527.168 | J30: =I30*(1+$C$21) -> 8279.8848 | K30: =J30*(1+$C$21) -> 9107.8733 | L30: =K30*(1+$C$21) -> 10018.661 | M30: =IF($C$24>0,$C$24,L30*(1+$C$22)) -> 11020.527 | N30: =M30*(1+$C$22) -> 12122.579 | O30: =N30*(1+$C$22) -> 13334.837 | P30: =O30*(1+$C$22) -> 14668.321 | Q30: =P30*(1+$C$22) -> 16135.153 | R30: =Q30*(1+$C$22) -> 17748.668 | S30: =R30*(1+$C$22) -> 19523.535 | T30: =S30*(1+$C$22) -> 21475.889 | U30: =T30*(1+$C$22) -> 23623.478 | V30: =U30*(1+$C$22) -> 25985.825
B31: Base revenue | C31: =$D$19 -> 5000 | D31: =C31*(1+$D$20) -> 7000 | E31: =D31*(1+$D$20) -> 9800 | F31: =E31*(1+$D$20) -> 13720 | G31: =F31*(1+$D$20) -> 19208 | H31: =IF($D$23>0,$D$23,G31*(1+$D$21)) -> 23049.6 | I31: =H31*(1+$D$21) -> 27659.52 | J31: =I31*(1+$D$21) -> 33191.424 | K31: =J31*(1+$D$21) -> 39829.709 | L31: =K31*(1+$D$21) -> 47795.651 | M31: =IF($D$24>0,$D$24,L31*(1+$D$22)) -> 54964.998 | N31: =M31*(1+$D$22) -> 63209.748 | O31: =N31*(1+$D$22) -> 72691.21 | P31: =O31*(1+$D$22) -> 83594.892 | Q31: =P31*(1+$D$22) -> 96134.125 | R31: =Q31*(1+$D$22) -> 110554.24 | S31: =R31*(1+$D$22) -> 127137.38 | T31: =S31*(1+$D$22) -> 146207.99 | U31: =T31*(1+$D$22) -> 168139.19 | V31: =U31*(1+$D$22) -> 193360.06
B32: Bull revenue | C32: =$E$19 -> 7000 | D32: =C32*(1+$E$20) -> 10500 | E32: =D32*(1+$E$20) -> 15750 | F32: =E32*(1+$E$20) -> 23625 | G32: =F32*(1+$E$20) -> 35437.5 | H32: =IF($E$23>0,$E$23,G32*(1+$E$21)) -> 46068.75 | I32: =H32*(1+$E$21) -> 59889.375 | J32: =I32*(1+$E$21) -> 77856.188 | K32: =J32*(1+$E$21) -> 101213.04 | L32: =K32*(1+$E$21) -> 131576.96 | M32: =IF($E$24>0,$E$24,L32*(1+$E$22)) -> 157892.35 | N32: =M32*(1+$E$22) -> 189470.82 | O32: =N32*(1+$E$22) -> 227364.98 | P32: =O32*(1+$E$22) -> 272837.98 | Q32: =P32*(1+$E$22) -> 327405.57 | R32: =Q32*(1+$E$22) -> 392886.69 | S32: =R32*(1+$E$22) -> 471464.03 | T32: =S32*(1+$E$22) -> 565756.83 | U32: =T32*(1+$E$22) -> 678908.2 | V32: =U32*(1+$E$22) -> 814689.84
B33: Scenario-weighted revenue | C33: =C30*$C$6+C31*$C$7+C32*$C$8 -> 4800 | D33: =D30*$C$6+D31*$C$7+D32*$C$8 -> 6680 | E33: =E30*$C$6+E31*$C$7+E32*$C$8 -> 9346 | F33: =F30*$C$6+F31*$C$7+F32*$C$8 -> 13140.2 | G33: =G30*$C$6+G31*$C$7+G32*$C$8 -> 18557.74 | H33: =H30*$C$6+H31*$C$7+H32*$C$8 -> 22791.414 | I33: =I30*$C$6+I31*$C$7+I32*$C$8 -> 28065.785 | J33: =J30*$C$6+J31*$C$7+J32*$C$8 -> 34650.915 | ... V33: =V30*$C$6+V31*$C$7+V32*$C$8 -> 267413.75
B34: Expected revenue (× materialization) | C34: =C33*$C$9 -> 4080 | D34: =D33*$C$9 -> 5678 | E34: =E33*$C$9 -> 7944.1 | F34: =F33*$C$9 -> 11169.17 | G34: =G33*$C$9 -> 15774.079 | H34: =H33*$C$9 -> 19372.702 | I34: =I33*$C$9 -> 23855.918 | J34: =J33*$C$9 -> 29453.278 | ... V34: =V33*$C$9 -> 227301.68
B36: Economics ($M)
B37: Year | C37: 2026 | D37: 2027 | E37: 2028 | F37: 2029 | G37: 2030 | H37: 2031 | I37: 2032 | J37: 2033 | K37: 2034 | L37: 2035 | M37: 2036 | N37: 2037 | O37: 2038 | P37: 2039 | Q37: 2040 | R37: 2041 | S37: 2042 | T37: 2043 | U37: 2044 | V37: 2045
B38: Blended EBITDA margin | C38: =IFERROR((C30*$C$6*$C$25+C31*$C$7*$D$25+C32*$C$8*$E$25)/C33,0) -> 0.184375 | D38: =IFERROR((D30*$C$6*$C$25+D31*$C$7*$D$25+D32*$C$8*$E$25)/D33,0) -> 0.18907186 | E38: =IFERROR((E30*$C$6*$C$25+E31*$C$7*$D$25+E32*$C$8*$E$25)/E33,0) -> 0.19362294 | F38: =IFERROR((F30*$C$6*$C$25+F31*$C$7*$D$25+F32*$C$8*$E$25)/F33,0) -> 0.19801982 | G38: =IFERROR((G30*$C$6*$C$25+G31*$C$7*$D$25+G32*$C$8*$E$25)/G33,0) -> 0.20225922 | H38: =IFERROR((H30*$C$6*$C$25+H31*$C$7*$D$25+H32*$C$8*$E$25)/H33,0) -> 0.20613602 | I38: =IFERROR((I30*$C$6*$C$25+I31*$C$7*$D$25+I32*$C$8*$E$25)/I33,0) -> 0.20999382 | J38: =IFERROR((J30*$C$6*$C$25+J31*$C$7*$D$25+J32*$C$8*$E$25)/J33,0) -> 0.2138219 | ... V38: =IFERROR((V30*$C$6*$C$25+V31*$C$7*$D$25+V32*$C$8*$E$25)/V33,0) -> 0.23993894
B39: Expected EBITDA | C39: =C34*C38 -> 752.25 | D39: =D34*D38 -> 1073.55 | E39: =E34*E38 -> 1538.16 | F39: =F34*F38 -> 2211.717 | G39: =G34*G38 -> 3190.4529 | H39: =H34*H38 -> 3993.4117 | I39: =I34*I38 -> 5009.5953 | J39: =J34*J38 -> 6297.7559 | ... V39: =V34*V38 -> 54538.524
B40: Blended CapEx (% of revenue) | C40: =IFERROR((C30*$C$6*$C$26+C31*$C$7*$D$26+C32*$C$8*$E$26)/C33,0) -> 0.075 | D40: =IFERROR((D30*$C$6*$C$26+D31*$C$7*$D$26+D32*$C$8*$E$26)/D33,0) -> 0.073802395 | E40: =IFERROR((E30*$C$6*$C$26+E31*$C$7*$D$26+E32*$C$8*$E$26)/E33,0) -> 0.072662101 | F40: =IFERROR((F30*$C$6*$C$26+F31*$C$7*$D$26+F32*$C$8*$E$26)/F33,0) -> 0.07157958 | G40: =IFERROR((G30*$C$6*$C$26+G31*$C$7*$D$26+G32*$C$8*$E$26)/G33,0) -> 0.070553796 | H40: =IFERROR((H30*$C$6*$C$26+H31*$C$7*$D$26+H32*$C$8*$E$26)/H33,0) -> 0.069673514 | I40: =IFERROR((I30*$C$6*$C$26+I31*$C$7*$D$26+I32*$C$8*$E$26)/I33,0) -> 0.068805828 | J40: =IFERROR((J30*$C$6*$C$26+J31*$C$7*$D$26+J32*$C$8*$E$26)/J33,0) -> 0.067952473 | ... V40: =IFERROR((V30*$C$6*$C$26+V31*$C$7*$D$26+V32*$C$8*$E$26)/V33,0) -> 0.062303737
B41: Expected CapEx | C41: =C34*C40 -> 306 | D41: =D34*D40 -> 419.05 | E41: =E34*E40 -> 577.235 | F41: =F34*F40 -> 799.4845 | G41: =G34*G40 -> 1112.9211 | H41: =H34*H40 -> 1349.7642 | I41: =I34*I40 -> 1641.4262 | J41: =J34*J40 -> 2001.4231 | ... V41: =V34*V40 -> 14161.744
B42: Tax on EBITDA (at Assumptions!$C$12) | C42: =MAX(0,C39)*Assumptions!$C$12 -> 157.9725 | D42: =MAX(0,D39)*Assumptions!$C$12 -> 225.4455 | E42: =MAX(0,E39)*Assumptions!$C$12 -> 323.0136 | F42: =MAX(0,F39)*Assumptions!$C$12 -> 464.46057 | G42: =MAX(0,G39)*Assumptions!$C$12 -> 669.99511 | H42: =MAX(0,H39)*Assumptions!$C$12 -> 838.61645 | I42: =MAX(0,I39)*Assumptions!$C$12 -> 1052.015 | J42: =MAX(0,J39)*Assumptions!$C$12 -> 1322.5287 | ... V42: =MAX(0,V39)*Assumptions!$C$12 -> 11453.09
B43: Unlevered Free Cash Flow | C43: =C39-C42-C41 -> 288.2775 | D43: =D39-D42-D41 -> 429.0545 | E43: =E39-E42-E41 -> 637.9114 | F43: =F39-F42-F41 -> 947.77193 | G43: =G39-G42-G41 -> 1407.5366 | H43: =H39-H42-H41 -> 1805.031 | I43: =I39-I42-I41 -> 2316.1541 | J43: =J39-J42-J41 -> 2973.8041 | ... V43: =V39-V42-V41 -> 28923.69
B45: Scenario rationale

Sheet Terafab
C2: Terafab — Semiconductor Manufacturing
C3: Custom chip fab in Grimes County, TX (~$55B initial CapEx). AI5/AI6 for Tesla/Optimus, D3 for orbital DCs, third-party AI accelerators
B5: Scenario weights (from Scenario_Engine)
B6: Bear weight | C6: 0.25
B7: Base weight | C7: 0.5
B8: Bull weight | C8: 0.25
B9: Probability of materialization | C9: 0.75
B11: Substantiation & Sources
B12: Bear ($0 / 2031 seed $800M): fab build slips; first wafer-out 2030+; captive demand only; no 3P sales
B13: Base ($0 / 2031 seed $3.0B): $55B fab capex commit (S-1); AI5/AI6 chips for Tesla/Optimus; D3 chips for orbital DCs; 2028 first wafer
B14: Bull ($0 / 2031 seed $10B): TSMC-class economics; 3P AI accelerator share vs NVIDIA/AMD; revenue scales rapidly post-2031 wafer-out (Bull CAGR 85% mid-phase, 45% mature — aggressive)
B15: Sources: SpaceX S-1 use-of-proceeds disclosure (May 20, 2026) $55B capex; Grimes County TX build site disclosure
B17: Scenario assumptions (edit blue cells)
B18: Driver | C18: Bear | D18: Base | E18: Bull
B19: 2026 starting revenue ($M) | C19: 0 | D19: 0 | E19: 0
B20: CAGR 2026→2030 (ramp) | C20: 0 | D20: 0 | E20: 0
B21: CAGR 2030→2035 (mid) | C21: 0.3 | D21: 0.55 | E21: 0.85
B22: CAGR 2035→2045 (mature) | C22: 0.15 | D22: 0.3 | E22: 0.45
B23: Mid-phase seed 2031 ($M, optional) | C23: 2000 | D23: 6000 | E23: 10000
B24: Mature-phase seed 2036 ($M, optional) | C24: 0 | D24: 0 | E24: 0
B25: EBITDA margin | C25: 0.22 | D25: 0.38 | E25: 0.55
B26: CapEx (% of revenue) | C26: 0.45 | D26: 0.28 | E26: 0.18
B28: Revenue build ($M, by scenario)
B29: Year | C29: 2026 | D29: 2027 | E29: 2028 | F29: 2029 | G29: 2030 | H29: 2031 | I29: 2032 | J29: 2033 | K29: 2034 | L29: 2035 | M29: 2036 | N29: 2037 | O29: 2038 | P29: 2039 | Q29: 2040 | R29: 2041 | S29: 2042 | T29: 2043 | U29: 2044 | V29: 2045
B30: Bear revenue | C30: =$C$19 -> 0 | D30: =C30*(1+$C$20) -> 0 | E30: =D30*(1+$C$20) -> 0 | F30: =E30*(1+$C$20) -> 0 | G30: =F30*(1+$C$20) -> 0 | H30: =IF($C$23>0,$C$23,G30*(1+$C$21)) -> 2000 | I30: =H30*(1+$C$21) -> 2600 | J30: =I30*(1+$C$21) -> 3380 | K30: =J30*(1+$C$21) -> 4394 | L30: =K30*(1+$C$21) -> 5712.2 | M30: =IF($C$24>0,$C$24,L30*(1+$C$22)) -> 6569.03 | N30: =M30*(1+$C$22) -> 7554.3845 | O30: =N30*(1+$C$22) -> 8687.5422 | P30: =O30*(1+$C$22) -> 9990.6735 | Q30: =P30*(1+$C$22) -> 11489.275 | R30: =Q30*(1+$C$22) -> 13212.666 | S30: =R30*(1+$C$22) -> 15194.566 | T30: =S30*(1+$C$22) -> 17473.75 | U30: =T30*(1+$C$22) -> 20094.813 | V30: =U30*(1+$C$22) -> 23109.035
B31: Base revenue | C31: =$D$19 -> 0 | D31: =C31*(1+$D$20) -> 0 | E31: =D31*(1+$D$20) -> 0 | F31: =E31*(1+$D$20) -> 0 | G31: =F31*(1+$D$20) -> 0 | H31: =IF($D$23>0,$D$23,G31*(1+$D$21)) -> 6000 | I31: =H31*(1+$D$21) -> 9300 | J31: =I31*(1+$D$21) -> 14415 | K31: =J31*(1+$D$21) -> 22343.25 | L31: =K31*(1+$D$21) -> 34632.037 | M31: =IF($D$24>0,$D$24,L31*(1+$D$22)) -> 45021.649 | N31: =M31*(1+$D$22) -> 58528.143 | O31: =N31*(1+$D$22) -> 76086.586 | P31: =O31*(1+$D$22) -> 98912.562 | Q31: =P31*(1+$D$22) -> 128586.33 | R31: =Q31*(1+$D$22) -> 167162.23 | S31: =R31*(1+$D$22) -> 217310.9 | T31: =S31*(1+$D$22) -> 282504.17 | U31: =T31*(1+$D$22) -> 367255.42 | V31: =U31*(1+$D$22) -> 477432.05
B32: Bull revenue | C32: =$E$19 -> 0 | D32: =C32*(1+$E$20) -> 0 | E32: =D32*(1+$E$20) -> 0 | F32: =E32*(1+$E$20) -> 0 | G32: =F32*(1+$E$20) -> 0 | H32: =IF($E$23>0,$E$23,G32*(1+$E$21)) -> 10000 | I32: =H32*(1+$E$21) -> 18500 | J32: =I32*(1+$E$21) -> 34225 | K32: =J32*(1+$E$21) -> 63316.25 | L32: =K32*(1+$E$21) -> 117135.06 | M32: =IF($E$24>0,$E$24,L32*(1+$E$22)) -> 169845.84 | N32: =M32*(1+$E$22) -> 246276.47 | O32: =N32*(1+$E$22) -> 357100.88 | P32: =O32*(1+$E$22) -> 517796.28 | Q32: =P32*(1+$E$22) -> 750804.6 | R32: =Q32*(1+$E$22) -> 1088666.7 | S32: =R32*(1+$E$22) -> 1578566.7 | T32: =S32*(1+$E$22) -> 2288921.7 | U32: =T32*(1+$E$22) -> 3318936.4 | V32: =U32*(1+$E$22) -> 4812457.8
